Workbook

Sheet Search Strings
A1: Inclusion Criterias | B1: Description | D1: Exclusion Criterias | E1: Description
A2: The study have a industrial focus, such as industrial automation, industrial control systems, industrial automation systems (IC1) | B2: Focus on industrial automation/ICS and closed‑loop/real‑time control contexts. | D2: The study is not available in full-text (EC1)
A3: The study describes industrial information‑exchange protocols (IC2) | D3: The study is not available in English (EC2)
A4: The study proposes a conceptual model, framework, or testbed for protocol evaluation (IC3) | D4: Unrelated domain - we are interested in automation systems (EC3)
A5: The study focuses on security or performance (IC4) | B5: Mentions security (encryption/authentication/IEC 62443/"secure communication"). Mentions performance/metrics (latency, jitter, overhead, determinism, stability). Although maybe including "performance" will limit the search results? Maybe only security and then extract any mentioned performance related metrics from the full text? | D5: Short papers with four pages or less (EC4)
A6: The study is published in a peer-reviewed publication (IC5) | D6: Secondary studies, such as other systematic literature reviews (SLRs), systematic mapping studies (SMSs), surveys etc. (EC5)
D7: Full proceedings (EC6)
D8: Exclude papers whose primary objective is not the experimental or theoretical evaluation of communication protocols, or the improvement of methods used for such evaluations. (EC7)
A14: Keywords | E14: Search Strings
A15: Focus | B15: Keyword(s) | E15: Database | F15: Search string | G15: #number matches
A16: Industrial Context (IC1) | B16: (IIoT OR "industrial iot" OR "industrial internet of things" OR "operational technology" OR "Industrial Control System" OR "Industrial Control Systems" OR "Industrial Automation System" OR "Industrial Automation Systems" OR "Industrial Automation and Control System" OR "Industrial Automation and Control Systems")
A17: Industrial information-exchange protocols (IC2) | B17: ("information‑exchange protocol" OR "information‑exchange protocols" OR "communication protocol" OR "communication protocols" OR "industrial protocol" OR "industrial protocols") | E17: IEEE | F17: (IIoT OR "industrial iot" OR "industrial internet of things" OR "operational technology" OR "Industrial Control System" OR "Industrial Control Systems" OR "Industrial Automation System" OR "Industrial Automation Systems" OR "Industrial Automation and Control System" OR "Industrial Automation and Control Systems") AND ("information‑exchange protocol" OR "information‑exchange protocols" OR "communication protocol" OR "communication protocols" OR "industrial protocol" OR "industrial protocols") AND (("performance" OR "security") NEAR/3 (evaluat* OR test* OR assess* OR compar* OR benchmark*)) AND ("conceptual model" OR "conceptual framework" OR "reference model" OR "domain model" OR "information model" OR metamodel OR ontology OR "reference architecture" OR "architecture description" OR testbed OR "test bench" OR testbench OR "experimental setup" OR "test harness" OR benchmarking OR benchmark* OR emulat* OR simulat* OR prototype OR "reference implementation" OR "software setup" OR "hardware setup") | G17: 107 | I17: https://ieeexplore-ieee-org.ep.bib.mdh.se/search/searchresult.jsp?action=search&matchBoolean=true&queryText=((IIoT%20OR%20%22industrial%20iot%22%20OR%20%22industrial%20internet%20of%20things%22%20OR%20%22operational%20technology%22%20OR%20%22Industrial%20Control%20System%22%20OR%20%22Industrial%20Control%20Systems%22%20OR%20%22Industrial%20Automation%20System%22%20OR%20%22Industrial%20Automation%20Systems%22%20OR%20%22Industrial%20Automation%20and%20Control%20System%22%20OR%20%22Industrial%20Automation%20and%20Control%20Systems%22)%20AND%20(%22information%E2%80%91exchange%20protocol%22%20OR%20%22information%E2%80%91exchange%20protocols%22%20OR%20%22communication%20protocol%22%20OR%20%22communication%20protocols%22%20OR%20%22industrial%20protocol%22%20OR%20%22industrial%20protocols%22)%20AND%20((%22performance%22%20OR%20%22security%22)%20NEAR%2F3%20(evaluat*%20OR%20test*%20OR%20assess*%20OR%20compar*%20OR%20benchmark*))%20AND%20(%22conceptual%20model%22%20OR%20%22conceptual%20framework%22%20OR%20%22reference%20model%22%20OR%20%22domain%20model%22%20OR%20%22information%20model%22%20OR%20metamodel%20OR%20ontology%20OR%20%22reference%20architecture%22%20OR%20%22architecture%20description%22%20OR%20testbed%20OR%20%22test%20bench%22%20OR%20testbench%20OR%20%22experimental%20setup%22%20OR%20%22test%20harness%22%20OR%20benchmarking%20OR%20benchmark*%20OR%20emulat*%20OR%20simulat*%20OR%20prototype%20OR%20%22reference%20implementation%22%20OR%20%22software%20setup%22%20OR%20%22hardware%20setup%22))&highlight=true&returnFacets=ALL&returnType=SEARCH&matchPubs=true&ranges=2016_2026_Year
A18: Conceptual model for protocol evaluation (IC3) | B18: ("conceptual model" OR "conceptual framework" OR "reference model" OR "domain model" OR "information model" OR metamodel OR ontology OR "reference architecture" OR "architecture description" OR testbed OR "test bench" OR testbench OR "experimental setup" OR "test harness" OR benchmarking OR benchmark* OR emulat* OR simulat* OR prototype OR "reference implementation" OR "software setup" OR "hardware setup") | E18: SCOPUS | F18: ( TITLE-ABS-KEY ( ( IIoT OR "industrial iot" OR "industrial internet of things" OR "operational technology" OR "Industrial Control System" OR "Industrial Control Systems" OR "Industrial Automation System" OR "Industrial Automation Systems" OR "Industrial Automation and Control System" OR "Industrial Automation and Control Systems" ) ) AND TITLE-ABS-KEY ( ( "information‑exchange protocol" OR "information‑exchange protocols" OR "communication protocol" OR "communication protocols" OR "industrial protocol" OR "industrial protocols" ) ) AND TITLE-ABS-KEY ( ( ( performance OR security ) W/3 ( evaluat* OR test* OR assess* OR compar* OR benchmark* ) ) ) AND TITLE-ABS-KEY ( ( "conceptual model" OR "conceptual framework" OR "reference model" OR "domain model" OR "information model" OR metamodel OR ontology OR "reference architecture" OR "architecture description" OR testbed OR "test bench" OR testbench OR "experimental setup" OR "test harness" OR benchmarking OR benchmark* OR emulat* OR simulat* OR prototype OR "reference implementation" OR "software setup" OR "hardware setup" ) ) ) AND PUBYEAR > 2015 AND PUBYEAR < 2026 AND ( LIMIT-TO ( DOCTYPE , "cp" ) OR LIMIT-TO ( DOCTYPE , "ar" ) ) | G18: 32 | I18: https://www-scopus-com.ep.bib.mdh.se/results/results.uri?sort=plf-f&src=s&sid=1349b548233cfe23a0b5a21aaad2b518&sot=a&sdt=a&cluster=scosubtype%2C%22cp%22%2Ct%2C%22ar%22%2Ct&sl=1146&s=%28+TITLE-ABS-KEY+%28+%28+IIoT+OR+%22industrial+iot%22+OR+%22industrial+internet+of+things%22+OR+%22operational+technology%22+OR+%22Industrial+Control+System%22+OR+%22Industrial+Control+Systems%22+OR+%22Industrial+Automation+System%22+OR+%22Industrial+Automation+Systems%22+OR+%22Industrial+Automation+and+Control+System%22+OR+%22Industrial+Automation+and+Control+Systems%22+%29+%29+AND+TITLE-ABS-KEY+%28+%28+%22information%26%238209%3Bexchange+protocol%22+OR+%22information%26%238209%3Bexchange+protocols%22+OR+%22communication+protocol%22+OR+%22communication+protocols%22+OR+%22industrial+protocol%22+OR+%22industrial+protocols%22+%29+%29+AND+TITLE-ABS-KEY+%28+%28+%28+performance+OR+security+%29+W%2F3+%28+evaluat*+OR+test*+OR+assess*+OR+compar*+OR+benchmark*+%29+%29+%29+AND+TITLE-ABS-KEY+%28+%28+%22conceptual+model%22+OR+%22conceptual+framework%22+OR+%22reference+model%22+OR+%22domain+model%22+OR+%22information+model%22+OR+metamodel+OR+ontology+OR+%22reference+architecture%22+OR+%22architecture+description%22+OR+testbed+OR+%22test+bench%22+OR+testbench+OR+%22experimental+setup%22+OR+%22test+harness%22+OR+benchmarking+OR+benchmark*+OR+emulat*+OR+simulat*+OR+prototype+OR+%22reference+implementation%22+OR+%22software+setup%22+OR+%22hardware+setup%22+%29+%29+%29+AND+PUBYEAR+%26gt%3B+2015+AND+PUBYEAR+%26lt%3B+2026&origin=searchadvanced&editSaveSearch=&txGid=766958fa8566bdc9fd88f0e955088426&sessionSearchId=1349b548233cfe23a0b5a21aaad2b518&limit=10
A19: The study focuses on security or performance (IC4) | B19: (("performance" OR "security") NEAR/3 (evaluat* OR test* OR assess* OR compar* OR benchmark*)) | E19: Web Of Science | F19: TS=((IIoT OR "industrial iot" OR "industrial internet of things" OR "operational technology" OR "industrial control system" OR "industrial control systems" OR "industrial automation system" OR "industrial automation systems" OR "industrial automation and control system" OR "industrial automation and control systems") AND ("information exchange protocol" OR "information exchange protocols" OR "communication protocol" OR "communication protocols" OR "industrial protocol" OR "industrial protocols") AND ((performance OR security) NEAR/3 (evaluat* OR test* OR assess* OR compar* OR benchmark*)) AND ("conceptual model" OR "conceptual framework" OR "reference model" OR "domain model" OR "information model" OR metamodel OR ontology OR "reference architecture" OR "architecture description" OR testbed OR "test bench" OR testbench OR "experimental setup" OR "test harness" OR benchmarking OR benchmark* OR emulat* OR simulat* OR prototype OR "reference implementation" OR "software setup" OR "hardware setup") ) | G19: 18 | I19: https://www.webofscience.com/wos/woscc/summary/20f4f276-9994-4d06-9ec7-00cb6cdb4fbd-019ec4b417/relevance/1
E20: ACM DL | F20: [[Abstract: iiot] OR [Abstract: "industrial iot"] OR [Abstract: "industrial internet of things"] OR [Abstract: "industrial control system"] OR [Abstract: "industrial control systems"] OR [Abstract: "industrial automation system"] OR [Abstract: "industrial automation systems"] OR [Abstract: "industrial automation and control system"] OR [Abstract: "industrial automation and control systems"]] AND [[Abstract: "information exchange protocol"] OR [Abstract: "information exchange protocols"] OR [Abstract: "communication protocol"] OR [Abstract: "communication protocols"] OR [Abstract: "industrial protocol"] OR [Abstract: "industrial protocols"]] AND [[Abstract: performance] OR [Abstract: security]] AND [[Abstract: evaluat*] OR [Abstract: test*] OR [Abstract: assess*] OR [Abstract: compar*] OR [Abstract: benchmark*]] AND [[Abstract: "conceptual model"] OR [Abstract: "conceptual framework"] OR [Abstract: "reference model"] OR [Abstract: "domain model"] OR [Abstract: "information model"] OR [Abstract: metamodel] OR [Abstract: ontology] OR [Abstract: "reference architecture"] OR [Abstract: "architecture description"] OR [Abstract: testbed] OR [Abstract: "test bench"] OR [Abstract: testbench] OR [Abstract: "experimental setup"] OR [Abstract: "test harness"] OR [Abstract: benchmarking] OR [Abstract: benchmark*] OR [Abstract: emulat*] OR [Abstract: simulat*] OR [Abstract: prototype] OR [Abstract: "reference implementation"] OR [Abstract: "software setup"] OR [Abstract: "hardware setup"]] | G20: 41 | I20: https://dl-acm-org.ep.bib.mdh.se/action/doSearch?fillQuickSearch=false&target=advanced&expand=dl&field1=Abstract&text1=%28+++%28IIoT+OR+%22industrial+iot%22+OR+%22industrial+internet+of+things%22++++OR+%22Industrial+Control+System%22+OR+%22Industrial+Control+Systems%22++++OR+%22Industrial+Automation+System%22+OR+%22Industrial+Automation+Systems%22++++OR+%22Industrial+Automation+and+Control+System%22+OR+%22Industrial+Automation+and+Control+Systems%22%29+++AND+++%28%22information+exchange+protocol%22+OR+%22information+exchange+protocols%22++++OR+%22communication+protocol%22+OR+%22communication+protocols%22++++OR+%22industrial+protocol%22+OR+%22industrial+protocols%22%29+++AND+++%28%28performance+OR+security%29+AND+%28evaluat*+OR+test*+OR+assess*+OR+compar*+OR+benchmark*%29%29+++AND+++%28%22conceptual+model%22+OR+%22conceptual+framework%22+OR+%22reference+model%22+OR+%22domain+model%22++++OR+%22information+model%22+OR+metamodel+OR+ontology+OR+%22reference+architecture%22++++OR+%22architecture+description%22+OR+testbed+OR+%22test+bench%22+OR+testbench++++OR+%22experimental+setup%22+OR+%22test+harness%22+OR+benchmarking+OR+benchmark*++++OR+emulat*+OR+simulat*+OR+prototype+OR+%22reference+implementation%22++++OR+%22software+setup%22+OR+%22hardware+setup%22%29+%29&startPage=0&pageSize=50

Sheet Results before duplicates
A1: Identifier | B1: Database | C1: Title | D1: Number of pages
A2: 0 | B2: IEEE | C2: =HYPERLINK(IEEE_NEW!$P2, IEEE_NEW!$A2) -> Towards a modular security testing framework for industrial automation and control systems: ISuTest | D2: =IEEE_NEW!$AC2 -> 5
A3: 1 | B3: IEEE | C3: =HYPERLINK(IEEE_NEW!$P3, IEEE_NEW!$A3) -> VTET: A Virtual Industrial Control System Testbed for Cyber Security Research | D3: =IEEE_NEW!$AC3 -> 7
A4: 2 | B4: IEEE | C4: =HYPERLINK(IEEE_NEW!$P4, IEEE_NEW!$A4) -> The SAir-IIoT Cyber Testbed as a Service: A Novel Cybertwins Architecture in IIoT-Based Smart Airports | D4: =IEEE_NEW!$AC4 -> 14
A5: 3 | B5: IEEE | C5: =HYPERLINK(IEEE_NEW!$P5, IEEE_NEW!$A5) -> Test Bed Development for a Security Engineered SCADA Laboratory | D5: =IEEE_NEW!$AC5 -> 5
A6: 4 | B6: IEEE | C6: =HYPERLINK(IEEE_NEW!$P6, IEEE_NEW!$A6) -> Industrial Internet of Things (IIoT): Testbed and Datasets for CyberSecurity and Digital Forensics | D6: =IEEE_NEW!$AC6 -> 10
A7: 5 | B7: IEEE | C7: =HYPERLINK(IEEE_NEW!$P7, IEEE_NEW!$A7) -> Improving Substation Network Security with DevSecOps and AIOps | D7: =IEEE_NEW!$AC7 -> 6
A8: 6 | B8: IEEE | C8: =HYPERLINK(IEEE_NEW!$P8, IEEE_NEW!$A8) -> Performance Evaluation of MQTT and CoAP Communication Protocols in IIoT for Electrical Substations Based on the IEC 61850 Standard | D8: =IEEE_NEW!$AC8 -> 6
A9: 7 | B9: IEEE | C9: =HYPERLINK(IEEE_NEW!$P9, IEEE_NEW!$A9) -> Behavior and Vulnerability Assessment of Drones-Enabled Industrial Internet of Things (IIoT) | D9: =IEEE_NEW!$AC9 -> 16
A10: 8 | B10: IEEE | C10: =HYPERLINK(IEEE_NEW!$P10, IEEE_NEW!$A10) -> Architecture of Modular System for Assessing Security of Telemetry Information Transmission System | D10: =IEEE_NEW!$AC10 -> 6
A11: 9 | B11: IEEE | C11: =HYPERLINK(IEEE_NEW!$P11, IEEE_NEW!$A11) -> Developing a Security Testbed for Industrial Internet of Things | D11: =IEEE_NEW!$AC11 -> 16
A12: 10 | B12: IEEE | C12: =HYPERLINK(IEEE_NEW!$P12, IEEE_NEW!$A12) -> SWaP: A Water Process Testbed for ICS Security Research | D12: =IEEE_NEW!$AC12 -> 4
A13: 11 | B13: IEEE | C13: =HYPERLINK(IEEE_NEW!$P13, IEEE_NEW!$A13) -> A Comparative Analysis of Application Layer Protocols Within an Industrial Internet of Things Monitoring System | D13: =IEEE_NEW!$AC13 -> 6
... A101: 99 | B101: IEEE | C101: =HYPERLINK(IEEE_NEW!$P101, IEEE_NEW!$A101) -> Energy-Efficient Wireless Sensor Networks Optimization using Deep Q-Networks for Smart Energy Applications | D101: =IEEE_NEW!$AC101 -> 5
A102: 100 | B102: ACM DL | C102: =HYPERLINK(ACM_NEW!$D2, ACM_NEW!$B2) -> ICSNet: A Hybrid-Interaction Honeynet for Industrial Control Systems | D102: =ACM_NEW!$H2 -> 12
A103: 101 | B103: ACM DL | C103: =HYPERLINK(ACM_NEW!$D3, ACM_NEW!$B3) -> RTPL: A Real-Time Communication Protocol for LoRa Network | D103: =ACM_NEW!$H3 -> 31
A104: 102 | B104: ACM DL | C104: =HYPERLINK(ACM_NEW!$D4, ACM_NEW!$B4) -> EmuFlex: A Flexible OT Testbed for Security Experiments with OPC UA | D104: =ACM_NEW!$H4 -> 9
A105: 103 | B105: ACM DL | C105: =HYPERLINK(ACM_NEW!$D5, ACM_NEW!$B5) -> A Comprehensive Survey on Interoperability for IIoT: Taxonomy, Standards, and Future Directions | D105: =ACM_NEW!$H5 -> 35
A106: 104 | B106: ACM DL | C106: =HYPERLINK(ACM_NEW!$D6, ACM_NEW!$B6) -> On Practical Realization of Evasion Attacks for Industrial Control Systems | D106: =ACM_NEW!$H6 -> 17
A107: 105 | B107: ACM DL | C107: =HYPERLINK(ACM_NEW!$D7, ACM_NEW!$B7) -> An Industrial Internet of Things (IIoT) platform for intelligent wind turbine gearbox fault detection with automatic annotation | D107: =ACM_NEW!$H7 -> 5
A108: 106 | B108: ACM DL | C108: =HYPERLINK(ACM_NEW!$D8, ACM_NEW!$B8) -> Examining the Suitability of Stream Ciphers for Modbus-TCP Encryption on Resource Constrained Devices | D108: =ACM_NEW!$H8 -> 7
A109: 107 | B109: ACM DL | C109: =HYPERLINK(ACM_NEW!$D9, ACM_NEW!$B9) -> HoneyICS: A High-interaction Physics-aware Honeynet for Industrial Control Systems | D109: =ACM_NEW!$H9 -> 10
A110: 108 | B110: ACM DL | C110: =HYPERLINK(ACM_NEW!$D10, ACM_NEW!$B10) -> The PRECINCT Ecosystem Platform for Critical Infrastructure Protection: Architecture, Deployment and Transferability | D110: =ACM_NEW!$H10 -> 8
A111: 109 | B111: ACM DL | C111: =HYPERLINK(ACM_NEW!$D11, ACM_NEW!$B11) -> Controller-in-the-Middle: Attacks on Software Defined Networks in Industrial Control Systems | D111: =ACM_NEW!$H11 -> 6
A112: 110 | B112: ACM DL | C112: =HYPERLINK(ACM_NEW!$D12, ACM_NEW!$B12) -> Identifying key attacks on an IEEE 9-Bus System by leveraging the MITRE ATT&amp;CK ICS Matrix | D112: =ACM_NEW!$H12 -> 8
A113: 111 | B113: ACM DL | C113: =HYPERLINK(ACM_NEW!$D13, ACM_NEW!$B13) -> SoK: A Taxonomy for Contrasting Industrial Control Systems Asset Discovery Tools | D113: =ACM_NEW!$H13 -> 12
... A140: 138 | B140: ACM DL | C140: =HYPERLINK(ACM_NEW!$D40, ACM_NEW!$B40) -> Sentinel: A Robust Intrusion Detection System for IoT Networks Using Kernel-Level System Information | D140: =ACM_NEW!$H40 -> 14
A141: 139 | B141: SCOPUS | C141: =HYPERLINK(SCOPUS_NEW!$N2, SCOPUS_NEW!$D2) -> Edge Computing-Enabled Predictive Maintenance System with Multi-Protocol RTU Integration for Industry 4.0 Applications | D141: =SCOPUS_NEW!$V2 -> 8
A142: 140 | B142: SCOPUS | C142: =HYPERLINK(SCOPUS_NEW!$N3, SCOPUS_NEW!$D3) -> Cyber4OT dataset: Network traces for cyber-security vulnerability evaluation in industrial control systems | D142: =SCOPUS_NEW!$V3 -> 0
A143: 141 | B143: SCOPUS | C143: =HYPERLINK(SCOPUS_NEW!$N4, SCOPUS_NEW!$D4) -> Exponential Backoff and Its Security Implications for Safety-Critical OT Protocols over TCP/IP Networks | D143: =SCOPUS_NEW!$V4 -> 0
A144: 142 | B144: SCOPUS | C144: =HYPERLINK(SCOPUS_NEW!$N5, SCOPUS_NEW!$D5) -> TSCH in Edge IoT: A Comprehensive Survey of Research Challenges | D144: =SCOPUS_NEW!$V5 -> 0
A145: 143 | B145: SCOPUS | C145: =HYPERLINK(SCOPUS_NEW!$N6, SCOPUS_NEW!$D6) -> Unleashing the Potential of Industrial IoT and Industry 5.0 | D145: =SCOPUS_NEW!$V6 -> 0
A146: 144 | B146: SCOPUS | C146: =HYPERLINK(SCOPUS_NEW!$N7, SCOPUS_NEW!$D7) -> Energy-Efficient Wireless Sensor Networks Optimization using Deep Q-Networks for Smart Energy Applications | D146: =SCOPUS_NEW!$V7 -> 4
A147: 145 | B147: SCOPUS | C147: =HYPERLINK(SCOPUS_NEW!$N8, SCOPUS_NEW!$D8) -> Methodology for Assessing Existing Vulnerabilities in Modbus Protocol | D147: =SCOPUS_NEW!$V8 -> 10
A148: 146 | B148: SCOPUS | C148: =HYPERLINK(SCOPUS_NEW!$N9, SCOPUS_NEW!$D9) -> IoTForge Pro: A Security Testbed for Generating Intrusion Dataset for Industrial IoT | D148: =SCOPUS_NEW!$V9 -> 7
A149: 147 | B149: SCOPUS | C149: =HYPERLINK(SCOPUS_NEW!$N10, SCOPUS_NEW!$D10) -> Simulation and modeling of a robust cybersecurity system for next-generation manufacturing execution | D149: =SCOPUS_NEW!$V10 -> 0
A150: 148 | B150: SCOPUS | C150: =HYPERLINK(SCOPUS_NEW!$N11, SCOPUS_NEW!$D11) -> Securing industrial control systems: Developing a SCADA/IoT test bench and evaluating lightweight cipher performance on hardware simulator | D150: =SCOPUS_NEW!$V11 -> 0
A151: 149 | B151: SCOPUS | C151: =HYPERLINK(SCOPUS_NEW!$N12, SCOPUS_NEW!$D12) -> OPC-UA in interoperability - a performance comparative testing | D151: =SCOPUS_NEW!$V12 -> 5
A152: 150 | B152: SCOPUS | C152: =HYPERLINK(SCOPUS_NEW!$N13, SCOPUS_NEW!$D13) -> A Comparative Analysis of Application Layer Protocols Within an Industrial Internet of Things Monitoring System | D152: =SCOPUS_NEW!$V13 -> 0
... A170: 168 | B170: SCOPUS | C170: =HYPERLINK(SCOPUS_NEW!$N31, SCOPUS_NEW!$D31) -> End-to-End Delay Evaluation of Industrial Automation Systems Based on EtherCAT | D170: =SCOPUS_NEW!$V31 -> 7
A171: 169 | B171: Web of Science | C171: =HYPERLINK(WoS_NEW!$BF2, WoS_NEW!$I2) -> SEAG: A novel dynamic security risk assessment method for industrial control systems with consideration of social engineering | D171: =WoS_NEW!$BW2 -> 0
A172: 170 | B172: Web of Science | C172: =HYPERLINK(WoS_NEW!$BF3, WoS_NEW!$I3) -> Developing a Security Testbed for Industrial Internet of Things | D172: =WoS_NEW!$BW3 -> 15
A173: 171 | B173: Web of Science | C173: =HYPERLINK(WoS_NEW!$BF4, WoS_NEW!$I4) -> Securing industrial control systems: Developing a SCADA/IoT test bench and evaluating lightweight cipher performance on hardware simulator | D173: =WoS_NEW!$BW4 -> 0
A174: 172 | B174: Web of Science | C174: =HYPERLINK(WoS_NEW!$BF5, WoS_NEW!$I5) -> IoTForge Pro: A Security Testbed for Generating Intrusion Dataset for Industrial IoT | D174: =WoS_NEW!$BW5 -> 7
A175: 173 | B175: Web of Science | C175: =HYPERLINK(WoS_NEW!$BF6, WoS_NEW!$I6) -> The SAir-IIoT Cyber Testbed as a Service: A Novel Cybertwins Architecture in IIoT-Based Smart Airports | D175: =WoS_NEW!$BW6 -> 13
A176: 174 | B176: Web of Science | C176: =HYPERLINK(WoS_NEW!$BF7, WoS_NEW!$I7) -> End-to-end Delay Evaluation of Industrial Automation Systems based on EtherCAT | D176: =WoS_NEW!$BW7 -> 7
A177: 175 | B177: Web of Science | C177: =HYPERLINK(WoS_NEW!$BF8, WoS_NEW!$I8) -> Towards Performance Benchmarking of Cyclic OPC UA PubSub over TSN | D177: =WoS_NEW!$BW8 -> 0
A178: 176 | B178: Web of Science | C178: =HYPERLINK(WoS_NEW!$BF9, WoS_NEW!$I9) -> A Comparative Analysis of Application Layer Protocols within an Industrial Internet of Things Monitoring System | D178: =WoS_NEW!$BW9 -> 0
A179: 177 | B179: Web of Science | C179: =HYPERLINK(WoS_NEW!$BF10, WoS_NEW!$I10) -> Holistic Risk Assessment in Industrial Control Systems: Combining Multiple Bayesian Networks with Multi-Criteria Decision Making | D179: =WoS_NEW!$BW10 -> 5
A180: 178 | B180: Web of Science | C180: =HYPERLINK(WoS_NEW!$BF11, WoS_NEW!$I11) -> Performance Evaluation and Modeling of an Industrial Application-Layer Firewall | D180: =WoS_NEW!$BW11 -> 11
A181: 179 | B181: Web of Science | C181: =HYPERLINK(WoS_NEW!$BF12, WoS_NEW!$I12) -> A Performance Analysis of Internet of Things Networking Protocols: Evaluating MQTT, CoAP, OPC UA | D181: =WoS_NEW!$BW12 -> 0
A182: 180 | B182: Web of Science | C182: =HYPERLINK(WoS_NEW!$BF13, WoS_NEW!$I13) -> Secure Sensor Prototype Using Hardware Security Modules and Trusted Execution Environments in a Blockchain Application: Wine Logistic Use Case | D182: =WoS_NEW!$BW13 -> 0
... A188: 186 | B188: Web of Science | C188: =HYPERLINK(WoS_NEW!$BF19, WoS_NEW!$I19) -> Simulation and modeling of a robust cybersecurity system for next-generation manufacturing execution | D188: =WoS_NEW!$BW19 -> 0
A189: 187 | B189: IEEE | C189: =HYPERLINK(IEEE_NEW!$P102, IEEE_NEW!$A102) -> A Testbed for Evaluating Performance and Cybersecurity Implications of IEC-61850 GOOSE Hardware Implementations | D189: =IEEE_NEW!$AC102 -> 6
A190: 188 | B190: IEEE | C190: =HYPERLINK(IEEE_NEW!$P103, IEEE_NEW!$A103) -> Benchmarking Cloud-Based SCADA System | D190: =IEEE_NEW!$AC103 -> 8
A191: 189 | B191: IEEE | C191: =HYPERLINK(IEEE_NEW!$P104, IEEE_NEW!$A104) -> Implementing a performant security control for Industrial Ethernet | D191: =IEEE_NEW!$AC104 -> 4
A192: 190 | B192: IEEE | C192: =HYPERLINK(IEEE_NEW!$P105, IEEE_NEW!$A105) -> Passive Device Fingerprinting for OT Networks Using Byte Histograms | D192: =IEEE_NEW!$AC105 -> 6
A193: 191 | B193: IEEE | C193: =HYPERLINK(IEEE_NEW!$P106, IEEE_NEW!$A106) -> Safety and Security: A Field of Tension in Industrial Practice | D193: =IEEE_NEW!$AC106 -> 7
A194: 192 | B194: IEEE | C194: =HYPERLINK(IEEE_NEW!$P107, IEEE_NEW!$A107) -> The importance of testing Smart Grid IEDs against security vulnerabilities | D194: =IEEE_NEW!$AC107 -> 21
A195: 193 | B195: IEEE | C195: =HYPERLINK(IEEE_NEW!$P108, IEEE_NEW!$A108) -> Virtual PLC in Industrial Edge Platform: Performance Evaluation of Supervision and Control Communication | D195: =IEEE_NEW!$AC108 -> 10
A196: 194 | B196: SCOPUS | C196: =HYPERLINK(SCOPUS_NEW!$N32, SCOPUS_NEW!$D32) -> A Testbed for Evaluating Performance and Cybersecurity Implications of IEC-61850 GOOSE Hardware Implementations | D196: =SCOPUS_NEW!$V32 -> 0
A197: 195 | B197: SCOPUS | C197: =HYPERLINK(SCOPUS_NEW!$N33, SCOPUS_NEW!$D33) -> Integrity Enhancing Protocols: Performance and Recommendations for Nuclear Systems | D197: =SCOPUS_NEW!$V33 -> 10
A198: 196 | B198: ACM DL | C198: =HYPERLINK(ACM_NEW!$D41, ACM_NEW!$B41) -> Identification of industrial devices based on payload | D198: =ACM_NEW!$H41 -> 9
A199: 197 | B199: ACM DL | C199: =HYPERLINK(ACM_NEW!$D42, ACM_NEW!$B42) -> Research on the realization of distance education practical training courses based on digital twin technology | D199: =ACM_NEW!$H42 -> 7

Sheet Results after duplicates
A1: Identifier | B1: Database | C1: Title | D1: Number of pages
A2: 0 | B2: IEEE | C2: =HYPERLINK(IEEE_NEW!$P2, IEEE_NEW!$A2) -> Towards a modular security testing framework for industrial automation and control systems: ISuTest | D2: =IEEE_NEW!$AC2 -> 5
A3: 1 | B3: IEEE | C3: =HYPERLINK(IEEE_NEW!$P3, IEEE_NEW!$A3) -> VTET: A Virtual Industrial Control System Testbed for Cyber Security Research | D3: =IEEE_NEW!$AC3 -> 7
A4: 2 | B4: IEEE | C4: =HYPERLINK(IEEE_NEW!$P4, IEEE_NEW!$A4) -> The SAir-IIoT Cyber Testbed as a Service: A Novel Cybertwins Architecture in IIoT-Based Smart Airports | D4: =IEEE_NEW!$AC4 -> 14
A5: 3 | B5: IEEE | C5: =HYPERLINK(IEEE_NEW!$P5, IEEE_NEW!$A5) -> Test Bed Development for a Security Engineered SCADA Laboratory | D5: =IEEE_NEW!$AC5 -> 5
A6: 4 | B6: IEEE | C6: =HYPERLINK(IEEE_NEW!$P6, IEEE_NEW!$A6) -> Industrial Internet of Things (IIoT): Testbed and Datasets for CyberSecurity and Digital Forensics | D6: =IEEE_NEW!$AC6 -> 10
A7: 5 | B7: IEEE | C7: =HYPERLINK(IEEE_NEW!$P7, IEEE_NEW!$A7) -> Improving Substation Network Security with DevSecOps and AIOps | D7: =IEEE_NEW!$AC7 -> 6
A8: 6 | B8: IEEE | C8: =HYPERLINK(IEEE_NEW!$P8, IEEE_NEW!$A8) -> Performance Evaluation of MQTT and CoAP Communication Protocols in IIoT for Electrical Substations Based on the IEC 61850 Standard | D8: =IEEE_NEW!$AC8 -> 6
A9: 7 | B9: IEEE | C9: =HYPERLINK(IEEE_NEW!$P9, IEEE_NEW!$A9) -> Behavior and Vulnerability Assessment of Drones-Enabled Industrial Internet of Things (IIoT) | D9: =IEEE_NEW!$AC9 -> 16
A10: 8 | B10: IEEE | C10: =HYPERLINK(IEEE_NEW!$P10, IEEE_NEW!$A10) -> Architecture of Modular System for Assessing Security of Telemetry Information Transmission System | D10: =IEEE_NEW!$AC10 -> 6
A11: 9 | B11: IEEE | C11: =HYPERLINK(IEEE_NEW!$P11, IEEE_NEW!$A11) -> Developing a Security Testbed for Industrial Internet of Things | D11: =IEEE_NEW!$AC11 -> 16
A12: 10 | B12: IEEE | C12: =HYPERLINK(IEEE_NEW!$P12, IEEE_NEW!$A12) -> SWaP: A Water Process Testbed for ICS Security Research | D12: =IEEE_NEW!$AC12 -> 4
A13: 11 | B13: IEEE | C13: =HYPERLINK(IEEE_NEW!$P13, IEEE_NEW!$A13) -> A Comparative Analysis of Application Layer Protocols Within an Industrial Internet of Things Monitoring System | D13: =IEEE_NEW!$AC13 -> 6
... A101: 99 | B101: IEEE | C101: =HYPERLINK(IEEE_NEW!$P101, IEEE_NEW!$A101) -> Energy-Efficient Wireless Sensor Networks Optimization using Deep Q-Networks for Smart Energy Applications | D101: =IEEE_NEW!$AC101 -> 5
A102: 100 | B102: ACM DL | C102: =HYPERLINK(ACM_NEW!$D2, ACM_NEW!$B2) -> ICSNet: A Hybrid-Interaction Honeynet for Industrial Control Systems | D102: =ACM_NEW!$H2 -> 12
A103: 101 | B103: ACM DL | C103: =HYPERLINK(ACM_NEW!$D3, ACM_NEW!$B3) -> RTPL: A Real-Time Communication Protocol for LoRa Network | D103: =ACM_NEW!$H3 -> 31
A104: 102 | B104: ACM DL | C104: =HYPERLINK(ACM_NEW!$D4, ACM_NEW!$B4) -> EmuFlex: A Flexible OT Testbed for Security Experiments with OPC UA | D104: =ACM_NEW!$H4 -> 9
A105: 103 | B105: ACM DL | C105: =HYPERLINK(ACM_NEW!$D5, ACM_NEW!$B5) -> A Comprehensive Survey on Interoperability for IIoT: Taxonomy, Standards, and Future Directions | D105: =ACM_NEW!$H5 -> 35
A106: 104 | B106: ACM DL | C106: =HYPERLINK(ACM_NEW!$D6, ACM_NEW!$B6) -> On Practical Realization of Evasion Attacks for Industrial Control Systems | D106: =ACM_NEW!$H6 -> 17
A107: 105 | B107: ACM DL | C107: =HYPERLINK(ACM_NEW!$D7, ACM_NEW!$B7) -> An Industrial Internet of Things (IIoT) platform for intelligent wind turbine gearbox fault detection with automatic annotation | D107: =ACM_NEW!$H7 -> 5
A108: 106 | B108: ACM DL | C108: =HYPERLINK(ACM_NEW!$D8, ACM_NEW!$B8) -> Examining the Suitability of Stream Ciphers for Modbus-TCP Encryption on Resource Constrained Devices | D108: =ACM_NEW!$H8 -> 7
A109: 107 | B109: ACM DL | C109: =HYPERLINK(ACM_NEW!$D9, ACM_NEW!$B9) -> HoneyICS: A High-interaction Physics-aware Honeynet for Industrial Control Systems | D109: =ACM_NEW!$H9 -> 10
A110: 108 | B110: ACM DL | C110: =HYPERLINK(ACM_NEW!$D10, ACM_NEW!$B10) -> The PRECINCT Ecosystem Platform for Critical Infrastructure Protection: Architecture, Deployment and Transferability | D110: =ACM_NEW!$H10 -> 8
A111: 109 | B111: ACM DL | C111: =HYPERLINK(ACM_NEW!$D11, ACM_NEW!$B11) -> Controller-in-the-Middle: Attacks on Software Defined Networks in Industrial Control Systems | D111: =ACM_NEW!$H11 -> 6
A112: 110 | B112: ACM DL | C112: =HYPERLINK(ACM_NEW!$D12, ACM_NEW!$B12) -> Identifying key attacks on an IEEE 9-Bus System by leveraging the MITRE ATT&amp;CK ICS Matrix | D112: =ACM_NEW!$H12 -> 8
A113: 111 | B113: ACM DL | C113: =HYPERLINK(ACM_NEW!$D13, ACM_NEW!$B13) -> SoK: A Taxonomy for Contrasting Industrial Control Systems Asset Discovery Tools | D113: =ACM_NEW!$H13 -> 12
... A140: 138 | B140: ACM DL | C140: =HYPERLINK(ACM_NEW!$D40, ACM_NEW!$B40) -> Sentinel: A Robust Intrusion Detection System for IoT Networks Using Kernel-Level System Information | D140: =ACM_NEW!$H40 -> 14
A141: 139 | B141: SCOPUS | C141: =HYPERLINK(SCOPUS_NEW!$N2, SCOPUS_NEW!$D2) -> Edge Computing-Enabled Predictive Maintenance System with Multi-Protocol RTU Integration for Industry 4.0 Applications | D141: =SCOPUS_NEW!$V2 -> 8
A142: 140 | B142: SCOPUS | C142: =HYPERLINK(SCOPUS_NEW!$N3, SCOPUS_NEW!$D3) -> Cyber4OT dataset: Network traces for cyber-security vulnerability evaluation in industrial control systems | D142: =SCOPUS_NEW!$V3 -> 0
A143: 141 | B143: SCOPUS | C143: =HYPERLINK(SCOPUS_NEW!$N4, SCOPUS_NEW!$D4) -> Exponential Backoff and Its Security Implications for Safety-Critical OT Protocols over TCP/IP Networks | D143: =SCOPUS_NEW!$V4 -> 0
A144: 142 | B144: SCOPUS | C144: =HYPERLINK(SCOPUS_NEW!$N5, SCOPUS_NEW!$D5) -> TSCH in Edge IoT: A Comprehensive Survey of Research Challenges | D144: =SCOPUS_NEW!$V5 -> 0
A145: 145 | B145: SCOPUS | C145: =HYPERLINK(SCOPUS_NEW!$N8, SCOPUS_NEW!$D8) -> Methodology for Assessing Existing Vulnerabilities in Modbus Protocol | D145: =SCOPUS_NEW!$V8 -> 10
A146: 147 | B146: SCOPUS | C146: =HYPERLINK(SCOPUS_NEW!$N10, SCOPUS_NEW!$D10) -> Simulation and modeling of a robust cybersecurity system for next-generation manufacturing execution | D146: =SCOPUS_NEW!$V10 -> 0
A147: 148 | B147: SCOPUS | C147: =HYPERLINK(SCOPUS_NEW!$N11, SCOPUS_NEW!$D11) -> Securing industrial control systems: Developing a SCADA/IoT test bench and evaluating lightweight cipher performance on hardware simulator | D147: =SCOPUS_NEW!$V11 -> 0
A148: 149 | B148: SCOPUS | C148: =HYPERLINK(SCOPUS_NEW!$N12, SCOPUS_NEW!$D12) -> OPC-UA in interoperability - a performance comparative testing | D148: =SCOPUS_NEW!$V12 -> 5
A149: 153 | B149: SCOPUS | C149: =HYPERLINK(SCOPUS_NEW!$N16, SCOPUS_NEW!$D16) -> SEAG: A novel dynamic security risk assessment method for industrial control systems with consideration of social engineering | D149: =SCOPUS_NEW!$V16 -> 0
A150: 154 | B150: SCOPUS | C150: =HYPERLINK(SCOPUS_NEW!$N17, SCOPUS_NEW!$D17) -> Secure Sensor Prototype Using Hardware Security Modules and Trusted Execution Environments in a Blockchain Application: Wine Logistic Use Case | D150: =SCOPUS_NEW!$V17 -> 0
A151: 162 | B151: SCOPUS | C151: =HYPERLINK(SCOPUS_NEW!$N25, SCOPUS_NEW!$D25) -> A performance analysis of internet of things networking protocols: Evaluating MQTT, CoAP, OPC UA | D151: =SCOPUS_NEW!$V25 -> 0
A152: 164 | B152: SCOPUS | C152: =HYPERLINK(SCOPUS_NEW!$N27, SCOPUS_NEW!$D27) -> Security Transformation Technology for Electricity Metering Communication Protocol; 电能计量用通信规约安全改造技术 | D152: =SCOPUS_NEW!$V27 -> 7
A153: 166 | B153: SCOPUS | C153: =HYPERLINK(SCOPUS_NEW!$N29, SCOPUS_NEW!$D29) -> SCADA Testbed Implementation, Attacks, and Security Solutions | D153: =SCOPUS_NEW!$V29 -> 19
A154: 187 | B154: IEEE | C154: =HYPERLINK(IEEE_NEW!$P102, IEEE_NEW!$A102) -> A Testbed for Evaluating Performance and Cybersecurity Implications of IEC-61850 GOOSE Hardware Implementations | D154: =IEEE_NEW!$AC102 -> 6
A155: 188 | B155: IEEE | C155: =HYPERLINK(IEEE_NEW!$P103, IEEE_NEW!$A103) -> Benchmarking Cloud-Based SCADA System | D155: =IEEE_NEW!$AC103 -> 8
A156: 189 | B156: IEEE | C156: =HYPERLINK(IEEE_NEW!$P104, IEEE_NEW!$A104) -> Implementing a performant security control for Industrial Ethernet | D156: =IEEE_NEW!$AC104 -> 4
A157: 190 | B157: IEEE | C157: =HYPERLINK(IEEE_NEW!$P105, IEEE_NEW!$A105) -> Passive Device Fingerprinting for OT Networks Using Byte Histograms | D157: =IEEE_NEW!$AC105 -> 6
A158: 191 | B158: IEEE | C158: =HYPERLINK(IEEE_NEW!$P106, IEEE_NEW!$A106) -> Safety and Security: A Field of Tension in Industrial Practice | D158: =IEEE_NEW!$AC106 -> 7
A159: 192 | B159: IEEE | C159: =HYPERLINK(IEEE_NEW!$P107, IEEE_NEW!$A107) -> The importance of testing Smart Grid IEDs against security vulnerabilities | D159: =IEEE_NEW!$AC107 -> 21
A160: 193 | B160: IEEE | C160: =HYPERLINK(IEEE_NEW!$P108, IEEE_NEW!$A108) -> Virtual PLC in Industrial Edge Platform: Performance Evaluation of Supervision and Control Communication | D160: =IEEE_NEW!$AC108 -> 10
A161: 195 | B161: SCOPUS | C161: =HYPERLINK(SCOPUS_NEW!$N33, SCOPUS_NEW!$D33) -> Integrity Enhancing Protocols: Performance and Recommendations for Nuclear Systems | D161: =SCOPUS_NEW!$V33 -> 10
A162: 196 | B162: ACM DL | C162: =HYPERLINK(ACM_NEW!$D41, ACM_NEW!$B41) -> Identification of industrial devices based on payload | D162: =ACM_NEW!$H41 -> 9

Sheet Title_and_Abstract_Screening
A1: Identifier | B1: Database | C1: Title | D1: Number of pages | E1: Done (mark with 'O') | F1: EC1 | G1: EC2 | H1: EC3 | I1: EC4 | J1: EC5 | K1: EC6 | L1: EC7 | M1: Title Exclusion | N1: Decision | O1: Motivation
A2: 0 | B2: IEEE | C2: =HYPERLINK(IEEE_NEW!$P2, IEEE_NEW!$A2) -> Towards a modular security testing framework for industrial automation and control systems: ISuTest | D2: 5 | E2: O | I2: =IF(AND(D2>=1, D2<=4), "X", "") | N2: =IF(COUNTIF(F2:M2,"X")>0,"Exclude",IF(UPPER(TRIM(E2))="O","Include","")) -> Include | O2: Security testing frameworks/protocol robustness testing in IACS. method/framework for security testing, including protocol-facing robustness tests
A3: 1 | B3: IEEE | C3: =HYPERLINK(IEEE_NEW!$P3, IEEE_NEW!$A3) -> VTET: A Virtual Industrial Control System Testbed for Cyber Security Research | D3: 7 | E3: O | I3: =IF(AND(D3>=1, D3<=4), "X", "") | L3: X | N3: =IF(COUNTIF(F3:M3,"X")>0,"Exclude",IF(UPPER(TRIM(E3))="O","Include","")) -> Exclude | O3: ICS security testbed to run ICS attacks, not protocol evaluation.
A4: 2 | B4: IEEE | C4: =HYPERLINK(IEEE_NEW!$P4, IEEE_NEW!$A4) -> The SAir-IIoT Cyber Testbed as a Service: A Novel Cybertwins Architecture in IIoT-Based Smart Airports | D4: 14 | E4: O | I4: =IF(AND(D4>=1, D4<=4), "X", "") | L4: X | M4: X | N4: =IF(COUNTIF(F4:M4,"X")>0,"Exclude",IF(UPPER(TRIM(E4))="O","Include","")) -> Exclude | O4: Not a experimental/theoretical evaluation of communication protocols | Q4: Statistics (total) | R4: Count | S4: Percentage | U4: Statistics (title screening) | V4: Count | W4: Percentage | Y4: Statistics (abstract screening) | Z4: Count | AA4: Percentage
A5: 3 | B5: IEEE | C5: =HYPERLINK(IEEE_NEW!$P5, IEEE_NEW!$A5) -> Test Bed Development for a Security Engineered SCADA Laboratory | D5: 5 | E5: O | I5: =IF(AND(D5>=1, D5<=4), "X", "") | L5: X | N5: =IF(COUNTIF(F5:M5,"X")>0,"Exclude",IF(UPPER(TRIM(E5))="O","Include","")) -> Exclude | O5: no experimental/theoretical evaluation of communication protocols and no concrete protocol-evaluation method with reported protocol metrics/results | Q5: Total papers: | R5: =COUNTIF(A2:A162,"<>") -> 161 | U5: Total papers: | V5: =COUNTIF($A2:$A162,"<>") -> 161 | Y5: Total papers: | Z5: =$V7 -> 63
A6: 4 | B6: IEEE | C6: =HYPERLINK(IEEE_NEW!$P6, IEEE_NEW!$A6) -> Industrial Internet of Things (IIoT): Testbed and Datasets for CyberSecurity and Digital Forensics | D6: 10 | E6: O | I6: =IF(AND(D6>=1, D6<=4), "X", "") | L6: X | M6: X | N6: =IF(COUNTIF(F6:M6,"X")>0,"Exclude",IF(UPPER(TRIM(E6))="O","Include","")) -> Exclude | O6: testbed + datasets paper for cybersecurity/digital forensics, not an evaluation method for industrial information-exchange protocols. | Q6: Number excluded: | R6: =COUNTIF(N2:N162,"Exclude") -> 137 | S6: =(($R6/$R5)) -> 0.85093168 | U6: Number excluded: | V6: =COUNTIFS($N2:$N162,"Exclude",$M2:$M162,"X") -> 98 | W6: =((V6/V5)) -> 0.60869565 | Y6: Number excluded: | Z6: =COUNTIFS($N2:$N162,"Exclude",$M2:$M162,"<>X") -> 39 | AA6: =((Z6/Z5)) -> 0.61904762
A7: 5 | B7: IEEE | C7: =HYPERLINK(IEEE_NEW!$P7, IEEE_NEW!$A7) -> Improving Substation Network Security with DevSecOps and AIOps | D7: 6 | E7: O | I7: =IF(AND(D7>=1, D7<=4), "X", "") | L7: X | M7: X | N7: =IF(COUNTIF(F7:M7,"X")>0,"Exclude",IF(UPPER(TRIM(E7))="O","Include","")) -> Exclude | O7: doesn’t evaluate communication protocols or propose a protocol-evaluation method/metrics set | Q7: Number included: | R7: =COUNTIF(N2:N153,"Include") -> 21 | S7: =(($R7/$R5)) -> 0.13043478 | U7: Number included: | V7: =COUNTIFS($M2:$M162,"<>X",$E2:$E162,"O") -> 63 | W7: =((V7/V5)) -> 0.39130435 | Y7: Number included: | Z7: =COUNTIFS($N2:$N162,"Include", $M2:$M162,"<>X") -> 24 | AA7: =((Z7/Z5)) -> 0.38095238
A8: 6 | B8: IEEE | C8: =HYPERLINK(IEEE_NEW!$P8, IEEE_NEW!$A8) -> Performance Evaluation of MQTT and CoAP Communication Protocols in IIoT for Electrical Substations Based on the IEC 61850 Standard | D8: 6 | E8: O | I8: =IF(AND(D8>=1, D8<=4), "X", "") | N8: =IF(COUNTIF(F8:M8,"X")>0,"Exclude",IF(UPPER(TRIM(E8))="O","Include","")) -> Include | O8: Evaluates protocols MQTT vs CoAP using performance metrics, done in a industrial automation setting. Evaluates latency, jitter, bandwidth, throughput, packet loss using thir test bench | Q8: Type violation: | U8: Type violation: | Y8: Type violation:
A9: 7 | B9: IEEE | C9: =HYPERLINK(IEEE_NEW!$P9, IEEE_NEW!$A9) -> Behavior and Vulnerability Assessment of Drones-Enabled Industrial Internet of Things (IIoT) | D9: 16 | E9: O | I9: =IF(AND(D9>=1, D9<=4), "X", "") | L9: X | M9: X | N9: =IF(COUNTIF(F9:M9,"X")>0,"Exclude",IF(UPPER(TRIM(E9))="O","Include","")) -> Exclude | O9: Petri-net (HCAPN) model to assess drone behaviour, It does not experimentally/theoretically evaluate communication protocols. | Q9: EC1 | R9: =COUNTIF(F$2:F$162,"X") -> 3 | S9: =(($R9/$R$5)) -> 0.01863354 | U9: EC1 | V9: =COUNTIFS($F2:$F162,"X", $M2:$M162,"X") -> 1 | W9: =((V9/V$5)) -> 0.0062111801 | Y9: EC1 | Z9: =COUNTIFS($F2:$F162,"X", $M2:$M162,"<>X") -> 2 | AA9: =((Z9/Z$5)) -> 0.031746032
A10: 8 | B10: IEEE | C10: =HYPERLINK(IEEE_NEW!$P10, IEEE_NEW!$A10) -> Architecture of Modular System for Assessing Security of Telemetry Information Transmission System | D10: 6 | E10: O | H10: X | I10: =IF(AND(D10>=1, D10<=4), "X", "") | N10: =IF(COUNTIF(F10:M10,"X")>0,"Exclude",IF(UPPER(TRIM(E10))="O","Include","")) -> Exclude | O10: not an industrial automation / closed-loop control communication setting | Q10: EC2 | R10: =COUNTIF(G$2:G$162,"X") -> 1 | S10: =(($R10/$R$5)) -> 0.0062111801 | U10: EC2 | V10: =COUNTIFS($G2:$G162,"X", $M2:$M162,"X") -> 1 | W10: =((V10/V$5)) -> 0.0062111801 | Y10: EC2 | Z10: =COUNTIFS($G2:$G162,"X", $M2:$M162,"<>X") -> 0 | AA10: =((Z10/Z$5)) -> 0
A11: 9 | B11: IEEE | C11: =HYPERLINK(IEEE_NEW!$P11, IEEE_NEW!$A11) -> Developing a Security Testbed for Industrial Internet of Things | D11: 16 | E11: O | I11: =IF(AND(D11>=1, D11<=4), "X", "") | N11: =IF(COUNTIF(F11:M11,"X")>0,"Exclude",IF(UPPER(TRIM(E11))="O","Include","")) -> Include | O11: It proposes a reproducible end-to-end IIoT security, testbed (Brown-IIoTbed), which supports security testing and evaluation of different solutions. It also reports concrete protocol timing/jitter numbers as part of validating the testbed. "Brown-IIoTbed covers existing gaps in the development of IoT/IIoT system testbeds by supporting various new IIoT application protocols, legacy industrial protocols, the interoperability among them" | Q11: EC3 | R11: =COUNTIF(H$2:H$162,"X") -> 26 | S11: =(($R11/$R$5)) -> 0.16149068 | U11: EC3 | V11: =COUNTIFS($H2:$H162,"X", $M2:$M162,"X") -> 21 | W11: =((V11/V$5)) -> 0.13043478 | Y11: EC3 | Z11: =COUNTIFS($H2:$H162,"X", $M2:$M162,"<>X") -> 5 | AA11: =((Z11/Z$5)) -> 0.079365079
A12: 10 | B12: IEEE | C12: =HYPERLINK(IEEE_NEW!$P12, IEEE_NEW!$A12) -> SWaP: A Water Process Testbed for ICS Security Research | D12: 4 | E12: O | I12: =IF(AND(D12>=1, D12<=4), "X", "") -> X | N12: =IF(COUNTIF(F12:M12,"X")>0,"Exclude",IF(UPPER(TRIM(E12))="O","Include","")) -> Exclude | O12: Violates EC4, i.e., 4 pages or less | Q12: EC4 | R12: =COUNTIF(I$2:I$162,"X") -> 6 | S12: =(($R12/$R$5)) -> 0.037267081 | U12: EC4 | V12: =COUNTIFS($I2:$I162,"X", $M2:$M162,"X") -> 1 | W12: =((V12/V$5)) -> 0.0062111801 | Y12: EC4 | Z12: =COUNTIFS($I2:$I162,"X", $M2:$M162,"<>X") -> 5 | AA12: =((Z12/Z$5)) -> 0.079365079
A13: 11 | B13: IEEE | C13: =HYPERLINK(IEEE_NEW!$P13, IEEE_NEW!$A13) -> A Comparative Analysis of Application Layer Protocols Within an Industrial Internet of Things Monitoring System | D13: 6 | E13: O | I13: =IF(AND(D13>=1, D13<=4), "X", "") | N13: =IF(COUNTIF(F13:M13,"X")>0,"Exclude",IF(UPPER(TRIM(E13))="O","Include","")) -> Include | O13: Experimental performance evaluation of MQTT, CoAP, WebSockets, and HTTP. It utilize metrics such as average latency, jitter, throughput, and protocol efficiency. | Q13: EC5 | R13: =COUNTIF(J$2:J$162,"X") -> 9 | S13: =(($R13/$R$5)) -> 0.055900621 | U13: EC5 | V13: =COUNTIFS($J2:$J162,"X", $M2:$M162,"X") -> 5 | W13: =((V13/V$5)) -> 0.031055901 | Y13: EC5 | Z13: =COUNTIFS($J2:$J162,"X", $M2:$M162,"<>X") -> 4 | AA13: =((Z13/Z$5)) -> 0.063492063
A14: 12 | B14: IEEE | C14: =HYPERLINK(IEEE_NEW!$P14, IEEE_NEW!$A14) -> Application of Industrial Internet of Things with Edge Computing and Artificial Intelligence Models | D14: 4 | E14: O | I14: =IF(AND(D14>=1, D14<=4), "X", "") -> X | N14: =IF(COUNTIF(F14:M14,"X")>0,"Exclude",IF(UPPER(TRIM(E14))="O","Include","")) -> Exclude | O14: Violates EC4, i.e., 4 pages or less | Q14: EC6 | R14: =COUNTIF(K$2:K$162,"X") -> 0 | S14: =(($R14/$R$5)) -> 0 | U14: EC6 | V14: =COUNTIFS($K2:$K162,"X", $M2:$M162,"X") -> 0 | W14: =((V14/V$5)) -> 0 | Y14: EC6 | Z14: =COUNTIFS($K2:$K162,"X", $M2:$M162,"<>X") -> 0 | AA14: =((Z14/Z$5)) -> 0
A15: 13 | B15: IEEE | C15: =HYPERLINK(IEEE_NEW!$P15, IEEE_NEW!$A15) -> A Cyber-Security Methodology for a Cyber-Physical Industrial Control System Testbed | D15: 15 | E15: O | I15: =IF(AND(D15>=1, D15<=4), "X", "") | L15: X | N15: =IF(COUNTIF(F15:M15,"X")>0,"Exclude",IF(UPPER(TRIM(E15))="O","Include","")) -> Exclude | O15: Builds a hybrid ICS testbed that they use to inject false-data attacks via PROFINET, then cmpare online attack-detection algorithms. Does not experimantilly or theoretically evaluate communication protocols. | Q15: EC7 | R15: =COUNTIF(L$2:L$162,"X") -> 104 | S15: =(($R15/$R$5)) -> 0.64596273 | U15: EC7 | V15: =COUNTIFS($L2:$L162,"X", $M2:$M162,"X") -> 79 | W15: =((V15/V$5)) -> 0.49068323 | Y15: EC7 | Z15: =COUNTIFS($L2:$L162,"X", $M2:$M162,"<>X") -> 25 | AA15: =((Z15/Z$5)) -> 0.3968254
A16: 14 | B16: IEEE | C16: =HYPERLINK(IEEE_NEW!$P16, IEEE_NEW!$A16) -> SCADA-SST: a SCADA security testbed | D16: 6 | E16: O | I16: =IF(AND(D16>=1, D16<=4), "X", "") | L16: X | N16: =IF(COUNTIF(F16:M16,"X")>0,"Exclude",IF(UPPER(TRIM(E16))="O","Include","")) -> Exclude | O16: SCADA simulation environment for security testing. The evaluation example is DoS/DDoS on an RTU and tracking opened/dropped TCP connections, not evaluation of communication protocols or a protocol-assessment method with protocol metrics for closed-loop control. | Q16: Title Exclusion | R16: =COUNTIF(M$2:M$162,"X") -> 98 | S16: =(($R16/$R$5)) -> 0.60869565
A17: 15 | B17: IEEE | C17: =HYPERLINK(IEEE_NEW!$P17, IEEE_NEW!$A17) -> Design and Implementation of Full-Scale Industrial Control System Test Bed for Assessing Cyber-Security Defenses | D17: 6 | E17: O | I17: =IF(AND(D17>=1, D17<=4), "X", "") | L17: X | N17: =IF(COUNTIF(F17:M17,"X")>0,"Exclude",IF(UPPER(TRIM(E17))="O","Include","")) -> Exclude | O17: methodology + implementation of a realistic ICS test bed to validate cybersecurity defenses. Not an experimental/theoretical evaluation of communication protocols or a method for protocol evaluation.
A18: 16 | B18: IEEE | C18: =HYPERLINK(IEEE_NEW!$P18, IEEE_NEW!$A18) -> A dual-standard solution for industrial Wireless Sensor Network deployment: Experimental testbed and performance evaluation | D18: 9 | E18: O | I18: =IF(AND(D18>=1, D18<=4), "X", "") | N18: =IF(COUNTIF(F18:M18,"X")>0,"Exclude",IF(UPPER(TRIM(E18))="O","Include","")) -> Include | O18: performance evaluation of industrial wireless communication standards ISA100.11a and WirelessHART, including a dual-standard architecture. It uses a real testbed and reports protocol/network KPIs.
A19: 17 | B19: IEEE | C19: =HYPERLINK(IEEE_NEW!$P19, IEEE_NEW!$A19) -> Enhancing Industrial Communication Protocol Fuzz Testing Through Virtualization And Intelligent Guidance | D19: 5 | E19: O | I19: =IF(AND(D19>=1, D19<=4), "X", "") | N19: =IF(COUNTIF(F19:M19,"X")>0,"Exclude",IF(UPPER(TRIM(E19))="O","Include","")) -> Include | O19: Improving fuzz testing for industrial protocol security, then reports experimental evaluation (coverage, vulnerbility discovery, efficiency, resource use, etc).
A20: 18 | B20: IEEE | C20: =HYPERLINK(IEEE_NEW!$P20, IEEE_NEW!$A20) -> A virtual testbed for security management of industrial control systems | D20: 6 | E20: O | I20: =IF(AND(D20>=1, D20<=4), "X", "") | L20: X | N20: =IF(COUNTIF(F20:M20,"X")>0,"Exclude",IF(UPPER(TRIM(E20))="O","Include","")) -> Exclude | O20: building an ICS security testbed and simulating attacks, not “experimental or theoretical evaluation of communication protocols” or “improving methods used for such evaluations"
A21: 19 | B21: IEEE | C21: =HYPERLINK(IEEE_NEW!$P21, IEEE_NEW!$A21) -> Design, Analysis and Implementation of a Security Assessment/Enhancement Platform for Cyber-Physical Systems | D21: 11 | E21: O | I21: =IF(AND(D21>=1, D21<=4), "X", "") | L21: X | M21: X | N21: =IF(COUNTIF(F21:M21,"X")>0,"Exclude",IF(UPPER(TRIM(E21))="O","Include","")) -> Exclude | O21: Generic CPS platform; protocol evaluation not implied (EC7)
A22: 20 | B22: IEEE | C22: =HYPERLINK(IEEE_NEW!$P22, IEEE_NEW!$A22) -> Cyber security of industrial communication protocols | D22: 4 | E22: O | I22: =IF(AND(D22>=1, D22<=4), "X", "") -> X | N22: =IF(COUNTIF(F22:M22,"X")>0,"Exclude",IF(UPPER(TRIM(E22))="O","Include","")) -> Exclude | O22: Violates EC4, i.e., 4 pages or less
A23: 21 | B23: IEEE | C23: =HYPERLINK(IEEE_NEW!$P23, IEEE_NEW!$A23) -> A Comparative Study to Evaluate the Performance of Communication Protocols for Process Industry | D23: 8 | E23: O | I23: =IF(AND(D23>=1, D23<=4), "X", "") | N23: =IF(COUNTIF(F23:M23,"X")>0,"Exclude",IF(UPPER(TRIM(E23))="O","Include","")) -> Include | O23: test environment and performance evaluation of OPC UA vs MQTT with defined metrics and scenarios.
A24: 22 | B24: IEEE | C24: =HYPERLINK(IEEE_NEW!$P24, IEEE_NEW!$A24) -> Access Control Framework for Cross-Platform Interoperability in the Industrial Internet of Things | D24: 10 | E24: O | I24: =IF(AND(D24>=1, D24<=4), "X", "") | L24: X | M24: X | N24: =IF(COUNTIF(F24:M24,"X")>0,"Exclude",IF(UPPER(TRIM(E24))="O","Include","")) -> Exclude | O24: Contributes a access-control interoperability framework between IIoT platforms, not an evaluation of communication proto9cols
A25: 23 | B25: IEEE | C25: =HYPERLINK(IEEE_NEW!$P25, IEEE_NEW!$A25) -> The Cybersecurity Landscape in Industrial Control Systems | D25: 19 | E25: O | I25: =IF(AND(D25>=1, D25<=4), "X", "") | J25: X | M25: X | N25: =IF(COUNTIF(F25:M25,"X")>0,"Exclude",IF(UPPER(TRIM(E25))="O","Include","")) -> Exclude | O25: survey of the ICS security landscape
A26: 24 | B26: IEEE | C26: =HYPERLINK(IEEE_NEW!$P26, IEEE_NEW!$A26) -> IoTForge Pro: A Security Testbed for Generating Intrusion Dataset for Industrial IoT | D26: 8 | E26: O | I26: =IF(AND(D26>=1, D26<=4), "X", "") | L26: X | N26: =IF(COUNTIF(F26:M26,"X")>0,"Exclude",IF(UPPER(TRIM(E26))="O","Include","")) -> Exclude | O26: an IIoT security testbed that generates an intrusion dataset (ForgeIIOT) and then evaluates IDS/ML classifiers on that dataset. no experimental/theoretical evaluation of communication protocols and no concrete protocol-evaluation method with reported protocol metrics/results
A27: 25 | B27: IEEE | C27: =HYPERLINK(IEEE_NEW!$P27, IEEE_NEW!$A27) -> Ransomware in Resource-Constrained Industrial IoT Networks: There Actually is a Threat | D27: 8 | E27: O | I27: =IF(AND(D27>=1, D27<=4), "X", "") | L27: X | M27: X | N27: =IF(COUNTIF(F27:M27,"X")>0,"Exclude",IF(UPPER(TRIM(E27))="O","Include","")) -> Exclude | O27: ransomware in IIoT networks; nothing suggests protocol evaluation, benchmarking, or a reusable evaluation setup.
A28: 26 | B28: IEEE | C28: =HYPERLINK(IEEE_NEW!$P28, IEEE_NEW!$A28) -> Machine Learning-Based Network Vulnerability Analysis of Industrial Internet of Things | D28: 13 | E28: O | I28: =IF(AND(D28>=1, D28<=4), "X", "") | L28: X | M28: X | N28: =IF(COUNTIF(F28:M28,"X")>0,"Exclude",IF(UPPER(TRIM(E28))="O","Include","")) -> Exclude | O28: Security/vulnerability analysis using ML; typically not a protocol evaluation framework/testbed.
A29: 27 | B29: IEEE | C29: =HYPERLINK(IEEE_NEW!$P29, IEEE_NEW!$A29) -> CPS-IIoT-P2Attention: Explainable Privacy-Preserving With Scaled Dot-Product Attention in Cyber-Physical System-Industrial IoT Network | D29: 25 | E29: O | I29: =IF(AND(D29>=1, D29<=4), "X", "") | L29: X | M29: X | N29: =IF(COUNTIF(F29:M29,"X")>0,"Exclude",IF(UPPER(TRIM(E29))="O","Include","")) -> Exclude | O29: model development/IDS-style work, not protocol evaluation/testbed work.
A30: 28 | B30: IEEE | C30: =HYPERLINK(IEEE_NEW!$P30, IEEE_NEW!$A30) -> Network Simulation in a TCP-Enabled Industrial Internet of Things Environment-Reproducibility Issues for Performance Evaluation | D30: 9 | E30: O | I30: =IF(AND(D30>=1, D30<=4), "X", "") | L30: X | N30: =IF(COUNTIF(F30:M30,"X")>0,"Exclude",IF(UPPER(TRIM(E30))="O","Include","")) -> Exclude | O30: no experimental/theoretical evaluation of communication protocols and no concrete protocol-evaluation method with reported protocol metrics/results
A31: 29 | B31: IEEE | C31: =HYPERLINK(IEEE_NEW!$P31, IEEE_NEW!$A31) -> Securing IIoT Against DDoS attacks: A Stochastic Approach | D31: 6 | E31: O | I31: =IF(AND(D31>=1, D31<=4), "X", "") | L31: X | M31: X | N31: =IF(COUNTIF(F31:M31,"X")>0,"Exclude",IF(UPPER(TRIM(E31))="O","Include","")) -> Exclude | O31: DDoS mitigation via stochastic modelling; doesn’t signal protocol evaluation setup or benchmarking framework.
A32: 30 | B32: IEEE | C32: =HYPERLINK(IEEE_NEW!$P32, IEEE_NEW!$A32) -> Comparative Study on Smart Grid Security Testbeds Using MITRE ATT&CK Matrix | D32: 7 | E32: O | I32: =IF(AND(D32>=1, D32<=4), "X", "") | J32: X | L32: X | N32: =IF(COUNTIF(F32:M32,"X")>0,"Exclude",IF(UPPER(TRIM(E32))="O","Include","")) -> Exclude | O32: comparative study of smart-grid security testbeds (EPIC, KASTEL Lab, SGCR)
A33: 31 | B33: IEEE | C33: =HYPERLINK(IEEE_NEW!$P33, IEEE_NEW!$A33) -> A Survey on Industrial Control System Testbeds and Datasets for Security Research | D33: 47 | E33: O | I33: =IF(AND(D33>=1, D33<=4), "X", "") | J33: X | N33: =IF(COUNTIF(F33:M33,"X")>0,"Exclude",IF(UPPER(TRIM(E33))="O","Include","")) -> Exclude | O33: Violates EC5, a review paper
A34: 32 | B34: IEEE | C34: =HYPERLINK(IEEE_NEW!$P34, IEEE_NEW!$A34) -> Li-Fi in Industrial Environments: Performance Analysis Compared to Wi-Fi and Ethernet | D34: 6 | E34: O | I34: =IF(AND(D34>=1, D34<=4), "X", "") | L34: X | M34: X | N34: =IF(COUNTIF(F34:M34,"X")>0,"Exclude",IF(UPPER(TRIM(E34))="O","Include","")) -> Exclude | O34: Link-tech comparison, not industrial protocol evaluation (EC7)
A35: 33 | B35: IEEE | C35: =HYPERLINK(IEEE_NEW!$P35, IEEE_NEW!$A35) -> URLLC-Based Cooperative Industrial IoT Networks With Nonlinear Energy Harvesting | D35: 11 | E35: O | I35: =IF(AND(D35>=1, D35<=4), "X", "") | L35: X | M35: X | N35: =IF(COUNTIF(F35:M35,"X")>0,"Exclude",IF(UPPER(TRIM(E35))="O","Include","")) -> Exclude | O35: theoretical performance analysis of wireless relaying and energy harvesting, not evaluation or improvement of methods for assessing industrial communication protocols.
A36: 34 | B36: IEEE | C36: =HYPERLINK(IEEE_NEW!$P36, IEEE_NEW!$A36) -> Methodology for Analyzing the Performance of 5G-NR Networks During Initial Planning Without Deployment Using the NS-3 Network Simulator | D36: 5 | E36: O | H36: X | I36: =IF(AND(D36>=1, D36<=4), "X", "") | L36: X | M36: X | N36: =IF(COUNTIF(F36:M36,"X")>0,"Exclude",IF(UPPER(TRIM(E36))="O","Include","")) -> Exclude | O36: 5G planning/scheduling, not IACS closed-loop protocol evaluation and primary objective is scheduler/network performance, not evaluating secure industrial communication protocols or improving methods for that evaluation
A37: 35 | B37: IEEE | C37: =HYPERLINK(IEEE_NEW!$P37, IEEE_NEW!$A37) -> Cybersecurity of Digital Twins in Industrial IoT Environments | D37: 6 | E37: O | I37: =IF(AND(D37>=1, D37<=4), "X", "") | L37: X | M37: X | N37: =IF(COUNTIF(F37:M37,"X")>0,"Exclude",IF(UPPER(TRIM(E37))="O","Include","")) -> Exclude | O37: Digital twin security topic; no industrial comms protocol + no evaluation method/testbed framing.
A38: 36 | B38: IEEE | C38: =HYPERLINK(IEEE_NEW!$P38, IEEE_NEW!$A38) -> Security and Effectiveness Analysis of the Gateway Integrity Checking Protocol | D38: 9 | E38: O | I38: =IF(AND(D38>=1, D38<=4), "X", "") | N38: =IF(COUNTIF(F38:M38,"X")>0,"Exclude",IF(UPPER(TRIM(E38))="O","Include","")) -> Include | O38: theoretical and experimental evaluation of a protocol and its detection effectiveness
A39: 37 | B39: IEEE | C39: =HYPERLINK(IEEE_NEW!$P39, IEEE_NEW!$A39) -> Secure Onboarding of IIoT Devices using OPC UA | D39: 4 | E39: O | I39: =IF(AND(D39>=1, D39<=4), "X", "") -> X | N39: =IF(COUNTIF(F39:M39,"X")>0,"Exclude",IF(UPPER(TRIM(E39))="O","Include","")) -> Exclude | O39: Violates EC4, i.e., 4 pages or less
A40: 38 | B40: IEEE | C40: =HYPERLINK(IEEE_NEW!$P40, IEEE_NEW!$A40) -> On the Cost of Asset Discovery Techniques for Industrial Control Systems | D40: 6 | E40: O | I40: =IF(AND(D40>=1, D40<=4), "X", "") | L40: X | M40: X | N40: =IF(COUNTIF(F40:M40,"X")>0,"Exclude",IF(UPPER(TRIM(E40))="O","Include","")) -> Exclude | O40: Asset discovery, not protocol evaluation (EC7)
A41: 39 | B41: IEEE | C41: =HYPERLINK(IEEE_NEW!$P41, IEEE_NEW!$A41) -> CrossTest: a cross-domain physical testbed environment for cybersecurity performance evaluations | D41: 8 | E41: O | I41: =IF(AND(D41>=1, D41<=4), "X", "") | L41: X | N41: =IF(COUNTIF(F41:M41,"X")>0,"Exclude",IF(UPPER(TRIM(E41))="O","Include","")) -> Exclude | O41: cross-domain cybersecurity testbed (CrossTest) to develop and evaluate NIDS / threat detection tools, plus an evaluation of the tool Malcolm using the generated PCAP datasets—not an experimental/theoretical evaluation of communication protocols themselves.
A42: 40 | B42: IEEE | C42: =HYPERLINK(IEEE_NEW!$P42, IEEE_NEW!$A42) -> Towards Performance Benchmarking of Cyclic OPC UA PubSub over TSN | D42: 8 | E42: O | I42: =IF(AND(D42>=1, D42<=4), "X", "") | N42: =IF(COUNTIF(F42:M42,"X")>0,"Exclude",IF(UPPER(TRIM(E42))="O","Include","")) -> Include | O42: protocol benchmarking + experimental results
A43: 41 | B43: IEEE | C43: =HYPERLINK(IEEE_NEW!$P43, IEEE_NEW!$A43) -> Performance Evaluation of Containerization in Edge-Cloud Computing Stacks for Industrial Applications: A Client Perspective | D43: 16 | E43: O | I43: =IF(AND(D43>=1, D43<=4), "X", "") | L43: X | M43: X | N43: =IF(COUNTIF(F43:M43,"X")>0,"Exclude",IF(UPPER(TRIM(E43))="O","Include","")) -> Exclude | O43: performance evaluation methodology for containerization-based edge–cloud stacks. Does not evaluate or compare communication protocols as the primary object of study
A44: 42 | B44: IEEE | C44: =HYPERLINK(IEEE_NEW!$P44, IEEE_NEW!$A44) -> FL-MU: A Benchmark Dataset for Federated Intrusion Detection in IoT Networks | D44: 28 | E44: O | H44: X | I44: =IF(AND(D44>=1, D44<=4), "X", "") | L44: X | M44: X | N44: =IF(COUNTIF(F44:M44,"X")>0,"Exclude",IF(UPPER(TRIM(E44))="O","Include","")) -> Exclude | O44: FL-MU: A Benchmark Dataset for Federated Intrusion Detection in IoT Networks
A45: 43 | B45: IEEE | C45: =HYPERLINK(IEEE_NEW!$P45, IEEE_NEW!$A45) -> ROSTAM: Railway-Oriented Security and Threat Abstraction Model | D45: 6 | E45: O | I45: =IF(AND(D45>=1, D45<=4), "X", "") | L45: X | M45: X | N45: =IF(COUNTIF(F45:M45,"X")>0,"Exclude",IF(UPPER(TRIM(E45))="O","Include","")) -> Exclude | O45: Threat model/abstraction; no protocol evaluation setup.
A46: 44 | B46: IEEE | C46: =HYPERLINK(IEEE_NEW!$P46, IEEE_NEW!$A46) -> Enabling multi-layer cyber-security assessment of Industrial Control Systems through Hardware-In-The-Loop testbeds | D46: 8 | E46: O | I46: =IF(AND(D46>=1, D46<=4), "X", "") | L46: X | N46: =IF(COUNTIF(F46:M46,"X")>0,"Exclude",IF(UPPER(TRIM(E46))="O","Include","")) -> Exclude | O46: ICS cyber-security assessment and arguing for Hardware-in-the-Loop (HIL) testbeds via a layered threat/vulnerability discussion. It does not present an experimental/theoretical evaluation of communication protocols, and it does not propose a protocol-evaluation method/model.
A47: 45 | B47: IEEE | C47: =HYPERLINK(IEEE_NEW!$P47, IEEE_NEW!$A47) -> Performance Benchmarking of OpenPLC Across Multiple Environments for Cloud-Based Industrial Automation | D47: 6 | E47: O | I47: =IF(AND(D47>=1, D47<=4), "X", "") | L47: X | M47: X | N47: =IF(COUNTIF(F47:M47,"X")>0,"Exclude",IF(UPPER(TRIM(E47))="O","Include","")) -> Exclude | O47: PLC runtime benchmarking, not comm protocol benchmarking/evaluation.
A48: 46 | B48: IEEE | C48: =HYPERLINK(IEEE_NEW!$P48, IEEE_NEW!$A48) -> A New Dataset for Intrusion Detection in Industrial Control System: A Gas Pipeline Testbed Study | D48: 6 | E48: O | I48: =IF(AND(D48>=1, D48<=4), "X", "") | L48: X | M48: X | N48: =IF(COUNTIF(F48:M48,"X")>0,"Exclude",IF(UPPER(TRIM(E48))="O","Include","")) -> Exclude | O48: IDS dataset/testbed study; not protocol evaluation method.
A49: 47 | B49: IEEE | C49: =HYPERLINK(IEEE_NEW!$P49, IEEE_NEW!$A49) -> Real-Time Communication over LoRa Networks | D49: 14 | E49: O | H49: X | I49: =IF(AND(D49>=1, D49<=4), "X", "") | N49: =IF(COUNTIF(F49:M49,"X")>0,"Exclude",IF(UPPER(TRIM(E49))="O","Include","")) -> Exclude | O49: It’s about LoRa real-time comms generally; not clearly centered on industrial automation protocol evaluation for closed-loop control
A50: 48 | B50: IEEE | C50: =HYPERLINK(IEEE_NEW!$P50, IEEE_NEW!$A50) -> Modelling Autonomous Mobile Robot Interaction with IIoT Environments | D50: 6 | E50: O | I50: =IF(AND(D50>=1, D50<=4), "X", "") | L50: X | M50: X | N50: =IF(COUNTIF(F50:M50,"X")>0,"Exclude",IF(UPPER(TRIM(E50))="O","Include","")) -> Exclude | O50: modelling approach for IIoT + multi-robot system integration, not an experimental/theoretical evaluation of communication protocols or methods to evaluate them.
A51: 49 | B51: IEEE | C51: =HYPERLINK(IEEE_NEW!$P51, IEEE_NEW!$A51) -> Covert Channels-Based Stealth Attacks in Industry 4.0 | D51: 9 | E51: O | I51: =IF(AND(D51>=1, D51<=4), "X", "") | M51: X | N51: =IF(COUNTIF(F51:M51,"X")>0,"Exclude",IF(UPPER(TRIM(E51))="O","Include","")) -> Exclude | O51: Attack study, not protocol evaluation (EC7)
A52: 50 | B52: IEEE | C52: =HYPERLINK(IEEE_NEW!$P52, IEEE_NEW!$A52) -> Feasibility Study on Virtual Process Controllers as Basis for Future Industrial Automation Systems | D52: 8 | E52: O | I52: =IF(AND(D52>=1, D52<=4), "X", "") | L52: X | N52: =IF(COUNTIF(F52:M52,"X")>0,"Exclude",IF(UPPER(TRIM(E52))="O","Include","")) -> Exclude | O52: primary objective is a virtual process controller (VPC) architecture and a testbed to validate features like reconfiguration, redeployment, and resilience, but it does not evaluate industrial communication protocols (nor methods for evaluating them).
A53: 51 | B53: IEEE | C53: =HYPERLINK(IEEE_NEW!$P53, IEEE_NEW!$A53) -> Contention Congestion Collision Adaptive Data Rate for LoRaWAN-Based Challenging Industrial IoT | D53: 6 | E53: O | H53: X | I53: =IF(AND(D53>=1, D53<=4), "X", "") | M53: X | N53: =IF(COUNTIF(F53:M53,"X")>0,"Exclude",IF(UPPER(TRIM(E53))="O","Include","")) -> Exclude | O53: LoRaWAN ADR tuning, not industrial automation protocol eval (EC3)
A54: 52 | B54: IEEE | C54: =HYPERLINK(IEEE_NEW!$P54, IEEE_NEW!$A54) -> Fog Computing Over Challenged Networks: A Real Case Evaluation | D54: 7 | E54: O | I54: =IF(AND(D54>=1, D54<=4), "X", "") | L54: X | M54: X | N54: =IF(COUNTIF(F54:M54,"X")>0,"Exclude",IF(UPPER(TRIM(E54))="O","Include","")) -> Exclude | O54: Fog networking, not protocol evaluation (EC7)
A55: 53 | B55: IEEE | C55: =HYPERLINK(IEEE_NEW!$P55, IEEE_NEW!$A55) -> Optimizing MQTT-CoAP Interoperability: A Broker-Based Extension for Seamless Integration | D55: 14 | E55: O | I55: =IF(AND(D55>=1, D55<=4), "X", "") | L55: X | M55: X | N55: =IF(COUNTIF(F55:M55,"X")>0,"Exclude",IF(UPPER(TRIM(E55))="O","Include","")) -> Exclude | O55: Protocol mechanism/extension paper; not an evaluation framework/testbed/method.
A56: 54 | B56: IEEE | C56: =HYPERLINK(IEEE_NEW!$P56, IEEE_NEW!$A56) -> Experimental Platform for Testing Open Process Automation Technologies Based on OPC UA and IEC 61499 | D56: 5 | E56: O | I56: =IF(AND(D56>=1, D56<=4), "X", "") | L56: X | M56: X | N56: =IF(COUNTIF(F56:M56,"X")>0,"Exclude",IF(UPPER(TRIM(E56))="O","Include","")) -> Exclude | O56: experimental platform/testbed for Open Process Automation attributes (interoperability, modularity, portability) using OPC UA + IEC 61499, not a protocol evaluation study.
A57: 55 | B57: IEEE | C57: =HYPERLINK(IEEE_NEW!$P57, IEEE_NEW!$A57) -> FedMqADV: A Unified Framework for End-to-End Evaluation of MQTT-Based Federated Learning in Adversarial Setting | D57: 6 | E57: O | H57: X | I57: =IF(AND(D57>=1, D57<=4), "X", "") | L57: X | M57: X | N57: =IF(COUNTIF(F57:M57,"X")>0,"Exclude",IF(UPPER(TRIM(E57))="O","Include","")) -> Exclude | O57: Evaluation is for federated learning setup, not industrial protocol evaluation model/testbed.
A58: 56 | B58: IEEE | C58: =HYPERLINK(IEEE_NEW!$P58, IEEE_NEW!$A58) -> Safeguarding Inter-Device Communications for Connected Systems: A Holistic Security Framework | D58: 6 | E58: O | I58: =IF(AND(D58>=1, D58<=4), "X", "") | L58: X | M58: X | N58: =IF(COUNTIF(F58:M58,"X")>0,"Exclude",IF(UPPER(TRIM(E58))="O","Include","")) -> Exclude | O58: Security framework for embedded inter-device comms, with a reference implementation over I2C on Arduino nodes. does not evaluate or compare industrial protocols used in control networks
A59: 57 | B59: IEEE | C59: =HYPERLINK(IEEE_NEW!$P59, IEEE_NEW!$A59) -> End-to-End Delay Evaluation of Industrial Automation Systems Based on EtherCAT | D59: 8 | E59: O | I59: =IF(AND(D59>=1, D59<=4), "X", "") | N59: =IF(COUNTIF(F59:M59,"X")>0,"Exclude",IF(UPPER(TRIM(E59))="O","Include","")) -> Include | O59: evaluates an industrial automation communication protocol (EtherCAT) with closed-loop timing focus (end-to-end delay)
A60: 58 | B60: IEEE | C60: =HYPERLINK(IEEE_NEW!$P60, IEEE_NEW!$A60) -> Secure IoT Deployment Checklist for Building Management System | D60: 6 | E60: O | I60: =IF(AND(D60>=1, D60<=4), "X", "") | L60: X | M60: X | N60: =IF(COUNTIF(F60:M60,"X")>0,"Exclude",IF(UPPER(TRIM(E60))="O","Include","")) -> Exclude | O60: Checklist/guidance; no protocol evaluation artifact.
A61: 59 | B61: IEEE | C61: =HYPERLINK(IEEE_NEW!$P61, IEEE_NEW!$A61) -> An FPGA-based Unidirectional Gateway Proposal for OT-IT Network Separation to Secure Industrial Automation Systems | D61: 6 | E61: O | I61: =IF(AND(D61>=1, D61<=4), "X", "") | L61: X | M61: X | N61: =IF(COUNTIF(F61:M61,"X")>0,"Exclude",IF(UPPER(TRIM(E61))="O","Include","")) -> Exclude | O61: Gateway proposal/architecture, not protocol evaluation (EC7)
A62: 60 | B62: IEEE | C62: =HYPERLINK(IEEE_NEW!$P62, IEEE_NEW!$A62) -> Security intelligence for industrial control systems | D62: 1.0076389 | E62: O | F62: X | I62: =IF(AND(D62>=1, D62<=4), "X", "") -> X | N62: =IF(COUNTIF(F62:M62,"X")>0,"Exclude",IF(UPPER(TRIM(E62))="O","Include","")) -> Exclude | O62: Violates EC1, full text not available
A63: 61 | B63: IEEE | C63: =HYPERLINK(IEEE_NEW!$P63, IEEE_NEW!$A63) -> Hierarchical Blockchain Framework for Node Authentication in IoT Networks: A Comprehensive Analysis | D63: 6 | E63: O | H63: X | I63: =IF(AND(D63>=1, D63<=4), "X", "") | J63: X | M63: X | N63: =IF(COUNTIF(F63:M63,"X")>0,"Exclude",IF(UPPER(TRIM(E63))="O","Include","")) -> Exclude | O63: “Comprehensive analysis” reads as secondary + IoT/blockchain (EC5/EC3)
A64: 62 | B64: IEEE | C64: =HYPERLINK(IEEE_NEW!$P64, IEEE_NEW!$A64) -> Development of SCADA Simulator using Omnet++ | D64: 5 | E64: O | I64: =IF(AND(D64>=1, D64<=4), "X", "") | L64: X | N64: =IF(COUNTIF(F64:M64,"X")>0,"Exclude",IF(UPPER(TRIM(E64))="O","Include","")) -> Exclude | O64: main goal is to build a SCADA simulator and use it to study a TCP flood DDoS case on a power distribution scenario. It doesn’t evaluate or compare industrial communication protocols, and it doesn’t improve a protocol evaluation method
A65: 63 | B65: IEEE | C65: =HYPERLINK(IEEE_NEW!$P65, IEEE_NEW!$A65) -> Indoor Localization-based Energy Management for Smart Home | D65: 5 | E65: O | H65: X | I65: =IF(AND(D65>=1, D65<=4), "X", "") | M65: X | N65: =IF(COUNTIF(F65:M65,"X")>0,"Exclude",IF(UPPER(TRIM(E65))="O","Include","")) -> Exclude | O65: Smart home, unrelated (EC3)
A66: 64 | B66: IEEE | C66: =HYPERLINK(IEEE_NEW!$P66, IEEE_NEW!$A66) -> Toward a Unified Security Framework for Digital Twin Architectures | D66: 6 | E66: O | I66: =IF(AND(D66>=1, D66<=4), "X", "") | L66: X | M66: X | N66: =IF(COUNTIF(F66:M66,"X")>0,"Exclude",IF(UPPER(TRIM(E66))="O","Include","")) -> Exclude | O66: Security architecture/framework; no protocol eval method/testbed.
A67: 65 | B67: IEEE | C67: =HYPERLINK(IEEE_NEW!$P67, IEEE_NEW!$A67) -> Implementation of Cyber-Physical Systems with Modbus Communication for Security Studies | D67: 6 | E67: O | I67: =IF(AND(D67>=1, D67<=4), "X", "") | L67: X | N67: =IF(COUNTIF(F67:M67,"X")>0,"Exclude",IF(UPPER(TRIM(E67))="O","Include","")) -> Exclude | O67: build a CPS test setup for security studies using Modbus/TCP, does not do a protocol evaluation study (no protocol comparison, no defined evaluation method/metrics for assessing protocols).
A68: 66 | B68: IEEE | C68: =HYPERLINK(IEEE_NEW!$P68, IEEE_NEW!$A68) -> Improving operational security for web-based distributed control systems in wastewater management | D68: 5 | E68: O | I68: =IF(AND(D68>=1, D68<=4), "X", "") | L68: X | M68: X | N68: =IF(COUNTIF(F68:M68,"X")>0,"Exclude",IF(UPPER(TRIM(E68))="O","Include","")) -> Exclude | O68: System security discussion; no protocol evaluation method/testbed.
A69: 67 | B69: IEEE | C69: =HYPERLINK(IEEE_NEW!$P69, IEEE_NEW!$A69) -> Holistic Risk Assessment in Industrial Control Systems: Combining Multiple Bayesian Networks with Multi-Criteria Decision Making | D69: 6 | E69: O | I69: =IF(AND(D69>=1, D69<=4), "X", "") | L69: X | M69: X | N69: =IF(COUNTIF(F69:M69,"X")>0,"Exclude",IF(UPPER(TRIM(E69))="O","Include","")) -> Exclude | O69: Risk assessment method, not protocol evaluation (EC7)
A70: 68 | B70: IEEE | C70: =HYPERLINK(IEEE_NEW!$P70, IEEE_NEW!$A70) -> Adversarial Generation of Modbus TCP Packets Using WGANs for ICS Security Testing | D70: 6 | E70: O | I70: =IF(AND(D70>=1, D70<=4), "X", "") | L70: X | N70: =IF(COUNTIF(F70:M70,"X")>0,"Exclude",IF(UPPER(TRIM(E70))="O","Include","")) -> Exclude | O70: synthetic Modbus/TCP packet generation for IDS/robustness testing, not experimental/theoretical evaluation of communication protocols
A71: 69 | B71: IEEE | C71: =HYPERLINK(IEEE_NEW!$P71, IEEE_NEW!$A71) -> ML-Augmented Network Packet Broker based Anomaly Detection at IIoT-Edge Egress Port | D71: 6 | E71: O | I71: =IF(AND(D71>=1, D71<=4), "X", "") | L71: X | M71: X | N71: =IF(COUNTIF(F71:M71,"X")>0,"Exclude",IF(UPPER(TRIM(E71))="O","Include","")) -> Exclude | O71: Anomaly detection system; not protocol evaluation framework.
A72: 70 | B72: IEEE | C72: =HYPERLINK(IEEE_NEW!$P72, IEEE_NEW!$A72) -> Timeliness of CSMA/CA-Based Wireless Networks With HARQ in the FBL Regime: Explicit Age Characterizations and Resource Allocation | D72: 13 | E72: O | H72: X | I72: =IF(AND(D72>=1, D72<=4), "X", "") | M72: X | N72: =IF(COUNTIF(F72:M72,"X")>0,"Exclude",IF(UPPER(TRIM(E72))="O","Include","")) -> Exclude | O72: Wireless MAC theory, not industrial protocol eval (EC3)
A73: 71 | B73: IEEE | C73: =HYPERLINK(IEEE_NEW!$P73, IEEE_NEW!$A73) -> Performance Evaluation of Asynchronous Pulse Code Multiple Access in Massive IoT Networks | D73: 14 | E73: O | H73: X | I73: =IF(AND(D73>=1, D73<=4), "X", "") | M73: X | N73: =IF(COUNTIF(F73:M73,"X")>0,"Exclude",IF(UPPER(TRIM(E73))="O","Include","")) -> Exclude | O73: IoT PHY/MAC, not industrial automation protocol eval (EC3)
A74: 72 | B74: IEEE | C74: =HYPERLINK(IEEE_NEW!$P74, IEEE_NEW!$A74) -> Performance impact of commercial industrial firewalls on networked control systems | D74: 8 | E74: O | I74: =IF(AND(D74>=1, D74<=4), "X", "") | L74: X | N74: =IF(COUNTIF(F74:M74,"X")>0,"Exclude",IF(UPPER(TRIM(E74))="O","Include","")) -> Exclude | O74: Evaluates firewalls (a security device/control), not communication protocols themselves.
A75: 73 | B75: IEEE | C75: =HYPERLINK(IEEE_NEW!$P75, IEEE_NEW!$A75) -> Performance Evaluation and Modeling of an Industrial Application-Layer Firewall | D75: 12 | E75: O | I75: =IF(AND(D75>=1, D75<=4), "X", "") | L75: X | N75: =IF(COUNTIF(F75:M75,"X")>0,"Exclude",IF(UPPER(TRIM(E75))="O","Include","")) -> Exclude | O75: evaluates and models the performance impact of a security device
A76: 74 | B76: IEEE | C76: =HYPERLINK(IEEE_NEW!$P76, IEEE_NEW!$A76) -> An Investigative Evaluation of Open Source Intrusion Detection Systems for Operational Technology Networks Using MITRE ICS Attack Simulation on a Thermal Power Plant Test Bed | D76: 6 | E76: O | I76: =IF(AND(D76>=1, D76<=4), "X", "") | L76: X | M76: X | N76: =IF(COUNTIF(F76:M76,"X")>0,"Exclude",IF(UPPER(TRIM(E76))="O","Include","")) -> Exclude | O76: Evaluates IDS tools, not comm protocols.
A77: 75 | B77: IEEE | C77: =HYPERLINK(IEEE_NEW!$P77, IEEE_NEW!$A77) -> Future of IoTSP – IT and OT Integration | D77: 5 | E77: O | I77: =IF(AND(D77>=1, D77<=4), "X", "") | L77: X | M77: X | N77: =IF(COUNTIF(F77:M77,"X")>0,"Exclude",IF(UPPER(TRIM(E77))="O","Include","")) -> Exclude | O77: Integration/position topic; no protocol evaluation method or metrics focus.
A78: 76 | B78: IEEE | C78: =HYPERLINK(IEEE_NEW!$P78, IEEE_NEW!$A78) -> An Adaptive Intrusion Detection System for IoT Networks Using Deep Learning | D78: 6 | E78: O | H78: X | I78: =IF(AND(D78>=1, D78<=4), "X", "") | L78: X | M78: X | N78: =IF(COUNTIF(F78:M78,"X")>0,"Exclude",IF(UPPER(TRIM(E78))="O","Include","")) -> Exclude | O78: IDS/IoT, not protocol evaluation (EC7/EC3)
A79: 77 | B79: IEEE | C79: =HYPERLINK(IEEE_NEW!$P79, IEEE_NEW!$A79) -> Unleashing the Potential of Industrial IoT and Industry 5.0 | D79: 13 | E79: O | I79: =IF(AND(D79>=1, D79<=4), "X", "") | L79: X | N79: =IF(COUNTIF(F79:M79,"X")>0,"Exclude",IF(UPPER(TRIM(E79))="O","Include","")) -> Exclude | O79: a testbed experiment on 6TiSCH scheduling schemes
A80: 78 | B80: IEEE | C80: =HYPERLINK(IEEE_NEW!$P80, IEEE_NEW!$A80) -> SenseFuzz: Black-box Fuzzing of ICS Protocols via Runtime Statistics Sensing | D80: 6 | E80: O | I80: =IF(AND(D80>=1, D80<=4), "X", "") | N80: =IF(COUNTIF(F80:M80,"X")>0,"Exclude",IF(UPPER(TRIM(E80))="O","Include","")) -> Include | O80: improving protocol security evaluation (black-box fuzzing) and testing multiple ICS protocol programs
A81: 79 | B81: IEEE | C81: =HYPERLINK(IEEE_NEW!$P81, IEEE_NEW!$A81) -> PIM-LLN: Protocol Independent Multicast for Low-Power and Lossy Networks | D81: 17 | E81: O | H81: X | I81: =IF(AND(D81>=1, D81<=4), "X", "") | M81: X | N81: =IF(COUNTIF(F81:M81,"X")>0,"Exclude",IF(UPPER(TRIM(E81))="O","Include","")) -> Exclude | O81: Generic networking protocol, not industrial automation (EC3)
A82: 80 | B82: IEEE | C82: =HYPERLINK(IEEE_NEW!$P82, IEEE_NEW!$A82) -> Optimizing Freshness in IoT Scans | D82: 6 | E82: O | I82: =IF(AND(D82>=1, D82<=4), "X", "") | L82: X | M82: X | N82: =IF(COUNTIF(F82:M82,"X")>0,"Exclude",IF(UPPER(TRIM(E82))="O","Include","")) -> Exclude | O82: IoT scanning, not protocol evaluation (EC7)
A83: 81 | B83: IEEE | C83: =HYPERLINK(IEEE_NEW!$P83, IEEE_NEW!$A83) -> PQ-CAN: A Framework for Simulating Post-Quantum Cryptography in Embedded Systems | D83: 6 | E83: O | H83: X | I83: =IF(AND(D83>=1, D83<=4), "X", "") | M83: X | N83: =IF(COUNTIF(F83:M83,"X")>0,"Exclude",IF(UPPER(TRIM(E83))="O","Include","")) -> Exclude | O83: Crypto simulation in embedded; not clearly ICS/industrial protocol evaluation.
A84: 82 | B84: IEEE | C84: =HYPERLINK(IEEE_NEW!$P84, IEEE_NEW!$A84) -> Experimenting With Digital Signatures Over a DNP3 Protocol in a Multitenant Cloud-Based SCADA Architecture | D84: 20 | E84: O | I84: =IF(AND(D84>=1, D84<=4), "X", "") | N84: =IF(COUNTIF(F84:M84,"X")>0,"Exclude",IF(UPPER(TRIM(E84))="O","Include","")) -> Include | O84: It modifies DNP3 to carry digital signatures and then measures the performance overhead in an ICS/SCADA setup (RTU↔MTU). That’s protocol security + performance evaluation, not just “security discussion.”
A85: 83 | B85: IEEE | C85: =HYPERLINK(IEEE_NEW!$P85, IEEE_NEW!$A85) -> Analysis of Machine Learning Methods in EtherCAT-Based Anomaly Detection | D85: 10 | E85: O | I85: =IF(AND(D85>=1, D85<=4), "X", "") | L85: X | N85: =IF(COUNTIF(F85:M85,"X")>0,"Exclude",IF(UPPER(TRIM(E85))="O","Include","")) -> Exclude | O85: evaluates machine-learning models for anomaly detection on EtherCAT traffic
A86: 84 | B86: IEEE | C86: =HYPERLINK(IEEE_NEW!$P86, IEEE_NEW!$A86) -> Time Synchronization Extension for the IO-Link Industrial Communication Protocol | D86: 6 | E86: O | I86: =IF(AND(D86>=1, D86<=4), "X", "") | N86: =IF(COUNTIF(F86:M86,"X")>0,"Exclude",IF(UPPER(TRIM(E86))="O","Include","")) -> Include | O86: primary objective is a protocol extension plus a prototype + performance evaluation (sync error/jitter measurements, sub-µs with 32-bit timer).
A87: 85 | B87: IEEE | C87: =HYPERLINK(IEEE_NEW!$P87, IEEE_NEW!$A87) -> Industrial data-collector by enabling OPC-UA standard for Industry 4.0 | D87: 8 | E87: O | I87: =IF(AND(D87>=1, D87<=4), "X", "") | L87: X | M87: X | N87: =IF(COUNTIF(F87:M87,"X")>0,"Exclude",IF(UPPER(TRIM(E87))="O","Include","")) -> Exclude | O87: Implementation/project, not evaluation (EC7)
A88: 86 | B88: IEEE | C88: =HYPERLINK(IEEE_NEW!$P88, IEEE_NEW!$A88) -> Priority-Aware Wireless Fieldbus Protocol for Mixed-Criticality Industrial Wireless Sensor Networks | D88: 14 | E88: O | I88: =IF(AND(D88>=1, D88<=4), "X", "") | N88: =IF(COUNTIF(F88:M88,"X")>0,"Exclude",IF(UPPER(TRIM(E88))="O","Include","")) -> Include | O88: contribution is a new wireless fieldbus/MAC protocol for mixed-criticality traffic, plus analytical + simulation evaluation (worst-case delay bounds for safety traffic, throughput and average delay for control traffic, on-time delivery ratio).
A89: 87 | B89: IEEE | C89: =HYPERLINK(IEEE_NEW!$P89, IEEE_NEW!$A89) -> DigSiNet: Using Multiple Digital Twins to Provide Rhythmic Network Consistency | D89: 5 | E89: O | I89: =IF(AND(D89>=1, D89<=4), "X", "") | L89: X | M89: X | N89: =IF(COUNTIF(F89:M89,"X")>0,"Exclude",IF(UPPER(TRIM(E89))="O","Include","")) -> Exclude | O89: Digital twins consistency, not protocol evaluation (EC7)
A90: 88 | B90: IEEE | C90: =HYPERLINK(IEEE_NEW!$P90, IEEE_NEW!$A90) -> Detection of Attacks on Modbus Industrial Communications Using the Communication Variable Memory Map Representation | D90: 9 | E90: O | I90: =IF(AND(D90>=1, D90<=4), "X", "") | L90: X | M90: X | N90: =IF(COUNTIF(F90:M90,"X")>0,"Exclude",IF(UPPER(TRIM(E90))="O","Include","")) -> Exclude | O90: Attack detection/IDS on Modbus, not evaluating the protocol itself
A91: 89 | B91: IEEE | C91: =HYPERLINK(IEEE_NEW!$P91, IEEE_NEW!$A91) -> IEC 61850 Compatible OpenPLC for Cyber Attack Case Studies on Smart Substation Systems | D91: 10 | E91: O | H91: X | I91: =IF(AND(D91>=1, D91<=4), "X", "") | N91: =IF(COUNTIF(F91:M91,"X")>0,"Exclude",IF(UPPER(TRIM(E91))="O","Include","")) -> Exclude | O91: contribution as a PLC emulator extension + cyber range use for attack/defense experiments, not a conceptual model/testbed whose primary aim is protocol evaluation/benchmarking across protocols or configurations
A92: 90 | B92: IEEE | C92: =HYPERLINK(IEEE_NEW!$P92, IEEE_NEW!$A92) -> A Logical Performance Evaluation Methodology based on Bandwidth Estimation Strategy to Minimize Communication Delay over Wireless Sensor Networks | D92: 7 | E92: O | H92: X | I92: =IF(AND(D92>=1, D92<=4), "X", "") | M92: X | N92: =IF(COUNTIF(F92:M92,"X")>0,"Exclude",IF(UPPER(TRIM(E92))="O","Include","")) -> Exclude | O92: Generic WSN method, not industrial automation protocol focus (EC3)
A93: 91 | B93: IEEE | C93: =HYPERLINK(IEEE_NEW!$P93, IEEE_NEW!$A93) -> Exploiting Control Device Vulnerabilities: Attacking Cyber-Physical Water System | D93: 10 | E93: O | I93: =IF(AND(D93>=1, D93<=4), "X", "") | L93: X | M93: X | N93: =IF(COUNTIF(F93:M93,"X")>0,"Exclude",IF(UPPER(TRIM(E93))="O","Include","")) -> Exclude | O93: Attacks, not protocol evaluation (EC7)
A94: 92 | B94: IEEE | C94: =HYPERLINK(IEEE_NEW!$P94, IEEE_NEW!$A94) -> BIER-Based Multicast Routing for Low-Power and Lossy Networks | D94: 6 | E94: O | H94: X | I94: =IF(AND(D94>=1, D94<=4), "X", "") | L94: X | M94: X | N94: =IF(COUNTIF(F94:M94,"X")>0,"Exclude",IF(UPPER(TRIM(E94))="O","Include","")) -> Exclude | O94: Routing/multicast networking; not industrial protocol evaluation.
A95: 93 | B95: IEEE | C95: =HYPERLINK(IEEE_NEW!$P95, IEEE_NEW!$A95) -> Stealthy cyber attacks and impact analysis on wide-area protection of smart grid | D95: 6 | E95: O | I95: =IF(AND(D95>=1, D95<=4), "X", "") | L95: X | M95: X | N95: =IF(COUNTIF(F95:M95,"X")>0,"Exclude",IF(UPPER(TRIM(E95))="O","Include","")) -> Exclude | O95: Attack analysis, not protocol evaluation (EC7)
A96: 94 | B96: IEEE | C96: =HYPERLINK(IEEE_NEW!$P96, IEEE_NEW!$A96) -> Knowledge Representation of Asset Information and Performance in OT Environments | D96: 8 | E96: O | I96: =IF(AND(D96>=1, D96<=4), "X", "") | L96: X | M96: X | N96: =IF(COUNTIF(F96:M96,"X")>0,"Exclude",IF(UPPER(TRIM(E96))="O","Include","")) -> Exclude | O96: Asset modelling/representation; not protocol eval/testbed.
A97: 95 | B97: IEEE | C97: =HYPERLINK(IEEE_NEW!$P97, IEEE_NEW!$A97) -> IoT Communication Framework with Ground Station Integration Using MQTT over TCP | D97: 6 | E97: O | H97: X | I97: =IF(AND(D97>=1, D97<=4), "X", "") | M97: X | N97: =IF(COUNTIF(F97:M97,"X")>0,"Exclude",IF(UPPER(TRIM(E97))="O","Include","")) -> Exclude | O97: Ground station domain, not industrial automation (EC3)
A98: 96 | B98: IEEE | C98: =HYPERLINK(IEEE_NEW!$P98, IEEE_NEW!$A98) -> CRT-LoRa: An efficient and reliable MAC scheme for real-time industrial applications | D98: 6 | E98: O | I98: =IF(AND(D98>=1, D98<=4), "X", "") | L98: X | M98: X | N98: =IF(COUNTIF(F98:M98,"X")>0,"Exclude",IF(UPPER(TRIM(E98))="O","Include","")) -> Exclude | O98: MAC scheme design; not protocol evaluation framework/testbed.
A99: 97 | B99: IEEE | C99: =HYPERLINK(IEEE_NEW!$P99, IEEE_NEW!$A99) -> DIIG: A Distributed Industrial IoT Gateway | D99: 5 | E99: O | I99: =IF(AND(D99>=1, D99<=4), "X", "") | L99: X | M99: X | N99: =IF(COUNTIF(F99:M99,"X")>0,"Exclude",IF(UPPER(TRIM(E99))="O","Include","")) -> Exclude | O99: Gateway architecture, not protocol evaluation (EC7)
A100: 98 | B100: IEEE | C100: =HYPERLINK(IEEE_NEW!$P100, IEEE_NEW!$A100) -> The Role of Monitoring Frequency in Optimizing Digital Twin Networks | D100: 7 | E100: O | I100: =IF(AND(D100>=1, D100<=4), "X", "") | L100: X | M100: X | N100: =IF(COUNTIF(F100:M100,"X")>0,"Exclude",IF(UPPER(TRIM(E100))="O","Include","")) -> Exclude | O100: Digital-twin monitoring strategy, not comm protocol evaluation
...

Sheet Fulltext_Screening
A1: Identifier | B1: Database | C1: Title | D1: Number of pages | E1: Done (mark with 'O') | F1: IC1 | G1: IC2 | H1: IC3 | I1: IC4 | J1: EC1 | K1: EC2 | L1: EC3 | M1: EC4 | N1: EC5 | O1: EC6 | P1: EC7 | Q1: Decision | R1: Motivation
A2: 0 | B2: IEEE | C2: =HYPERLINK(IEEE_NEW!$P2, IEEE_NEW!$A2) -> Towards a modular security testing framework for industrial automation and control systems: ISuTest | D2: 5 | E2: O | F2: X | G2: X | H2: X | I2: X | M2: =IF(AND(D2>=1, D2<=4), "X", "") | P2: X | Q2: =IF(OR(COUNTIF(J2:P2,"X")>0,COUNTIF(F2:I2,"X")<>4),"Exclude",IF(UPPER(TRIM(E2))="O","Include","")) -> Exclude | R2: Focusing on black-box vulnerability and communication robustness testing of IACS devices, not protocols
A3: 6 | B3: IEEE | C3: =HYPERLINK(IEEE_NEW!$P8, IEEE_NEW!$A8) -> Performance Evaluation of MQTT and CoAP Communication Protocols in IIoT for Electrical Substations Based on the IEC 61850 Standard | D3: 6 | E3: O | F3: X | G3: X | H3: X | I3: X | M3: =IF(AND(D3>=1, D3<=4), "X", "") | Q3: =IF(COUNTIF(J3:P3,"X")>0,"Exclude",IF(UPPER(TRIM(E3))="O","Include","")) -> Include | R3: Industrial power/IEC 61850 context + MQTT/CoAP + IEC 61850–IIoT test bench | Z3: Statistics (total) | AA3: Count | AB3: Percentage
A4: 9 | B4: IEEE | C4: =HYPERLINK(IEEE_NEW!$P11, IEEE_NEW!$A11) -> Developing a Security Testbed for Industrial Internet of Things | D4: 16 | E4: O | F4: X | G4: X | H4: X | I4: X | M4: =IF(AND(D4>=1, D4<=4), "X", "") | Q4: =IF(COUNTIF(J4:P4,"X")>0,"Exclude",IF(UPPER(TRIM(E4))="O","Include","")) -> Include | R4: Industrial/brownfield IIoT + security testbed aimed at assessment | Z4: Total papers: | AA4: =COUNTIF(A2:A25,"<>") -> 24
A5: 11 | B5: IEEE | C5: =HYPERLINK(IEEE_NEW!$P13, IEEE_NEW!$A13) -> A Comparative Analysis of Application Layer Protocols Within an Industrial Internet of Things Monitoring System | D5: 6 | E5: O | F5: X | G5: X | H5: X | I5: X | M5: =IF(AND(D5>=1, D5<=4), "X", "") | Q5: =IF(COUNTIF(J5:P5,"X")>0,"Exclude",IF(UPPER(TRIM(E5))="O","Include","")) -> Include | R5: Industrial monitoring context + protocol selection + experimental setup built for industrial scenario | Z5: Number excluded: | AA5: =COUNTIF(Q2:Q25,"Exclude") -> 11 | AB5: =(($AA5/$AA4)) -> 0.45833333
A6: 16 | B6: IEEE | C6: =HYPERLINK(IEEE_NEW!$P18, IEEE_NEW!$A18) -> A dual-standard solution for industrial Wireless Sensor Network deployment: Experimental testbed and performance evaluation | D6: 9 | E6: O | F6: X | G6: X | H6: X | I6: X | M6: =IF(AND(D6>=1, D6<=4), "X", "") | Q6: =IF(COUNTIF(J6:P6,"X")>0,"Exclude",IF(UPPER(TRIM(E6))="O","Include","")) -> Include | R6: Industrial WSN + named industrial protocols + real testbed + KPI performance evaluation | Z6: Number included: | AA6: =COUNTIF(Q2:Q25,"Include") -> 13 | AB6: =(($AA6/$AA4)) -> 0.54166667
A7: 17 | B7: IEEE | C7: =HYPERLINK(IEEE_NEW!$P19, IEEE_NEW!$A19) -> Enhancing Industrial Communication Protocol Fuzz Testing Through Virtualization And Intelligent Guidance | D7: 5 | E7: O | F7: X | G7: X | H7: X | I7: X | M7: =IF(AND(D7>=1, D7<=4), "X", "") | P7: X | Q7: =IF(COUNTIF(J7:P7,"X")>0,"Exclude",IF(UPPER(TRIM(E7))="O","Include","")) -> Exclude | R7: Focuses on enhancement of a fuzzing method (evaluation method improvement), targeting vulnerability finding, not an evaluation framework for comparing proötocols or their runtime performance/security trade-offs. | Z7: Type violation:
A8: 21 | B8: IEEE | C8: =HYPERLINK(IEEE_NEW!$P23, IEEE_NEW!$A23) -> A Comparative Study to Evaluate the Performance of Communication Protocols for Process Industry | D8: 8 | E8: O | F8: X | G8: X | H8: X | I8: X | M8: =IF(AND(D8>=1, D8<=4), "X", "") | Q8: =IF(COUNTIF(J8:P8,"X")>0,"Exclude",IF(UPPER(TRIM(E8))="O","Include","")) -> Include | R8: Industrial process setting + software-based test environment to evaluate protocol performance | Z8: EC1 | AA8: =COUNTIF(J$2:J$25,"X") -> 0 | AB8: =(($AA8/$AA$4)) -> 0
A9: 36 | B9: IEEE | C9: =HYPERLINK(IEEE_NEW!$P38, IEEE_NEW!$A38) -> Security and Effectiveness Analysis of the Gateway Integrity Checking Protocol | D9: 9 | E9: O | F9: X | I9: X | M9: =IF(AND(D9>=1, D9<=4), "X", "") | P9: X | Q9: =IF(COUNTIF(J9:P9,"X")>0,"Exclude",IF(UPPER(TRIM(E9))="O","Include","")) -> Exclude | R9: Focus is a gateway integrity protocol (GIP), not industrial information-exchange protocols evaluation/testbeds | Z9: EC2 | AA9: =COUNTIF(K$2:K$25,"X") -> 0 | AB9: =(($AA9/$AA$4)) -> 0
A10: 40 | B10: IEEE | C10: =HYPERLINK(IEEE_NEW!$P42, IEEE_NEW!$A42) -> Towards Performance Benchmarking of Cyclic OPC UA PubSub over TSN | D10: 8 | E10: O | F10: X | G10: X | H10: X | I10: X | M10: =IF(AND(D10>=1, D10<=4), "X", "") | Q10: =IF(COUNTIF(J10:P10,"X")>0,"Exclude",IF(UPPER(TRIM(E10))="O","Include","")) -> Include | R10: Industrial automation + OPC UA PubSub/TSN + experimental setup for performance benchmarking | Z10: EC3 | AA10: =COUNTIF(L$2:L$25,"X") -> 0 | AB10: =(($AA10/$AA$4)) -> 0
A11: 57 | B11: IEEE | C11: =HYPERLINK(IEEE_NEW!$P59, IEEE_NEW!$A59) -> End-to-End Delay Evaluation of Industrial Automation Systems Based on EtherCAT | D11: 8 | E11: O | F11: X | G11: X | H11: X | I11: X | M11: =IF(AND(D11>=1, D11<=4), "X", "") | Q11: =IF(COUNTIF(J11:P11,"X")>0,"Exclude",IF(UPPER(TRIM(E11))="O","Include","")) -> Include | R11: Industrial automation + EtherCAT + simulation-based evaluation setup for end-to-end delay | Z11: EC4 | AA11: =COUNTIF(M$2:M$25,"X") -> 0 | AB11: =(($AA11/$AA$4)) -> 0
A12: 78 | B12: IEEE | C12: =HYPERLINK(IEEE_NEW!$P80, IEEE_NEW!$A80) -> SenseFuzz: Black-box Fuzzing of ICS Protocols via Runtime Statistics Sensing | D12: 6 | E12: O | F12: X | G12: X | H12: X | I12: X | M12: =IF(AND(D12>=1, D12<=4), "X", "") | P12: X | Q12: =IF(COUNTIF(J12:P12,"X")>0,"Exclude",IF(UPPER(TRIM(E12))="O","Include","")) -> Exclude | R12: Focuses on enhancement of a fuzzing method (evaluation method improvement), method for improving protocol security testing. does not evaluate protocol behaviour, performance, or trade-offs in an industrial communication setup. | Z12: EC5 | AA12: =COUNTIF(N$2:N$25,"X") -> 0 | AB12: =(($AA12/$AA$4)) -> 0
A13: 82 | B13: IEEE | C13: =HYPERLINK(IEEE_NEW!$P84, IEEE_NEW!$A84) -> Experimenting With Digital Signatures Over a DNP3 Protocol in a Multitenant Cloud-Based SCADA Architecture | D13: 20 | E13: O | F13: X | G13: X | I13: X | M13: =IF(AND(D13>=1, D13<=4), "X", "") | P13: X | Q13: =IF(COUNTIF(J13:P13,"X")>0,"Exclude",IF(UPPER(TRIM(E13))="O","Include","")) -> Exclude | R13: Focus is adding security (signatures) and measuring overhead in one architecture; not a reusable evaluation framework/testbed for protocol comparison | Z13: EC6 | AA13: =COUNTIF(O$2:O$25,"X") -> 0 | AB13: =(($AA13/$AA$4)) -> 0
A14: 84 | B14: IEEE | C14: =HYPERLINK(IEEE_NEW!$P86, IEEE_NEW!$A86) -> Time Synchronization Extension for the IO-Link Industrial Communication Protocol | D14: 6 | E14: O | F14: X | G14: X | I14: X | M14: =IF(AND(D14>=1, D14<=4), "X", "") | P14: X | Q14: =IF(COUNTIF(J14:P14,"X")>0,"Exclude",IF(UPPER(TRIM(E14))="O","Include","")) -> Exclude | R14: Primary goal is protocol extension/design, not protocol evaluation framework/testbed | Z14: EC7 | AA14: =COUNTIF(P$2:P$25,"X") -> 11 | AB14: =(($AA14/$AA$4)) -> 0.45833333
A15: 86 | B15: IEEE | C15: =HYPERLINK(IEEE_NEW!$P88, IEEE_NEW!$A88) -> Priority-Aware Wireless Fieldbus Protocol for Mixed-Criticality Industrial Wireless Sensor Networks | D15: 14 | E15: O | F15: X | G15: X | H15: X | I15: X | M15: =IF(AND(D15>=1, D15<=4), "X", "") | P15: X | Q15: =IF(COUNTIF(J15:P15,"X")>0,"Exclude",IF(UPPER(TRIM(E15))="O","Include","")) -> Exclude | R15: Primary goal is designing a new protocol, not evaluating existing protocols / evaluation methods | Z15: IC1 | AA15: =COUNTIF(F$2:F$25,"<>X") -> 0 | AB15: =(($AA15/$AA$4)) -> 0
A16: 101 | B16: ACM DL | C16: =HYPERLINK(ACM_NEW!$D3, ACM_NEW!$B3) -> RTPL: A Real-Time Communication Protocol for LoRa Network | D16: 31 | E16: O | F16: X | G16: X | H16: X | I16: X | M16: =IF(AND(D16>=1, D16<=4), "X", "") | P16: X | Q16: =IF(COUNTIF(J16:P16,"X")>0,"Exclude",IF(UPPER(TRIM(E16))="O","Include","")) -> Exclude | R16: Primary goal is new protocol design for LoRa, not evaluation of existing industrial protocols / evaluation methods for them | Z16: IC2 | AA16: =COUNTIF(G$2:G$25,"<>X") -> 1 | AB16: =(($AA16/$AA$4)) -> 0.041666667
A17: 102 | B17: ACM DL | C17: =HYPERLINK(ACM_NEW!$D4, ACM_NEW!$B4) -> EmuFlex: A Flexible OT Testbed for Security Experiments with OPC UA | D17: 9 | E17: O | F17: X | G17: X | H17: X | I17: X | M17: =IF(AND(D17>=1, D17<=4), "X", "") | P17: X | Q17: =IF(COUNTIF(J17:P17,"X")>0,"Exclude",IF(UPPER(TRIM(E17))="O","Include","")) -> Exclude | R17: OT/IIoT + OPC UA + virtual testbed for security experiments, not protocol evaluation | Z17: IC3 | AA17: =COUNTIF(H$2:H$25,"<>X") -> 5 | AB17: =(($AA17/$AA$4)) -> 0.20833333
A18: 106 | B18: ACM DL | C18: =HYPERLINK(ACM_NEW!$D8, ACM_NEW!$B8) -> Examining the Suitability of Stream Ciphers for Modbus-TCP Encryption on Resource Constrained Devices | D18: 7 | E18: O | F18: X | G18: X | I18: X | M18: =IF(AND(D18>=1, D18<=4), "X", "") | P18: X | Q18: =IF(COUNTIF(J18:P18,"X")>0,"Exclude",IF(UPPER(TRIM(E18))="O","Include","")) -> Exclude | R18: Focus is crypto choice for Modbus-TCP encryption (component-level), not a reusable protocol evaluation framework/testbed | Z18: IC4 | AA18: =COUNTIF(I$2:I$25,"<>X") -> 1 | AB18: =(($AA18/$AA$4)) -> 0.041666667
A19: 123 | B19: ACM DL | C19: =HYPERLINK(ACM_NEW!$D25, ACM_NEW!$B25) -> Enabling Industry 4.0 Communication Protocol Interoperability: An OPC UA Case Study | D19: 9 | E19: O | F19: X | G19: X | M19: =IF(AND(D19>=1, D19<=4), "X", "") | P19: X | Q19: =IF(COUNTIF(J19:P19,"X")>0,"Exclude",IF(UPPER(TRIM(E19))="O","Include","")) -> Exclude | R19: Primary goal is integration/interoperability guidance, not protocol evaluation/benchmarking/testbed
A20: 141 | B20: SCOPUS | C20: =HYPERLINK(SCOPUS_NEW!$N4, SCOPUS_NEW!$D4) -> Exponential Backoff and Its Security Implications for Safety-Critical OT Protocols over TCP/IP Networks | D20: 0 | E20: O | F20: X | G20: X | H20: X | I20: X | M20: =IF(AND(D20>=1, D20<=4), "X", "") | Q20: =IF(COUNTIF(J20:P20,"X")>0,"Exclude",IF(UPPER(TRIM(E20))="O","Include","")) -> Include | R20: OT/IIoT + performance/security implications tied to TCP/IP behaviour affecting OT protocols + analysis aimed at evaluating robustness/performance impacts
A21: 149 | B21: SCOPUS | C21: =HYPERLINK(SCOPUS_NEW!$N12, SCOPUS_NEW!$D12) -> OPC-UA in interoperability - a performance comparative testing | D21: 5 | E21: O | F21: X | G21: X | H21: X | I21: X | M21: =IF(AND(D21>=1, D21<=4), "X", "") | Q21: =IF(COUNTIF(J21:P21,"X")>0,"Exclude",IF(UPPER(TRIM(E21))="O","Include","")) -> Include | R21: OPC UA + comparative performance testing approach for interoperability context
A22: 162 | B22: SCOPUS | C22: =HYPERLINK(SCOPUS_NEW!$N25, SCOPUS_NEW!$D25) -> A performance analysis of internet of things networking protocols: Evaluating MQTT, CoAP, OPC UA | D22: 0 | E22: O | F22: X | G22: X | H22: X | I22: X | M22: =IF(AND(D22>=1, D22<=4), "X", "") | Q22: =IF(COUNTIF(J22:P22,"X")>0,"Exclude",IF(UPPER(TRIM(E22))="O","Include","")) -> Include | R22: Covers industrial IoT use + named protocols + local testbed experiments (and broader experiments) on performance
A23: 187 | B23: IEEE | C23: =HYPERLINK(IEEE_NEW!$P102, IEEE_NEW!$A102) -> A Testbed for Evaluating Performance and Cybersecurity Implications of IEC-61850 GOOSE Hardware Implementations | D23: 6 | E23: O | F23: X | G23: X | H23: X | I23: X | M23: =IF(AND(D23>=1, D23<=4), "X", "") | Q23: =IF(COUNTIF(J23:P23,"X")>0,"Exclude",IF(UPPER(TRIM(E23))="O","Include","")) -> Include | R23: primary objective is to propose a flexible testbed and use it to evaluate IEC‑61850 GOOSE implementations under DoS/Replay/FDIA, including performance measurements (traffic rates, saturation) and security implications.
A24: 188 | B24: IEEE | C24: =HYPERLINK(IEEE_NEW!$P103, IEEE_NEW!$A103) -> Benchmarking Cloud-Based SCADA System | D24: 8 | E24: O | F24: X | G24: X | H24: X | I24: X | M24: =IF(AND(D24>=1, D24<=4), "X", "") | Q24: =IF(COUNTIF(J24:P24,"X")>0,"Exclude",IF(UPPER(TRIM(E24))="O","Include","")) -> Include | R24: experimentally evaluates protocol behavior (Modbus TCP vs. IEC 60870‑5‑101) under different scenarios and introduces a benchmark framework (i.e., a method/testbed to evaluate such protocols). While the broader aim is cloud‑SCADA performance, protocol comparison and evaluation methodology are central.
A25: 193 | B25: IEEE | C25: =HYPERLINK(IEEE_NEW!$P108, IEEE_NEW!$A108) -> Virtual PLC in Industrial Edge Platform: Performance Evaluation of Supervision and Control Communication | D25: 10 | E25: O | F25: X | G25: X | H25: X | I25: X | M25: =IF(AND(D25>=1, D25<=4), "X", "") | Q25: =IF(COUNTIF(J25:P25,"X")>0,"Exclude",IF(UPPER(TRIM(E25))="O","Include","")) -> Include | R25: primary objective is the experimental evaluation of protocol‑level supervision communication (S7comm) between PLCs/vPLCs and the proposal of a reusable evaluation methodology/metrics
M26: =IF(AND(D26>=1, D26<=4), "X", "") | Q26: =IF(COUNTIF(J26:P26,"X")>0,"Exclude",IF(UPPER(TRIM(E26))="O","Include",""))

Sheet Snowballing-it1-before-duplicat
A1: Source | B1: Title | C1: Year | D1: Number of pages
A2: Citations | B2: =HYPERLINK('citations-it1-studies'!$D2,'citations-it1-studies'!$B2) -> Practical approaches towards IoT dataset generation for security experiments | C2: ='citations-it1-studies'!$C2 -> 2025 | D2: ='citations-it1-studies'!$H2 -> 65
A3: Citations | B3: =HYPERLINK('citations-it1-studies'!$D3,'citations-it1-studies'!$B3) -> Performance Evaluation of IoT-Enabled Edge Computing Infrastructure for mHealth Services | C3: ='citations-it1-studies'!$C3 -> 2025 | D3: ='citations-it1-studies'!$H3 -> 12
A4: Citations | B4: =HYPERLINK('citations-it1-studies'!$D4,'citations-it1-studies'!$B4) -> Learning Temporal and Spatial Features Jointly: A Unified Framework for Space-Time Data Prediction in Industrial IoT Networks | C4: ='citations-it1-studies'!$C4 -> 2023 | D4: ='citations-it1-studies'!$H4 -> 13
A5: Citations | B5: =HYPERLINK('citations-it1-studies'!$D5,'citations-it1-studies'!$B5) -> Design of 5G private network quality monitoring System based on edge computing | C5: ='citations-it1-studies'!$C5 -> 2023 | D5: ='citations-it1-studies'!$H5 -> 5
A6: Citations | B6: =HYPERLINK('citations-it1-studies'!$D6,'citations-it1-studies'!$B6) -> Evaluating the Latency Impact for Time-Critical Operational Technology Applications of Transitioning IEC-61850 GOOSE Operations to 5G | C6: ='citations-it1-studies'!$C6 -> 2024 | D6: ='citations-it1-studies'!$H6 -> 2
A7: Citations | B7: =HYPERLINK('citations-it1-studies'!$D7,'citations-it1-studies'!$B7) -> Challenges in Resource-Constrained IoT Devices: Energy and Communication as Critical Success Factors for Future IoT Deployment. | C7: ='citations-it1-studies'!$C7 -> 2020 | D7: ='citations-it1-studies'!$H7 -> 0
A8: Citations | B8: =HYPERLINK('citations-it1-studies'!$D8,'citations-it1-studies'!$B8) -> A forensic tool for the identification, acquisition and analysis of sources of evidence in IoT investigations | C8: ='citations-it1-studies'!$C8 -> 2024 | D8: ='citations-it1-studies'!$H8 -> 1
A9: Citations | B9: =HYPERLINK('citations-it1-studies'!$D9,'citations-it1-studies'!$B9) -> Construction of intelligent integrated model framework for the workshop manufacturing system via digital twin | C9: ='citations-it1-studies'!$C9 -> 2021 | D9: ='citations-it1-studies'!$H9 -> 14
A10: Citations | B10: =HYPERLINK('citations-it1-studies'!$D10,'citations-it1-studies'!$B10) -> Communication and Coordination for Multi AGVs Based on MQTT Protocol | C10: ='citations-it1-studies'!$C10 -> 2023 | D10: ='citations-it1-studies'!$H10 -> 6
A11: Citations | B11: =HYPERLINK('citations-it1-studies'!$D11,'citations-it1-studies'!$B11) -> QoSmart-IoT: Secure QoS-Based Reconfiguration and Protocol Adaptation for Hybrid Clustered IoT Systems in Constrained Environments | C11: ='citations-it1-studies'!$C11 -> 2025 | D11: ='citations-it1-studies'!$H11 -> 13
A12: Citations | B12: =HYPERLINK('citations-it1-studies'!$D12,'citations-it1-studies'!$B12) -> APT Adversarial Defence Mechanism for Industrial IoT Enabled Cyber-Physical System | C12: ='citations-it1-studies'!$C12 -> 2023 | D12: ='citations-it1-studies'!$H12 -> 21
A13: Citations | B13: =HYPERLINK('citations-it1-studies'!$D13,'citations-it1-studies'!$B13) -> Secure Communication Protocols: Safeguarding Information in The Digital Age | C13: ='citations-it1-studies'!$C13 -> 2025 | D13: ='citations-it1-studies'!$H13 -> 65
... A211: Citations | B211: =HYPERLINK('citations-it1-studies'!$D211,'citations-it1-studies'!$B211) -> The Significance of the Industrial Internet of Things (IIoT) for the Oil and Gas Space | C211: ='citations-it1-studies'!$C211 -> 2023 | D211: ='citations-it1-studies'!$H211 -> 30
A212: References | B212: =HYPERLINK('references-it1-studies'!$D2,'references-it1-studies'!$B2) -> CCS - POIROT: Aligning Attack Behavior with Kernel Audit Records for Cyber Threat Hunting | C212: ='references-it1-studies'!$C2 -> 2019 | D212: ='references-it1-studies'!$H2 -> 18
A213: References | B213: =HYPERLINK('references-it1-studies'!$D3,'references-it1-studies'!$B3) -> Man-in-the-middle-attack: Understanding in simple words | C213: ='references-it1-studies'!$C3 -> 2019 | D213: ='references-it1-studies'!$H3 -> 16
A214: References | B214: =HYPERLINK('references-it1-studies'!$D4,'references-it1-studies'!$B4) -> ICICS - S7commTrace: A High Interactive Honeypot for Industrial Control System Based on S7 Protocol | C214: ='references-it1-studies'!$C4 -> 2018 | D214: ='references-it1-studies'!$H4 -> 12
A215: References | B215: =HYPERLINK('references-it1-studies'!$D5,'references-it1-studies'!$B5) -> Integration of IoT Technologies into the Smart Grid. | C215: ='references-it1-studies'!$C5 -> 2022 | D215: ='references-it1-studies'!$H5 -> 1
A216: References | B216: =HYPERLINK('references-it1-studies'!$D6,'references-it1-studies'!$B6) -> Performance evaluation of CoAP and MQTT with security support for IoT environments | C216: ='references-it1-studies'!$C6 -> 2021 | D216: ='references-it1-studies'!$H6 -> 0
A217: References | B217: =HYPERLINK('references-it1-studies'!$D7,'references-it1-studies'!$B7) -> INFOCOM Workshops - Simulation of Industrial Wireless Sensor Network (IWSN) protocols | C217: ='references-it1-studies'!$C7 -> 2016 | D217: ='references-it1-studies'!$H7 -> 7
A218: References | B218: =HYPERLINK('references-it1-studies'!$D8,'references-it1-studies'!$B8) -> Computer Communication Within Industrial Distributed Environment—a Survey | C218: ='references-it1-studies'!$C8 -> 2013 | D218: ='references-it1-studies'!$H8 -> 8
A219: References | B219: =HYPERLINK('references-it1-studies'!$D9,'references-it1-studies'!$B9) -> Property Patterns for the Formal Verification of Automated Production Systemsstar | C219: ='references-it1-studies'!$C9 -> 2008 | D219: ='references-it1-studies'!$H9 -> 6
A220: References | B220: =HYPERLINK('references-it1-studies'!$D10,'references-it1-studies'!$B10) -> Digital transformation of manufacturing through cloud services and resource virtualization | C220: ='references-it1-studies'!$C10 -> 2019 | D220: ='references-it1-studies'!$H10 -> 13
A221: References | B221: =HYPERLINK('references-it1-studies'!$D11,'references-it1-studies'!$B11) -> WF-IoT - FIT IoT-LAB: A large scale open experimental IoT testbed | C221: ='references-it1-studies'!$C11 -> 2015 | D221: ='references-it1-studies'!$H11 -> 6
A222: References | B222: =HYPERLINK('references-it1-studies'!$D12,'references-it1-studies'!$B12) -> Container-based architecture for flexible industrial control applications | C222: ='references-it1-studies'!$C12 -> 2018 | D222: ='references-it1-studies'!$H12 -> 9
A223: References | B223: =HYPERLINK('references-it1-studies'!$D13,'references-it1-studies'!$B13) -> Interworking between Modbus and internet of things platform for industrial services | C223: ='references-it1-studies'!$C13 -> 2024 | D223: ='references-it1-studies'!$H13 -> 11
... A410: References | B410: =HYPERLINK('references-it1-studies'!$D200,'references-it1-studies'!$B200) -> IoT Fundamentals: Networking Technologies, Protocols, and Use Cases for the Internet of Things | C410: ='references-it1-studies'!$C200 -> 2017 | D410: ='references-it1-studies'!$H200 -> 0

Sheet Snowballing-it1-after-duplicate
A1: Source | B1: Title | C1: Year | D1: Number of pages
A2: Citations | B2: =HYPERLINK('citations-it1-studies'!$D2,'citations-it1-studies'!$B2) -> Practical approaches towards IoT dataset generation for security experiments | C2: ='citations-it1-studies'!$C2 -> 2025 | D2: ='citations-it1-studies'!$H2 -> 65
A3: Citations | B3: =HYPERLINK('citations-it1-studies'!$D3,'citations-it1-studies'!$B3) -> Performance Evaluation of IoT-Enabled Edge Computing Infrastructure for mHealth Services | C3: ='citations-it1-studies'!$C3 -> 2025 | D3: ='citations-it1-studies'!$H3 -> 12
A4: Citations | B4: =HYPERLINK('citations-it1-studies'!$D4,'citations-it1-studies'!$B4) -> Learning Temporal and Spatial Features Jointly: A Unified Framework for Space-Time Data Prediction in Industrial IoT Networks | C4: ='citations-it1-studies'!$C4 -> 2023 | D4: ='citations-it1-studies'!$H4 -> 13
A5: Citations | B5: =HYPERLINK('citations-it1-studies'!$D5,'citations-it1-studies'!$B5) -> Design of 5G private network quality monitoring System based on edge computing | C5: ='citations-it1-studies'!$C5 -> 2023 | D5: ='citations-it1-studies'!$H5 -> 5
A6: Citations | B6: =HYPERLINK('citations-it1-studies'!$D6,'citations-it1-studies'!$B6) -> Evaluating the Latency Impact for Time-Critical Operational Technology Applications of Transitioning IEC-61850 GOOSE Operations to 5G | C6: ='citations-it1-studies'!$C6 -> 2024 | D6: ='citations-it1-studies'!$H6 -> 2
A7: Citations | B7: =HYPERLINK('citations-it1-studies'!$D7,'citations-it1-studies'!$B7) -> Challenges in Resource-Constrained IoT Devices: Energy and Communication as Critical Success Factors for Future IoT Deployment. | C7: ='citations-it1-studies'!$C7 -> 2020 | D7: ='citations-it1-studies'!$H7 -> 0
A8: Citations | B8: =HYPERLINK('citations-it1-studies'!$D8,'citations-it1-studies'!$B8) -> A forensic tool for the identification, acquisition and analysis of sources of evidence in IoT investigations | C8: ='citations-it1-studies'!$C8 -> 2024 | D8: ='citations-it1-studies'!$H8 -> 1
A9: Citations | B9: =HYPERLINK('citations-it1-studies'!$D9,'citations-it1-studies'!$B9) -> Construction of intelligent integrated model framework for the workshop manufacturing system via digital twin | C9: ='citations-it1-studies'!$C9 -> 2021 | D9: ='citations-it1-studies'!$H9 -> 14
A10: Citations | B10: =HYPERLINK('citations-it1-studies'!$D10,'citations-it1-studies'!$B10) -> Communication and Coordination for Multi AGVs Based on MQTT Protocol | C10: ='citations-it1-studies'!$C10 -> 2023 | D10: ='citations-it1-studies'!$H10 -> 6
A11: Citations | B11: =HYPERLINK('citations-it1-studies'!$D11,'citations-it1-studies'!$B11) -> QoSmart-IoT: Secure QoS-Based Reconfiguration and Protocol Adaptation for Hybrid Clustered IoT Systems in Constrained Environments | C11: ='citations-it1-studies'!$C11 -> 2025 | D11: ='citations-it1-studies'!$H11 -> 13
A12: Citations | B12: =HYPERLINK('citations-it1-studies'!$D12,'citations-it1-studies'!$B12) -> APT Adversarial Defence Mechanism for Industrial IoT Enabled Cyber-Physical System | C12: ='citations-it1-studies'!$C12 -> 2023 | D12: ='citations-it1-studies'!$H12 -> 21
A13: Citations | B13: =HYPERLINK('citations-it1-studies'!$D13,'citations-it1-studies'!$B13) -> Secure Communication Protocols: Safeguarding Information in The Digital Age | C13: ='citations-it1-studies'!$C13 -> 2025 | D13: ='citations-it1-studies'!$H13 -> 65
... A161: Citations | B161: =HYPERLINK('citations-it1-studies'!$D161,'citations-it1-studies'!$B161) -> Connecting 3D Printer to the Industrial Internet of Things (IIoT) through MQTT Sparkplug B Protocol | C161: ='citations-it1-studies'!$C161 -> 2023 | D161: ='citations-it1-studies'!$H161 -> 6
A162: Citations | B162: =HYPERLINK('citations-it1-studies'!$D163,'citations-it1-studies'!$B163) -> SDN-DMQTT: SDN-Based Platform for Re-configurable MQTT Distributed Brokers Architecture | C162: ='citations-it1-studies'!$C163 -> 2024 | D162: ='citations-it1-studies'!$H163 -> 19
A163: Citations | B163: =HYPERLINK('citations-it1-studies'!$D164,'citations-it1-studies'!$B164) -> Survey on Wireless Technology Trade-Offs for the Industrial Internet of Things. | C163: ='citations-it1-studies'!$C164 -> 2020 | D163: ='citations-it1-studies'!$H164 -> 0
A164: Citations | B164: =HYPERLINK('citations-it1-studies'!$D165,'citations-it1-studies'!$B165) -> Shaping Intelligent Connectivity Using AI and IoT | C164: ='citations-it1-studies'!$C165 -> 2025 | D164: ='citations-it1-studies'!$H165 -> 42
A165: Citations | B165: =HYPERLINK('citations-it1-studies'!$D166,'citations-it1-studies'!$B166) -> Holistic Survey on Security in IoT Application Layer: Attacks, Protocols, and Applications | C165: ='citations-it1-studies'!$C166 -> 2024 | D165: ='citations-it1-studies'!$H166 -> 58
A166: Citations | B166: =HYPERLINK('citations-it1-studies'!$D167,'citations-it1-studies'!$B167) -> Big Data and Machine Learning in Industry 6.0 | C166: ='citations-it1-studies'!$C167 -> 2026 | D166: ='citations-it1-studies'!$H167 -> 27
A167: Citations | B167: =HYPERLINK('citations-it1-studies'!$D168,'citations-it1-studies'!$B168) -> Trend Analysis of Factory Automation Using Topic Modeling | C167: ='citations-it1-studies'!$C168 -> 2025 | D167: ='citations-it1-studies'!$H168 -> 1
A168: Citations | B168: =HYPERLINK('citations-it1-studies'!$D169,'citations-it1-studies'!$B169) -> Edge Computing for Safe Control of a Parametric Multi-floor Manufacturing Process | C168: ='citations-it1-studies'!$C169 -> 2025 | D168: ='citations-it1-studies'!$H169 -> 6
A169: Citations | B169: =HYPERLINK('citations-it1-studies'!$D170,'citations-it1-studies'!$B170) -> DDoS attack detection using CNN-BiLSTM with attention mechanism | C169: ='citations-it1-studies'!$C170 -> 2025 | D169: ='citations-it1-studies'!$H170 -> 1
A170: Citations | B170: =HYPERLINK('citations-it1-studies'!$D171,'citations-it1-studies'!$B171) -> Resilience Against APTs: A Provenance-Based IIoT Dataset for Cybersecurity Research | C170: ='citations-it1-studies'!$C171 -> 2026 | D170: ='citations-it1-studies'!$H171 -> 24
A171: Citations | B171: =HYPERLINK('citations-it1-studies'!$D172,'citations-it1-studies'!$B172) -> A Performance Analysis of Security Protocols for Distributed Measurement Systems Based on Internet of Things with Constrained Hardware and Open Source Infrastructures. | C171: ='citations-it1-studies'!$C172 -> 2024 | D171: ='citations-it1-studies'!$H172 -> 1
A172: Citations | B172: =HYPERLINK('citations-it1-studies'!$D173,'citations-it1-studies'!$B173) -> Comparative Analysis and Implementation of HTTP3, MQTT, and CoAP for IoT Applications | C172: ='citations-it1-studies'!$C173 -> 2024 | D172: ='citations-it1-studies'!$H173 -> 6
A173: Citations | B173: =HYPERLINK('citations-it1-studies'!$D174,'citations-it1-studies'!$B174) -> Comprehensive electrical models for a wireless sensor network device. | C173: ='citations-it1-studies'!$C174 -> 2024 | D173: ='citations-it1-studies'!$H174 -> 1
... A210: Citations | B210: =HYPERLINK('citations-it1-studies'!$D211,'citations-it1-studies'!$B211) -> The Significance of the Industrial Internet of Things (IIoT) for the Oil and Gas Space | C210: ='citations-it1-studies'!$C211 -> 2023 | D210: ='citations-it1-studies'!$H211 -> 30
A211: References | B211: =HYPERLINK('references-it1-studies'!$D2,'references-it1-studies'!$B2) -> CCS - POIROT: Aligning Attack Behavior with Kernel Audit Records for Cyber Threat Hunting | C211: ='references-it1-studies'!$C2 -> 2019 | D211: ='references-it1-studies'!$H2 -> 18
A212: References | B212: =HYPERLINK('references-it1-studies'!$D3,'references-it1-studies'!$B3) -> Man-in-the-middle-attack: Understanding in simple words | C212: ='references-it1-studies'!$C3 -> 2019 | D212: ='references-it1-studies'!$H3 -> 16
A213: References | B213: =HYPERLINK('references-it1-studies'!$D4,'references-it1-studies'!$B4) -> ICICS - S7commTrace: A High Interactive Honeypot for Industrial Control System Based on S7 Protocol | C213: ='references-it1-studies'!$C4 -> 2018 | D213: ='references-it1-studies'!$H4 -> 12
A214: References | B214: =HYPERLINK('references-it1-studies'!$D5,'references-it1-studies'!$B5) -> Integration of IoT Technologies into the Smart Grid. | C214: ='references-it1-studies'!$C5 -> 2022 | D214: ='references-it1-studies'!$H5 -> 1
A215: References | B215: =HYPERLINK('references-it1-studies'!$D6,'references-it1-studies'!$B6) -> Performance evaluation of CoAP and MQTT with security support for IoT environments | C215: ='references-it1-studies'!$C6 -> 2021 | D215: ='references-it1-studies'!$H6 -> 0
A216: References | B216: =HYPERLINK('references-it1-studies'!$D7,'references-it1-studies'!$B7) -> INFOCOM Workshops - Simulation of Industrial Wireless Sensor Network (IWSN) protocols | C216: ='references-it1-studies'!$C7 -> 2016 | D216: ='references-it1-studies'!$H7 -> 7
A217: References | B217: =HYPERLINK('references-it1-studies'!$D8,'references-it1-studies'!$B8) -> Computer Communication Within Industrial Distributed Environment—a Survey | C217: ='references-it1-studies'!$C8 -> 2013 | D217: ='references-it1-studies'!$H8 -> 8
A218: References | B218: =HYPERLINK('references-it1-studies'!$D9,'references-it1-studies'!$B9) -> Property Patterns for the Formal Verification of Automated Production Systemsstar | C218: ='references-it1-studies'!$C9 -> 2008 | D218: ='references-it1-studies'!$H9 -> 6
A219: References | B219: =HYPERLINK('references-it1-studies'!$D10,'references-it1-studies'!$B10) -> Digital transformation of manufacturing through cloud services and resource virtualization | C219: ='references-it1-studies'!$C10 -> 2019 | D219: ='references-it1-studies'!$H10 -> 13
A220: References | B220: =HYPERLINK('references-it1-studies'!$D11,'references-it1-studies'!$B11) -> WF-IoT - FIT IoT-LAB: A large scale open experimental IoT testbed | C220: ='references-it1-studies'!$C11 -> 2015 | D220: ='references-it1-studies'!$H11 -> 6
A221: References | B221: =HYPERLINK('references-it1-studies'!$D12,'references-it1-studies'!$B12) -> Container-based architecture for flexible industrial control applications | C221: ='references-it1-studies'!$C12 -> 2018 | D221: ='references-it1-studies'!$H12 -> 9
A222: References | B222: =HYPERLINK('references-it1-studies'!$D13,'references-it1-studies'!$B13) -> Interworking between Modbus and internet of things platform for industrial services | C222: ='references-it1-studies'!$C13 -> 2024 | D222: ='references-it1-studies'!$H13 -> 11
... A311: References | B311: =HYPERLINK('references-it1-studies'!$D102,'references-it1-studies'!$B102) -> Communication Systems for Industry 4.0 and the IIoT | C311: ='references-it1-studies'!$C102 -> 2018 | D311: ='references-it1-studies'!$H102 -> 6
A312: References | B312: =HYPERLINK('references-it1-studies'!$D104,'references-it1-studies'!$B104) -> ICN - NDN, CoAP, and MQTT: a comparative measurement study in the IoT | C312: ='references-it1-studies'!$C104 -> 2018 | D312: ='references-it1-studies'!$H104 -> 13
A313: References | B313: =HYPERLINK('references-it1-studies'!$D105,'references-it1-studies'!$B105) -> Energy Management Systems | C313: ='references-it1-studies'!$C105 -> 1991 | D313: ='references-it1-studies'!$H105 -> 0
A314: References | B314: =HYPERLINK('references-it1-studies'!$D106,'references-it1-studies'!$B106) -> Integration of WirelessHART and ISA100.11a field devices into condition monitoring system for starting IIoT implementation | C314: ='references-it1-studies'!$C106 -> 2017 | D314: ='references-it1-studies'!$H106 -> 6
A315: References | B315: =HYPERLINK('references-it1-studies'!$D107,'references-it1-studies'!$B107) -> JOSE: An Open Testbed for Field Trials of Large-scale IoT Services | C315: ='references-it1-studies'!$C107 -> 2016 | D315: ='references-it1-studies'!$H107 -> 9
A316: References | B316: =HYPERLINK('references-it1-studies'!$D108,'references-it1-studies'!$B108) -> Open-Source Implementierung von OPC UA PubSub für echtzeitfähige Kommunikation mit Time-Sensitive Networking | C316: ='references-it1-studies'!$C108 -> 2020 | D316: ='references-it1-studies'!$H108 -> 10
A317: References | B317: =HYPERLINK('references-it1-studies'!$D109,'references-it1-studies'!$B109) -> Communication Architecture of the IEC 61850-based Micro Grid System | C317: ='references-it1-studies'!$C109 -> 2011 | D317: ='references-it1-studies'!$H109 -> 8
A318: References | B318: =HYPERLINK('references-it1-studies'!$D110,'references-it1-studies'!$B110) -> A performance analysis of three potential control network for monitoring and control in Power Electronics converter | C318: ='references-it1-studies'!$C110 -> 2012 | D318: ='references-it1-studies'!$H110 -> 6
A319: References | B319: =HYPERLINK('references-it1-studies'!$D111,'references-it1-studies'!$B111) -> IECON - Network delay analysis of EtherCAT and PROFINET IRT protocols | C319: ='references-it1-studies'!$C111 -> 2014 | D319: ='references-it1-studies'!$H111 -> 7
A320: References | B320: =HYPERLINK('references-it1-studies'!$D112,'references-it1-studies'!$B112) -> Concept and engineering development of cyber physical production systems: a systematic literature review | C320: ='references-it1-studies'!$C112 -> 2020 | D320: ='references-it1-studies'!$H112 -> 19
A321: References | B321: =HYPERLINK('references-it1-studies'!$D113,'references-it1-studies'!$B113) -> Real-Time Hardware-in-the-Loop Testing of IEC 61850 GOOSE-Based Logically Selective Adaptive Protection of AC Microgrid | C321: ='references-it1-studies'!$C113 -> 2021 | D321: ='references-it1-studies'!$H113 -> 28
A322: References | B322: =HYPERLINK('references-it1-studies'!$D114,'references-it1-studies'!$B114) -> Container-based Virtualization for Real-time Industrial Systems—A Systematic Review | C322: ='references-it1-studies'!$C114 -> 2023 | D322: ='references-it1-studies'!$H114 -> 38
A323: References | B323: =HYPERLINK('references-it1-studies'!$D115,'references-it1-studies'!$B115) -> Industry 4.0 for SMEs | C323: ='references-it1-studies'!$C115 -> 2020 | D323: ='references-it1-studies'!$H115 -> 0
... A400: References | B400: =HYPERLINK('references-it1-studies'!$D192,'references-it1-studies'!$B192) -> ETFA - Real Time Ethernet networks evaluation using performance indicators | C400: ='references-it1-studies'!$C192 -> 2009 | D400: ='references-it1-studies'!$H192 -> 8
A401: References | B401: =HYPERLINK('references-it1-studies'!$D194,'references-it1-studies'!$B194) -> Wireless Technologies for Industry 4.0 Applications | C401: ='references-it1-studies'!$C194 -> 2023 | D401: ='references-it1-studies'!$H194 -> 1
A402: References | B402: =HYPERLINK('references-it1-studies'!$D195,'references-it1-studies'!$B195) -> Anomaly Detection and its Adaptation: Studies on Cyber-Physical Systems | C402: ='references-it1-studies'!$C195 -> 2013 | D402: ='references-it1-studies'!$H195 -> 0
A403: References | B403: =HYPERLINK('references-it1-studies'!$D196,'references-it1-studies'!$B196) -> RESTful information-centric networking | C403: ='references-it1-studies'!$C196 -> 2022 | D403: ='references-it1-studies'!$H196 -> 3
A404: References | B404: =HYPERLINK('references-it1-studies'!$D197,'references-it1-studies'!$B197) -> Key Challenges and Emerging Technologies in Industrial IoT Architectures: A Review. | C404: ='references-it1-studies'!$C197 -> 2022 | D404: ='references-it1-studies'!$H197 -> 1
A405: References | B405: =HYPERLINK('references-it1-studies'!$D198,'references-it1-studies'!$B198) -> A survey on communication protocols and performance evaluations for Internet of Things | C405: ='references-it1-studies'!$C198 -> 2022 | D405: ='references-it1-studies'!$H198 -> 11
A406: References | B406: =HYPERLINK('references-it1-studies'!$D199,'references-it1-studies'!$B199) -> Performance Tuning Towards a KVM-based Embedded Real-time Virtualization System | C406: ='references-it1-studies'!$C199 -> 2013 | D406: ='references-it1-studies'!$H199 -> 15
A407: References | B407: =HYPERLINK('references-it1-studies'!$D200,'references-it1-studies'!$B200) -> IoT Fundamentals: Networking Technologies, Protocols, and Use Cases for the Internet of Things | C407: ='references-it1-studies'!$C200 -> 2017 | D407: ='references-it1-studies'!$H200 -> 0

Sheet Snowballing-it1-filtering
A1: Source | B1: Title | C1: Year | D1: Number of pages
A2: Citations | B2: =HYPERLINK('citations-it1-studies'!$D2,'citations-it1-studies'!$B2) -> Practical approaches towards IoT dataset generation for security experiments | C2: ='citations-it1-studies'!$C2 -> 2025 | D2: ='citations-it1-studies'!$H2 -> 65
A3: Citations | B3: =HYPERLINK('citations-it1-studies'!$D3,'citations-it1-studies'!$B3) -> Performance Evaluation of IoT-Enabled Edge Computing Infrastructure for mHealth Services | C3: ='citations-it1-studies'!$C3 -> 2025 | D3: ='citations-it1-studies'!$H3 -> 12
A4: Citations | B4: =HYPERLINK('citations-it1-studies'!$D4,'citations-it1-studies'!$B4) -> Learning Temporal and Spatial Features Jointly: A Unified Framework for Space-Time Data Prediction in Industrial IoT Networks | C4: ='citations-it1-studies'!$C4 -> 2023 | D4: ='citations-it1-studies'!$H4 -> 13
A5: Citations | B5: =HYPERLINK('citations-it1-studies'!$D5,'citations-it1-studies'!$B5) -> Design of 5G private network quality monitoring System based on edge computing | C5: ='citations-it1-studies'!$C5 -> 2023 | D5: ='citations-it1-studies'!$H5 -> 5
A6: Citations | B6: =HYPERLINK('citations-it1-studies'!$D7,'citations-it1-studies'!$B7) -> Challenges in Resource-Constrained IoT Devices: Energy and Communication as Critical Success Factors for Future IoT Deployment. | C6: ='citations-it1-studies'!$C7 -> 2020 | D6: ='citations-it1-studies'!$H7 -> 0
A7: Citations | B7: =HYPERLINK('citations-it1-studies'!$D9,'citations-it1-studies'!$B9) -> Construction of intelligent integrated model framework for the workshop manufacturing system via digital twin | C7: ='citations-it1-studies'!$C9 -> 2021 | D7: ='citations-it1-studies'!$H9 -> 14
A8: Citations | B8: =HYPERLINK('citations-it1-studies'!$D10,'citations-it1-studies'!$B10) -> Communication and Coordination for Multi AGVs Based on MQTT Protocol | C8: ='citations-it1-studies'!$C10 -> 2023 | D8: ='citations-it1-studies'!$H10 -> 6
A9: Citations | B9: =HYPERLINK('citations-it1-studies'!$D11,'citations-it1-studies'!$B11) -> QoSmart-IoT: Secure QoS-Based Reconfiguration and Protocol Adaptation for Hybrid Clustered IoT Systems in Constrained Environments | C9: ='citations-it1-studies'!$C11 -> 2025 | D9: ='citations-it1-studies'!$H11 -> 13
A10: Citations | B10: =HYPERLINK('citations-it1-studies'!$D12,'citations-it1-studies'!$B12) -> APT Adversarial Defence Mechanism for Industrial IoT Enabled Cyber-Physical System | C10: ='citations-it1-studies'!$C12 -> 2023 | D10: ='citations-it1-studies'!$H12 -> 21
A11: Citations | B11: =HYPERLINK('citations-it1-studies'!$D13,'citations-it1-studies'!$B13) -> Secure Communication Protocols: Safeguarding Information in The Digital Age | C11: ='citations-it1-studies'!$C13 -> 2025 | D11: ='citations-it1-studies'!$H13 -> 65
A12: Citations | B12: =HYPERLINK('citations-it1-studies'!$D14,'citations-it1-studies'!$B14) -> IBAM: IPFS and Blockchain based Authentication for MQTT protocol in IoT | C12: ='citations-it1-studies'!$C14 -> 2023 | D12: ='citations-it1-studies'!$H14 -> 6
A13: Citations | B13: =HYPERLINK('citations-it1-studies'!$D15,'citations-it1-studies'!$B15) -> Integration of MQTT and CoAP Protocols in OneM2M for IoT Applications | C13: ='citations-it1-studies'!$C15 -> 2025 | D13: ='citations-it1-studies'!$H15 -> 11
A14: Citations | B14: =HYPERLINK('citations-it1-studies'!$D16,'citations-it1-studies'!$B16) -> MECInOT: a multi-access edge computing and industrial internet of things emulator for the modelling and study of cybersecurity threats | C14: ='citations-it1-studies'!$C16 -> 2023 | D14: ='citations-it1-studies'!$H16 -> 39
A15: Citations | B15: =HYPERLINK('citations-it1-studies'!$D17,'citations-it1-studies'!$B17) -> Implementing Dead Letter Exchanges in MQTT and Proposing a Broker Failure Algorithm Utilizing Blockchain DNS | C15: ='citations-it1-studies'!$C17 -> 2023 | D15: ='citations-it1-studies'!$H17 -> 6
A16: Citations | B16: =HYPERLINK('citations-it1-studies'!$D18,'citations-it1-studies'!$B18) -> X-IIoTID: A Connectivity-Agnostic and Device-Agnostic Intrusion Data Set for Industrial Internet of Things | C16: ='citations-it1-studies'!$C18 -> 2022 | D16: ='citations-it1-studies'!$H18 -> 16
A17: Citations | B17: =HYPERLINK('citations-it1-studies'!$D19,'citations-it1-studies'!$B19) -> Intelligent Monitoring and Control Systems for Smart Water Management | C17: ='citations-it1-studies'!$C19 -> 2025 | D17: ='citations-it1-studies'!$H19 -> 22
A18: Citations | B18: =HYPERLINK('citations-it1-studies'!$D20,'citations-it1-studies'!$B20) -> Multisensory Fusion, Haptic, and Visual Feedback Teleoperation System Under IoT Framework | C18: ='citations-it1-studies'!$C20 -> 2022 | D18: ='citations-it1-studies'!$H20 -> 11
... A23: Citations | B23: =HYPERLINK('citations-it1-studies'!$D25,'citations-it1-studies'!$B25) -> Evaluating Real-Time Ethernet performance indicators for SERCOS III networks | C23: ='citations-it1-studies'!$C25 -> 2021 | D23: ='citations-it1-studies'!$H25 -> 7
A24: Citations | B24: =HYPERLINK('citations-it1-studies'!$D27,'citations-it1-studies'!$B27) -> Cloud-Fog Automation: The New Paradigm Toward Autonomous Industrial Cyber-Physical Systems | C24: ='citations-it1-studies'!$C27 -> 2025 | D24: ='citations-it1-studies'!$H27 -> 21
A25: Citations | B25: =HYPERLINK('citations-it1-studies'!$D28,'citations-it1-studies'!$B28) -> Integrating Fieldbus and Data-Centric Middleware: An STM32 Modbus Master Gateway for DDS-Based IIoT Systems | C25: ='citations-it1-studies'!$C28 -> 2025 | D25: ='citations-it1-studies'!$H28 -> 0
A26: Citations | B26: =HYPERLINK('citations-it1-studies'!$D29,'citations-it1-studies'!$B29) -> Online Compensation Method for Contour Error in the Parallel Module of a Hybrid Gantry Machining Center | C26: ='citations-it1-studies'!$C29 -> 2025 | D26: ='citations-it1-studies'!$H29 -> 0
A27: Citations | B27: =HYPERLINK('citations-it1-studies'!$D30,'citations-it1-studies'!$B30) -> RAPTOR: Advanced Persistent Threat Detection in Industrial IoT via Attack Stage Correlation | C27: ='citations-it1-studies'!$C30 -> 2023 | D27: ='citations-it1-studies'!$H30 -> 12
A28: Citations | B28: =HYPERLINK('citations-it1-studies'!$D31,'citations-it1-studies'!$B31) -> Improving Security and Preventing Cyber Attacks in Smart Device Networks | C28: ='citations-it1-studies'!$C31 -> 2025 | D28: ='citations-it1-studies'!$H31 -> 6
A29: Citations | B29: =HYPERLINK('citations-it1-studies'!$D32,'citations-it1-studies'!$B32) -> KOTO: A Kubernetes-Based Platform for Secure and Scalable OT Orchestration in Industry 5.0 | C29: ='citations-it1-studies'!$C32 -> 2025 | D29: ='citations-it1-studies'!$H32 -> 6
A30: Citations | B30: =HYPERLINK('citations-it1-studies'!$D33,'citations-it1-studies'!$B33) -> A Survey of Public IoT Datasets for Network Security Research | C30: ='citations-it1-studies'!$C33 -> 2023 | D30: ='citations-it1-studies'!$H33 -> 33
A31: Citations | B31: =HYPERLINK('citations-it1-studies'!$D37,'citations-it1-studies'!$B37) -> ExaMon-X: A Predictive Maintenance Framework for Automatic Monitoring in Industrial IoT Systems | C31: ='citations-it1-studies'!$C37 -> 2023 | D31: ='citations-it1-studies'!$H37 -> 11
A32: Citations | B32: =HYPERLINK('citations-it1-studies'!$D39,'citations-it1-studies'!$B39) -> Interaction of Artificial Intelligence and Machining Processes Regarding Industry 4.0 Production Systems | C32: ='citations-it1-studies'!$C39 -> 2023 | D32: ='citations-it1-studies'!$H39 -> 10
A33: Citations | B33: =HYPERLINK('citations-it1-studies'!$D40,'citations-it1-studies'!$B40) -> The Influence of Choosing Sensor Locations Inside Closed Facilities on the Reliability, Adaptability, and Energy Efficiency of IoT Systems | C33: ='citations-it1-studies'!$C40 -> 2024 | D33: ='citations-it1-studies'!$H40 -> 6
A34: Citations | B34: =HYPERLINK('citations-it1-studies'!$D41,'citations-it1-studies'!$B41) -> Messaging Protocols for IoT Systems-A Pragmatic Comparison. | C34: ='citations-it1-studies'!$C41 -> 2021 | D34: ='citations-it1-studies'!$H41 -> 0
A35: Citations | B35: =HYPERLINK('citations-it1-studies'!$D42,'citations-it1-studies'!$B42) -> Deep Learning-Based Intrusion Detection for Distributed Denial of Service Attack in Agriculture 4.0 | C35: ='citations-it1-studies'!$C42 -> 2021 | D35: ='citations-it1-studies'!$H42 -> 0
A36: Citations | B36: =HYPERLINK('citations-it1-studies'!$D44,'citations-it1-studies'!$B44) -> Enhancing Cybersecurity in Industrial Internet of Things: Machine Learning-Based Approaches for Cyber-Attack Detection in a Realworld Testbed Environment | C36: ='citations-it1-studies'!$C44 -> 2025 | D36: ='citations-it1-studies'!$H44 -> 14
A37: Citations | B37: =HYPERLINK('citations-it1-studies'!$D45,'citations-it1-studies'!$B45) -> Wireless Cyber-Physical Systems Performance Evaluation through a Graph Database Approach. | C37: ='citations-it1-studies'!$C45 -> 2020 | D37: ='citations-it1-studies'!$H45 -> 19
A38: Citations | B38: =HYPERLINK('citations-it1-studies'!$D46,'citations-it1-studies'!$B46) -> Orchestrating Embodied Systems through the Embodied Context Protocol: Motivation, Progress, and Directions. | C38: ='citations-it1-studies'!$C46 -> 2025 | D38: ='citations-it1-studies'!$H46 -> 0
A39: Citations | B39: =HYPERLINK('citations-it1-studies'!$D47,'citations-it1-studies'!$B47) -> Functioning and Development of a Real-Time Information System for the Oil Treatment Technological Process Control | C39: ='citations-it1-studies'!$C47 -> 2020 | D39: ='citations-it1-studies'!$H47 -> 6
A40: Citations | B40: =HYPERLINK('citations-it1-studies'!$D48,'citations-it1-studies'!$B48) -> OPC UA PubSub and Industrial Controller Redundancy | C40: ='citations-it1-studies'!$C48 -> 2024 | D40: ='citations-it1-studies'!$H48 -> 8
A41: Citations | B41: =HYPERLINK('citations-it1-studies'!$D49,'citations-it1-studies'!$B49) -> Evaluation of quality of service parameters for MQTT communication in IoT application by using deep neural network | C41: ='citations-it1-studies'!$C49 -> 2023 | D41: ='citations-it1-studies'!$H49 -> 14
A42: Citations | B42: =HYPERLINK('citations-it1-studies'!$D50,'citations-it1-studies'!$B50) -> Game Theoretic Feedback Control for Reliability Enhancement of EtherCAT-Based Networked Systems | C42: ='citations-it1-studies'!$C50 -> 2019 | D42: ='citations-it1-studies'!$H50 -> 12
A43: Citations | B43: =HYPERLINK('citations-it1-studies'!$D51,'citations-it1-studies'!$B51) -> Centralized controlling of distributed PV systems using cloud and IoT technologies | C43: ='citations-it1-studies'!$C51 -> 2023 | D43: ='citations-it1-studies'!$H51 -> 6
A44: Citations | B44: =HYPERLINK('citations-it1-studies'!$D52,'citations-it1-studies'!$B52) -> A Thorough Analysis and Comparison of Data Communication Protocols Used in Industry 4.0: the Case of Smart-CNC | C44: ='citations-it1-studies'!$C52 -> 2022 | D44: ='citations-it1-studies'!$H52 -> 8
A45: Citations | B45: =HYPERLINK('citations-it1-studies'!$D53,'citations-it1-studies'!$B53) -> Redundancy for an all-in-one ISA100.11a Gateway: Protocol Design and Hardware Integration | C45: ='citations-it1-studies'!$C53 -> 2019 | D45: ='citations-it1-studies'!$H53 -> 6
A46: Citations | B46: =HYPERLINK('citations-it1-studies'!$D54,'citations-it1-studies'!$B54) -> Driving Factors Behind Adopting Virtual Testbeds for ICS Cybersecurity Education. | C46: ='citations-it1-studies'!$C54 -> 2025 | D46: ='citations-it1-studies'!$H54 -> 7
A47: Citations | B47: =HYPERLINK('citations-it1-studies'!$D55,'citations-it1-studies'!$B55) -> A platform-enabled CNC within edge-cloud environments: perspectives, challenges, and potential solutions | C47: ='citations-it1-studies'!$C55 -> 2025 | D47: ='citations-it1-studies'!$H55 -> 17
... A50: Citations | B50: =HYPERLINK('citations-it1-studies'!$D58,'citations-it1-studies'!$B58) -> Characterizing the Real-Time Communication Performance of Virtual PLC in Industrial Edge Platform | C50: ='citations-it1-studies'!$C58 -> 2025 | D50: ='citations-it1-studies'!$H58 -> 11
A51: Citations | B51: =HYPERLINK('citations-it1-studies'!$D60,'citations-it1-studies'!$B60) -> A Hybrid VLC/RF Parking Automation System | C51: ='citations-it1-studies'!$C60 -> 2023 | D51: ='citations-it1-studies'!$H60 -> 19
A52: Citations | B52: =HYPERLINK('citations-it1-studies'!$D62,'citations-it1-studies'!$B62) -> A Novel Industrial Software Model for Social Manufacturing | C52: ='citations-it1-studies'!$C62 -> 2024 | D52: ='citations-it1-studies'!$H62 -> 0
A53: Citations | B53: =HYPERLINK('citations-it1-studies'!$D63,'citations-it1-studies'!$B63) -> A Systematic Review of Recent Advances in IoT-Based Sensor Networks for Warehouse Management | C53: ='citations-it1-studies'!$C63 -> 2025 | D53: ='citations-it1-studies'!$H63 -> 0
A54: Citations | B54: =HYPERLINK('citations-it1-studies'!$D65,'citations-it1-studies'!$B65) -> Blake-2s based Improved Authentication Scheme for IEC 61850 GOOSE Messages | C54: ='citations-it1-studies'!$C65 -> 2025 | D54: ='citations-it1-studies'!$H65 -> 6
A55: Citations | B55: =HYPERLINK('citations-it1-studies'!$D67,'citations-it1-studies'!$B67) -> Communication in collaborating construction equipment | C55: ='citations-it1-studies'!$C67 -> 2023 | D55: ='citations-it1-studies'!$H67 -> 10
A56: Citations | B56: =HYPERLINK('citations-it1-studies'!$D68,'citations-it1-studies'!$B68) -> A Blockchain-Reinforced Federated Intrusion Detection Architecture for IIoT | C56: ='citations-it1-studies'!$C68 -> 2024 | D56: ='citations-it1-studies'!$H68 -> 13
A57: Citations | B57: =HYPERLINK('citations-it1-studies'!$D69,'citations-it1-studies'!$B69) -> OPC UA client-server connection over an ISO 11783 vehicle network | C57: ='citations-it1-studies'!$C69 -> 2023 | D57: ='citations-it1-studies'!$H69 -> 12
A58: Citations | B58: =HYPERLINK('citations-it1-studies'!$D71,'citations-it1-studies'!$B71) -> WiSEE - Wireless Transmission of Sensor Data over UWB in Spacecraft Payload Networks | C58: ='citations-it1-studies'!$C71 -> 2018 | D58: ='citations-it1-studies'!$H71 -> 6
A59: Citations | B59: =HYPERLINK('citations-it1-studies'!$D72,'citations-it1-studies'!$B72) -> The Digital Backbone of Manufacturing: A Framework for Network Protocol Selection | C59: ='citations-it1-studies'!$C72 -> 2025 | D59: ='citations-it1-studies'!$H72 -> 0
A60: Citations | B60: =HYPERLINK('citations-it1-studies'!$D73,'citations-it1-studies'!$B73) -> ETFA - Clock Synchronization in Integrated TSN-EtherCAT Networks | C60: ='citations-it1-studies'!$C73 -> 2020 | D60: ='citations-it1-studies'!$H73 -> 8
A61: Citations | B61: =HYPERLINK('citations-it1-studies'!$D74,'citations-it1-studies'!$B74) -> End-to-End Visual Control Framework in Wireless TSN Networks for Industrial IoT | C61: ='citations-it1-studies'!$C74 -> 2025 | D61: ='citations-it1-studies'!$H74 -> 14
A62: Citations | B62: =HYPERLINK('citations-it1-studies'!$D75,'citations-it1-studies'!$B75) -> Beyond the Virtual PLC Networking Constraints: MACvLAN Approach in Industrial Environments | C62: ='citations-it1-studies'!$C75 -> 2025 | D62: ='citations-it1-studies'!$H75 -> 6
A63: Citations | B63: =HYPERLINK('citations-it1-studies'!$D76,'citations-it1-studies'!$B76) -> A Study on 28 GHz Power Amplifiers for Industrial Revolution 4.0 Compatible 5G NR FR2 IoT Transceivers | C63: ='citations-it1-studies'!$C76 -> 2023 | D63: ='citations-it1-studies'!$H76 -> 6
A64: Citations | B64: =HYPERLINK('citations-it1-studies'!$D78,'citations-it1-studies'!$B78) -> Asset Management Method of Industrial IoT Systems for Cyber-Security Countermeasures | C64: ='citations-it1-studies'!$C78 -> 2021 | D64: ='citations-it1-studies'!$H78 -> 0
A65: Citations | B65: =HYPERLINK('citations-it1-studies'!$D79,'citations-it1-studies'!$B79) -> A threat intelligence framework for protecting smart satellite-based healthcare networks | C65: ='citations-it1-studies'!$C79 -> 2021 | D65: ='citations-it1-studies'!$H79 -> 21
A66: Citations | B66: =HYPERLINK('citations-it1-studies'!$D80,'citations-it1-studies'!$B80) -> Performance Analysis of OPC UA for Industrial Interoperability towards Industry 4.0 | C66: ='citations-it1-studies'!$C80 -> 2022 | D66: ='citations-it1-studies'!$H80 -> 19
A67: Citations | B67: =HYPERLINK('citations-it1-studies'!$D81,'citations-it1-studies'!$B81) -> Benchmark and Design Support for Demand-Oriented Cloud-Communication Architectures of Cyber-Physical Production Systems | C67: ='citations-it1-studies'!$C81 -> 2023 | D67: ='citations-it1-studies'!$H81 -> 8
A68: Citations | B68: =HYPERLINK('citations-it1-studies'!$D82,'citations-it1-studies'!$B82) -> A Real Network Performance Analysis Testbed for Encrypted MQTT in DMS | C68: ='citations-it1-studies'!$C82 -> 2024 | D68: ='citations-it1-studies'!$H82 -> 6
A69: Citations | B69: =HYPERLINK('citations-it1-studies'!$D83,'citations-it1-studies'!$B83) -> ДОСЛІДЖЕННЯ ЕФЕКТИВНОСТІ ВИКОРИСТАННЯ РОЗПОДІЛЕНИХ БАЗ ДАНИХ В СИСТЕМАХ IIOT | C69: ='citations-it1-studies'!$C83 -> 2022 | D69: ='citations-it1-studies'!$H83 -> 7
A70: Citations | B70: =HYPERLINK('citations-it1-studies'!$D84,'citations-it1-studies'!$B84) -> Performance Evaluation of an IEEE 802.11g Network in an Industrial Environment | C70: ='citations-it1-studies'!$C84 -> 2020 | D70: ='citations-it1-studies'!$H84 -> 7
A71: Citations | B71: =HYPERLINK('citations-it1-studies'!$D85,'citations-it1-studies'!$B85) -> Improving Fault Tolerance and Tackling Broker Failure in MQTT through Blockchain | C71: ='citations-it1-studies'!$C85 -> 2023 | D71: ='citations-it1-studies'!$H85 -> 6
A72: Citations | B72: =HYPERLINK('citations-it1-studies'!$D87,'citations-it1-studies'!$B87) -> Time Sensitive Networking for Future Enabling Technologies: Overview and Measurement Issues for Metrological Characterization | C72: ='citations-it1-studies'!$C87 -> 2024 | D72: ='citations-it1-studies'!$H87 -> 6
A73: Citations | B73: =HYPERLINK('citations-it1-studies'!$D88,'citations-it1-studies'!$B88) -> On the integration of OPC UA over Wired – Wireless Time Sensitive Networking | C73: ='citations-it1-studies'!$C88 -> 2023 | D73: ='citations-it1-studies'!$H88 -> 6
A74: Citations | B74: =HYPERLINK('citations-it1-studies'!$D90,'citations-it1-studies'!$B90) -> An Innovative Digital Twin of Integrated Transportation and Power Networks for Efficient Scheduling of Autonomous Electric Vehicles | C74: ='citations-it1-studies'!$C90 -> 2024 | D74: ='citations-it1-studies'!$H90 -> 5
A75: Citations | B75: =HYPERLINK('citations-it1-studies'!$D91,'citations-it1-studies'!$B91) -> A Comprehensive Review on 5G IIoT Test-Beds | C75: ='citations-it1-studies'!$C91 -> 2025 | D75: ='citations-it1-studies'!$H91 -> 25
A76: Citations | B76: =HYPERLINK('citations-it1-studies'!$D93,'citations-it1-studies'!$B93) -> Implementing and using smart maintenance technologies: Introducing challenges and enablers related to human, organizational and technological perspectives | C76: ='citations-it1-studies'!$C93 -> 2025 | D76: ='citations-it1-studies'!$H93 -> 10
A77: Citations | B77: =HYPERLINK('citations-it1-studies'!$D94,'citations-it1-studies'!$B94) -> Performance evaluation of industrial Ethernet protocols for networked control application | C77: ='citations-it1-studies'!$C94 -> 2019 | D77: ='citations-it1-studies'!$H94 -> 10
A78: Citations | B78: =HYPERLINK('citations-it1-studies'!$D95,'citations-it1-studies'!$B95) -> Comprehensive Exploration of IoT Communication Protocol: CoAP, MQTT, HTTP, LoRaWAN and AMQP | C78: ='citations-it1-studies'!$C95 -> 2024 | D78: ='citations-it1-studies'!$H95 -> 14
A79: Citations | B79: =HYPERLINK('citations-it1-studies'!$D96,'citations-it1-studies'!$B96) -> System architecture for small‐scale personalized production lines based on industrial Internet | C79: ='citations-it1-studies'!$C96 -> 2024 | D79: ='citations-it1-studies'!$H96 -> 0
A80: Citations | B80: =HYPERLINK('citations-it1-studies'!$D98,'citations-it1-studies'!$B98) -> Encryption for Industrial Control Systems: A Survey of Application-Level and Network-Level Approaches in Smart Grids | C80: ='citations-it1-studies'!$C98 -> 2026 | D80: ='citations-it1-studies'!$H98 -> 0
A81: Citations | B81: =HYPERLINK('citations-it1-studies'!$D101,'citations-it1-studies'!$B101) -> Design of Cloud-Edge-Gateway Collaborative Zero-Trust Architecture and Workflow for Smart Factories | C81: ='citations-it1-studies'!$C101 -> 2024 | D81: ='citations-it1-studies'!$H101 -> 5
A82: Citations | B82: =HYPERLINK('citations-it1-studies'!$D102,'citations-it1-studies'!$B102) -> Performance Evaluation of Application Layer IoT Protocols: MQTT and CoAP | C82: ='citations-it1-studies'!$C102 -> 2024 | D82: ='citations-it1-studies'!$H102 -> 6
A83: Citations | B83: =HYPERLINK('citations-it1-studies'!$D103,'citations-it1-studies'!$B103) -> Mitigating 3D printing defects via cyber-physical systems: a process for fabricating defect-free components | C83: ='citations-it1-studies'!$C103 -> 2025 | D83: ='citations-it1-studies'!$H103 -> 22
A84: Citations | B84: =HYPERLINK('citations-it1-studies'!$D104,'citations-it1-studies'!$B104) -> Environment Monitoring Subsystem Based on Recursive InterNetwork Architecture | C84: ='citations-it1-studies'!$C104 -> 2024 | D84: ='citations-it1-studies'!$H104 -> 19
A85: Citations | B85: =HYPERLINK('citations-it1-studies'!$D105,'citations-it1-studies'!$B105) -> When the digital twin meets the preventive conservation of movable wooden artifacts | C85: ='citations-it1-studies'!$C105 -> 2023 | D85: ='citations-it1-studies'!$H105 -> 0
A86: Citations | B86: =HYPERLINK('citations-it1-studies'!$D106,'citations-it1-studies'!$B106) -> Deep Learning Applications for Blockchain in Industrial IoT | C86: ='citations-it1-studies'!$C106 -> 2022 | D86: ='citations-it1-studies'!$H106 -> 6
A87: Citations | B87: =HYPERLINK('citations-it1-studies'!$D107,'citations-it1-studies'!$B107) -> Edge Computing: Use Cases and Research Challenges | C87: ='citations-it1-studies'!$C107 -> 2023 | D87: ='citations-it1-studies'!$H107 -> 18
A88: Citations | B88: =HYPERLINK('citations-it1-studies'!$D108,'citations-it1-studies'!$B108) -> Data Security and Privacy in Industrial IoT | C88: ='citations-it1-studies'!$C108 -> 2021 | D88: ='citations-it1-studies'!$H108 -> 19
A89: Citations | B89: =HYPERLINK('citations-it1-studies'!$D109,'citations-it1-studies'!$B109) -> Cloud Computing for High Voltage Substation Based Relay Protection | C89: ='citations-it1-studies'!$C109 -> 2024 | D89: ='citations-it1-studies'!$H109 -> 7
A90: Citations | B90: =HYPERLINK('citations-it1-studies'!$D110,'citations-it1-studies'!$B110) -> An Online Model to Minimize Energy Consumption of IoT Sensors in Smart Cities | C90: ='citations-it1-studies'!$C110 -> 2022 | D90: ='citations-it1-studies'!$H110 -> 9
A91: Citations | B91: =HYPERLINK('citations-it1-studies'!$D111,'citations-it1-studies'!$B111) -> Model of a Device-Level Combined Wireless Network Based on NB-IoT and IEEE 802.15.4 Standards for Low-Power Applications in a Diverse IoT Framework. | C91: ='citations-it1-studies'!$C111 -> 2021 | D91: ='citations-it1-studies'!$H111 -> 0
A92: Citations | B92: =HYPERLINK('citations-it1-studies'!$D113,'citations-it1-studies'!$B113) -> Joint Security-Reliability Performance Optimization in Low-Latency Industrial IoT Networks | C92: ='citations-it1-studies'!$C113 -> 2025 | D92: ='citations-it1-studies'!$H113 -> 5
A93: Citations | B93: =HYPERLINK('citations-it1-studies'!$D114,'citations-it1-studies'!$B114) -> Identifying key attacks on an IEEE 9-Bus System by leveraging the MITRE ATT&CK ICS Matrix | C93: ='citations-it1-studies'!$C114 -> 2025 | D93: ='citations-it1-studies'!$H114 -> 8
A94: Citations | B94: =HYPERLINK('citations-it1-studies'!$D116,'citations-it1-studies'!$B116) -> Engineering Interoperable, Plug-and-Play, Distributed, Robotic Control Systems for Futureproof Fusion Power Plants | C94: ='citations-it1-studies'!$C116 -> 2021 | D94: ='citations-it1-studies'!$H116 -> 0
A95: Citations | B95: =HYPERLINK('citations-it1-studies'!$D117,'citations-it1-studies'!$B117) -> Cybersecurity Testbeds for IoT: A Systematic Literature Review and Taxonomy | C95: ='citations-it1-studies'!$C117 -> 2024 | D95: ='citations-it1-studies'!$H117 -> 24
A96: Citations | B96: =HYPERLINK('citations-it1-studies'!$D118,'citations-it1-studies'!$B118) -> A systematic literature review: Messaging protocols and electronic platforms used in the internet of things for the purpose of building smart homes | C96: ='citations-it1-studies'!$C118 -> 2023 | D96: ='citations-it1-studies'!$H118 -> 10
A97: Citations | B97: =HYPERLINK('citations-it1-studies'!$D119,'citations-it1-studies'!$B119) -> Data-Based Process Monitoring for Structural Bonding of Fiber-Reinforced Thermoplastics in Aviation | C97: ='citations-it1-studies'!$C119 -> 2025 | D97: ='citations-it1-studies'!$H119 -> 6
A98: Citations | B98: =HYPERLINK('citations-it1-studies'!$D120,'citations-it1-studies'!$B120) -> Smart Tree: An Architectural, Greening and ICT Multidisciplinary Approach to Smart Campus Environments. | C98: ='citations-it1-studies'!$C120 -> 2021 | D98: ='citations-it1-studies'!$H120 -> 0
A99: Citations | B99: =HYPERLINK('citations-it1-studies'!$D121,'citations-it1-studies'!$B121) -> The Nexus Between Digital Transformation and Economic Efficiency: Evidence from Selected Countries | C99: ='citations-it1-studies'!$C121 -> 2023 | D99: ='citations-it1-studies'!$H121 -> 10
A100: Citations | B100: =HYPERLINK('citations-it1-studies'!$D123,'citations-it1-studies'!$B123) -> Methods and means of conflict-free data exchange in the group of mobile robotic platforms | C100: ='citations-it1-studies'!$C123 -> 2024 | D100: ='citations-it1-studies'!$H123 -> 11
A101: Citations | B101: =HYPERLINK('citations-it1-studies'!$D124,'citations-it1-studies'!$B124) -> A Survey on Industrial Internet With ISA100 Wireless | C101: ='citations-it1-studies'!$C124 -> 2020 | D101: ='citations-it1-studies'!$H124 -> 20
A102: Citations | B102: =HYPERLINK('citations-it1-studies'!$D125,'citations-it1-studies'!$B125) -> A Comprehensive Systematic Survey of IoT Protocols: Implications for Data Quality and Performance | C102: ='citations-it1-studies'!$C125 -> 2025 | D102: ='citations-it1-studies'!$H125 -> 30
A103: Citations | B103: =HYPERLINK('citations-it1-studies'!$D127,'citations-it1-studies'!$B127) -> Wide area, IoT-based PID control of slow systems over LoRaWAN | C103: ='citations-it1-studies'!$C127 -> 2025 | D103: ='citations-it1-studies'!$H127 -> 6
A104: Citations | B104: =HYPERLINK('citations-it1-studies'!$D128,'citations-it1-studies'!$B128) -> ETFA - Modular Signal Processing Unit for Motion Control Applications Based on System-on-Chip with FPGA | C104: ='citations-it1-studies'!$C128 -> 2019 | D104: ='citations-it1-studies'!$H128 -> 7
A105: Citations | B105: =HYPERLINK('citations-it1-studies'!$D131,'citations-it1-studies'!$B131) -> Faster Implementation Time Through Interoperability: Let's Prove it! | C105: ='citations-it1-studies'!$C131 -> 2025 | D105: ='citations-it1-studies'!$H131 -> 7
A106: Citations | B106: =HYPERLINK('citations-it1-studies'!$D132,'citations-it1-studies'!$B132) -> AI-Enhanced Process Digital Twins for Circular Manufacturing: Design, Architecture, and Deployment | C106: ='citations-it1-studies'!$C132 -> 2025 | D106: ='citations-it1-studies'!$H132 -> 8
...

Sheet Snowballing-it1-screening
A1: Source | B1: Title | C1: Year | D1: Number of pages | E1: Done (mark with 'O') | F1: EC1 | G1: EC2 | H1: EC3 | I1: EC4 | J1: EC5 | K1: EC6 | L1: EC7 | M1: Title Exclusion | N1: Decision | O1: Motivation
A2: Citations | B2: =HYPERLINK('citations-it1-studies'!$D2,'citations-it1-studies'!$B2) -> Practical approaches towards IoT dataset generation for security experiments | C2: ='citations-it1-studies'!$C2 -> 2025 | D2: ='citations-it1-studies'!$H2 -> 65 | E2: O | L2: X | M2: X | N2: =IF(COUNTIF(F2:M2,"X")>0,"Exclude",IF(UPPER(TRIM(E2))="O","Include","")) -> Exclude | O2: IDS/ML/dataset focus, not protocol evaluation
A3: Citations | B3: =HYPERLINK('citations-it1-studies'!$D3,'citations-it1-studies'!$B3) -> Performance Evaluation of IoT-Enabled Edge Computing Infrastructure for mHealth Services | C3: ='citations-it1-studies'!$C3 -> 2025 | D3: ='citations-it1-studies'!$H3 -> 12 | E3: O | H3: X | M3: X | N3: =IF(COUNTIF(F3:M3,"X")>0,"Exclude",IF(UPPER(TRIM(E3))="O","Include","")) -> Exclude | O3: not clearly industrial automation context
A4: Citations | B4: =HYPERLINK('citations-it1-studies'!$D4,'citations-it1-studies'!$B4) -> Learning Temporal and Spatial Features Jointly: A Unified Framework for Space-Time Data Prediction in Industrial IoT Networks | C4: ='citations-it1-studies'!$C4 -> 2023 | D4: ='citations-it1-studies'!$H4 -> 13 | E4: O | L4: X | M4: X | N4: =IF(COUNTIF(F4:M4,"X")>0,"Exclude",IF(UPPER(TRIM(E4))="O","Include","")) -> Exclude | O4: no clear protocol focus | U4: Statistics (total) | V4: Count | W4: Percentage | Y4: Statistics (title screening) | Z4: Count | AA4: Percentage | AC4: Statistics (abstract screening) | AD4: Count | AE4: Percentage
A5: Citations | B5: =HYPERLINK('citations-it1-studies'!$D5,'citations-it1-studies'!$B5) -> Design of 5G private network quality monitoring System based on edge computing | C5: ='citations-it1-studies'!$C5 -> 2023 | D5: ='citations-it1-studies'!$H5 -> 5 | E5: O | H5: X | M5: X | N5: =IF(COUNTIF(F5:M5,"X")>0,"Exclude",IF(UPPER(TRIM(E5))="O","Include","")) -> Exclude | O5: not clearly industrial automation context | U5: Total papers: | V5: =COUNTIF(A2:A1948,"<>") -> 335 | Y5: Total papers: | Z5: =COUNTIF($A2:$A1948,"<>") -> 335 | AC5: Total papers: | AD5: =Z7 -> 51
A6: Citations | B6: =HYPERLINK('citations-it1-studies'!$D7,'citations-it1-studies'!$B7) -> Challenges in Resource-Constrained IoT Devices: Energy and Communication as Critical Success Factors for Future IoT Deployment. | C6: ='citations-it1-studies'!$C7 -> 2020 | D6: ='citations-it1-studies'!$H7 -> 0 | E6: O | H6: X | I6: X | M6: X | N6: =IF(COUNTIF(F6:M6,"X")>0,"Exclude",IF(UPPER(TRIM(E6))="O","Include","")) -> Exclude | O6: not clearly industrial automation context | U6: Number excluded: | V6: =COUNTIF(N2:N1948,"Exclude") -> 311 | W6: =((V6/V5)) -> 0.92835821 | Y6: Number excluded: | Z6: =COUNTIFS($N2:$N1948,"Exclude",$M2:$M1948,"X") -> 284 | AA6: =((Z6/Z5)) -> 0.84776119 | AC6: Number excluded: | AD6: =COUNTIFS($N2:$N1948,"Exclude",$M2:$M1948,"<>X") -> 27 | AE6: =((AD6/AD5)) -> 0.52941176
A7: Citations | B7: =HYPERLINK('citations-it1-studies'!$D9,'citations-it1-studies'!$B9) -> Construction of intelligent integrated model framework for the workshop manufacturing system via digital twin | C7: ='citations-it1-studies'!$C9 -> 2021 | D7: ='citations-it1-studies'!$H9 -> 14 | E7: O | L7: X | M7: X | N7: =IF(COUNTIF(F7:M7,"X")>0,"Exclude",IF(UPPER(TRIM(E7))="O","Include","")) -> Exclude | O7: no clear protocol focus | U7: Number included: | V7: =COUNTIF(N2:N1948,"Include") -> 24 | W7: =((V7/V5)) -> 0.071641791 | Y7: Number included: | Z7: =COUNTIFS($M2:$M1948,"<>X",$E2:$E1948,"O") -> 51 | AA7: =((Z7/Z5)) -> 0.15223881 | AC7: Number included: | AD7: =COUNTIFS($N2:$N1948,"Include", $M2:$M1948,"<>X") -> 24 | AE7: =((AD7/AD5)) -> 0.47058824
A8: Citations | B8: =HYPERLINK('citations-it1-studies'!$D10,'citations-it1-studies'!$B10) -> Communication and Coordination for Multi AGVs Based on MQTT Protocol | C8: ='citations-it1-studies'!$C10 -> 2023 | D8: ='citations-it1-studies'!$H10 -> 6 | E8: O | H8: X | M8: X | N8: =IF(COUNTIF(F8:M8,"X")>0,"Exclude",IF(UPPER(TRIM(E8))="O","Include","")) -> Exclude | O8: not clearly industrial automation context | U8: Type violation: | Y8: Type violation: | AC8: Type violation:
A9: Citations | B9: =HYPERLINK('citations-it1-studies'!$D11,'citations-it1-studies'!$B11) -> QoSmart-IoT: Secure QoS-Based Reconfiguration and Protocol Adaptation for Hybrid Clustered IoT Systems in Constrained Environments | C9: ='citations-it1-studies'!$C11 -> 2025 | D9: ='citations-it1-studies'!$H11 -> 13 | E9: O | H9: X | M9: X | N9: =IF(COUNTIF(F9:M9,"X")>0,"Exclude",IF(UPPER(TRIM(E9))="O","Include","")) -> Exclude | O9: not clearly industrial automation context | U9: EC1 | V9: =COUNTIF($F$2:$F$1948,"X") -> 2 | W9: =((V9/V$5)) -> 0.0059701493 | Y9: EC1 | Z9: =COUNTIFS($F2:$F1948,"X", $M2:$M1948,"X") -> 0 | AA9: =((Z9/Z$5)) -> 0 | AC9: EC1 | AD9: =COUNTIFS($F2:$F1948,"X", $M2:$M1948,"<>X") -> 2 | AE9: =((AD9/AD$5)) -> 0.039215686
A10: Citations | B10: =HYPERLINK('citations-it1-studies'!$D12,'citations-it1-studies'!$B12) -> APT Adversarial Defence Mechanism for Industrial IoT Enabled Cyber-Physical System | C10: ='citations-it1-studies'!$C12 -> 2023 | D10: ='citations-it1-studies'!$H12 -> 21 | E10: O | L10: X | M10: X | N10: =IF(COUNTIF(F10:M10,"X")>0,"Exclude",IF(UPPER(TRIM(E10))="O","Include","")) -> Exclude | O10: no clear protocol focus | U10: EC2 | V10: =COUNTIF($G$2:$G$1948,"X") -> 1 | W10: =((V10/V$5)) -> 0.0029850746 | Y10: EC2 | Z10: =COUNTIFS($G2:$G1948,"X", $M2:$M1948,"X") -> 1 | AA10: =((Z10/Z$5)) -> 0.0029850746 | AC10: EC2 | AD10: =COUNTIFS($G2:$G1948,"X", $M2:$M1948,"<>X") -> 0 | AE10: =((AD10/AD$5)) -> 0
A11: Citations | B11: =HYPERLINK('citations-it1-studies'!$D13,'citations-it1-studies'!$B13) -> Secure Communication Protocols: Safeguarding Information in The Digital Age | C11: ='citations-it1-studies'!$C13 -> 2025 | D11: ='citations-it1-studies'!$H13 -> 65 | E11: O | H11: X | M11: X | N11: =IF(COUNTIF(F11:M11,"X")>0,"Exclude",IF(UPPER(TRIM(E11))="O","Include","")) -> Exclude | O11: not clearly industrial automation context | U11: EC3 | V11: =COUNTIF($H$2:$H$1948,"X") -> 124 | W11: =((V11/V$5)) -> 0.37014925 | Y11: EC3 | Z11: =COUNTIFS($H2:$H1948,"X", $M2:$M1948,"X") -> 120 | AA11: =((Z11/Z$5)) -> 0.35820896 | AC11: EC3 | AD11: =COUNTIFS($H2:$H1948,"X", $M2:$M1948,"<>X") -> 4 | AE11: =((AD11/AD$5)) -> 0.078431373
A12: Citations | B12: =HYPERLINK('citations-it1-studies'!$D14,'citations-it1-studies'!$B14) -> IBAM: IPFS and Blockchain based Authentication for MQTT protocol in IoT | C12: ='citations-it1-studies'!$C14 -> 2023 | D12: ='citations-it1-studies'!$H14 -> 6 | E12: O | H12: X | M12: X | N12: =IF(COUNTIF(F12:M12,"X")>0,"Exclude",IF(UPPER(TRIM(E12))="O","Include","")) -> Exclude | O12: not clearly industrial automation context | U12: EC4 | V12: =COUNTIF($I$2:$I$1948,"X") -> 37 | W12: =((V12/V$5)) -> 0.11044776 | Y12: EC4 | Z12: =COUNTIFS($I2:$I1948,"X", $M2:$M1948,"X") -> 37 | AA12: =((Z12/Z$5)) -> 0.11044776 | AC12: EC4 | AD12: =COUNTIFS($I2:$I1948,"X", $M2:$M1948,"<>X") -> 0 | AE12: =((AD12/AD$5)) -> 0
A13: Citations | B13: =HYPERLINK('citations-it1-studies'!$D15,'citations-it1-studies'!$B15) -> Integration of MQTT and CoAP Protocols in OneM2M for IoT Applications | C13: ='citations-it1-studies'!$C15 -> 2025 | D13: ='citations-it1-studies'!$H15 -> 11 | E13: O | H13: X | M13: X | N13: =IF(COUNTIF(F13:M13,"X")>0,"Exclude",IF(UPPER(TRIM(E13))="O","Include","")) -> Exclude | O13: not clearly industrial automation context | U13: EC5 | V13: =COUNTIF(J$2:J$1948,"X") -> 43 | W13: =((V13/V$5)) -> 0.12835821 | Y13: EC5 | Z13: =COUNTIFS($J2:$J1948,"X", $M2:$M1948,"X") -> 43 | AA13: =((Z13/Z$5)) -> 0.12835821 | AC13: EC5 | AD13: =COUNTIFS($J2:$J1948,"X", $M2:$M1948,"<>X") -> 0 | AE13: =((AD13/AD$5)) -> 0
A14: Citations | B14: =HYPERLINK('citations-it1-studies'!$D16,'citations-it1-studies'!$B16) -> MECInOT: a multi-access edge computing and industrial internet of things emulator for the modelling and study of cybersecurity threats | C14: ='citations-it1-studies'!$C16 -> 2023 | D14: ='citations-it1-studies'!$H16 -> 39 | E14: O | L14: X | N14: =IF(COUNTIF(F14:M14,"X")>0,"Exclude",IF(UPPER(TRIM(E14))="O","Include","")) -> Exclude | O14: Protocol not explicit; fails IC2 as no mention of protocols | U14: EC6 | V14: =COUNTIF($K$2:$K$1948,"X") -> 0 | W14: =((V14/V$5)) -> 0 | Y14: EC6 | Z14: =COUNTIFS($K2:$K1948,"X", $M2:$M1948,"X") -> 0 | AA14: =((Z14/Z$5)) -> 0 | AC14: EC6 | AD14: =COUNTIFS($K2:$K1948,"X", $M2:$M1948,"<>X") -> 0 | AE14: =((AD14/AD$5)) -> 0
A15: Citations | B15: =HYPERLINK('citations-it1-studies'!$D17,'citations-it1-studies'!$B17) -> Implementing Dead Letter Exchanges in MQTT and Proposing a Broker Failure Algorithm Utilizing Blockchain DNS | C15: ='citations-it1-studies'!$C17 -> 2023 | D15: ='citations-it1-studies'!$H17 -> 6 | E15: O | H15: X | M15: X | N15: =IF(COUNTIF(F15:M15,"X")>0,"Exclude",IF(UPPER(TRIM(E15))="O","Include","")) -> Exclude | O15: not clearly industrial automation context | U15: EC7 | V15: =COUNTIF($L$2:$L$1948,"X") -> 143 | W15: =((V15/V$5)) -> 0.42686567 | Y15: EC7 | Z15: =COUNTIFS($L2:$L1948,"X", $M2:$M1948,"X") -> 121 | AA15: =((Z15/Z$5)) -> 0.36119403 | AC15: EC7 | AD15: =COUNTIFS($L2:$L1948,"X", $M2:$M1948,"<>X") -> 22 | AE15: =((AD15/AD$5)) -> 0.43137255
A16: Citations | B16: =HYPERLINK('citations-it1-studies'!$D18,'citations-it1-studies'!$B18) -> X-IIoTID: A Connectivity-Agnostic and Device-Agnostic Intrusion Data Set for Industrial Internet of Things | C16: ='citations-it1-studies'!$C18 -> 2022 | D16: ='citations-it1-studies'!$H18 -> 16 | E16: O | L16: X | M16: X | N16: =IF(COUNTIF(F16:M16,"X")>0,"Exclude",IF(UPPER(TRIM(E16))="O","Include","")) -> Exclude | O16: no clear protocol focus | U16: Title Exclusion | V16: =COUNTIF($M$2:$M$1948,"X") -> 284 | W16: =((V16/V$5)) -> 0.84776119
A17: Citations | B17: =HYPERLINK('citations-it1-studies'!$D19,'citations-it1-studies'!$B19) -> Intelligent Monitoring and Control Systems for Smart Water Management | C17: ='citations-it1-studies'!$C19 -> 2025 | D17: ='citations-it1-studies'!$H19 -> 22 | E17: O | H17: X | M17: X | N17: =IF(COUNTIF(F17:M17,"X")>0,"Exclude",IF(UPPER(TRIM(E17))="O","Include","")) -> Exclude | O17: not clearly industrial automation context
A18: Citations | B18: =HYPERLINK('citations-it1-studies'!$D20,'citations-it1-studies'!$B20) -> Multisensory Fusion, Haptic, and Visual Feedback Teleoperation System Under IoT Framework | C18: ='citations-it1-studies'!$C20 -> 2022 | D18: ='citations-it1-studies'!$H20 -> 11 | E18: O | H18: X | M18: X | N18: =IF(COUNTIF(F18:M18,"X")>0,"Exclude",IF(UPPER(TRIM(E18))="O","Include","")) -> Exclude | O18: not clearly industrial automation context
A19: Citations | B19: =HYPERLINK('citations-it1-studies'!$D21,'citations-it1-studies'!$B21) -> Transfer Fuzzy Learning enabled Streebog Cryptographic Substitution Permutation based zero trust security in IIOT | C19: ='citations-it1-studies'!$C21 -> 2023 | D19: ='citations-it1-studies'!$H21 -> 11 | E19: O | L19: X | M19: X | N19: =IF(COUNTIF(F19:M19,"X")>0,"Exclude",IF(UPPER(TRIM(E19))="O","Include","")) -> Exclude | O19: no clear protocol focus
A20: Citations | B20: =HYPERLINK('citations-it1-studies'!$D22,'citations-it1-studies'!$B22) -> High Precision Open Laboratory 3D Positioning System for Automated Underwater Measurements | C20: ='citations-it1-studies'!$C22 -> 2021 | D20: ='citations-it1-studies'!$H22 -> 5 | E20: O | H20: X | M20: X | N20: =IF(COUNTIF(F20:M20,"X")>0,"Exclude",IF(UPPER(TRIM(E20))="O","Include","")) -> Exclude | O20: not clearly industrial automation context
A21: Citations | B21: =HYPERLINK('citations-it1-studies'!$D23,'citations-it1-studies'!$B23) -> Architecture for data-centric and semantic-enhanced industrial metaverse: Bridging physical factories and virtual landscape | C21: ='citations-it1-studies'!$C23 -> 2024 | D21: ='citations-it1-studies'!$H23 -> 15 | E21: O | L21: X | M21: X | N21: =IF(COUNTIF(F21:M21,"X")>0,"Exclude",IF(UPPER(TRIM(E21))="O","Include","")) -> Exclude | O21: no clear protocol focus
A22: Citations | B22: =HYPERLINK('citations-it1-studies'!$D24,'citations-it1-studies'!$B24) -> Developing a Low-cost SCADA System for Industrial Application | C22: ='citations-it1-studies'!$C24 -> 2022 | D22: ='citations-it1-studies'!$H24 -> 6 | E22: O | L22: X | M22: X | N22: =IF(COUNTIF(F22:M22,"X")>0,"Exclude",IF(UPPER(TRIM(E22))="O","Include","")) -> Exclude | O22: no clear protocol focus
A23: Citations | B23: =HYPERLINK('citations-it1-studies'!$D25,'citations-it1-studies'!$B25) -> Evaluating Real-Time Ethernet performance indicators for SERCOS III networks | C23: ='citations-it1-studies'!$C25 -> 2021 | D23: ='citations-it1-studies'!$H25 -> 7 | E23: O | N23: =IF(COUNTIF(F23:M23,"X")>0,"Exclude",IF(UPPER(TRIM(E23))="O","Include","")) -> Include | O23: Meets IC1–IC4 based on title! Proposes an “analysis structure / method” using performance indicators
A24: Citations | B24: =HYPERLINK('citations-it1-studies'!$D27,'citations-it1-studies'!$B27) -> Cloud-Fog Automation: The New Paradigm Toward Autonomous Industrial Cyber-Physical Systems | C24: ='citations-it1-studies'!$C27 -> 2025 | D24: ='citations-it1-studies'!$H27 -> 21 | E24: O | L24: X | M24: X | N24: =IF(COUNTIF(F24:M24,"X")>0,"Exclude",IF(UPPER(TRIM(E24))="O","Include","")) -> Exclude | O24: no clear protocol focus
A25: Citations | B25: =HYPERLINK('citations-it1-studies'!$D28,'citations-it1-studies'!$B28) -> Integrating Fieldbus and Data-Centric Middleware: An STM32 Modbus Master Gateway for DDS-Based IIoT Systems | C25: ='citations-it1-studies'!$C28 -> 2025 | D25: ='citations-it1-studies'!$H28 -> 0 | E25: O | I25: X | L25: X | M25: X | N25: =IF(COUNTIF(F25:M25,"X")>0,"Exclude",IF(UPPER(TRIM(E25))="O","Include","")) -> Exclude | O25: likely not protocol evaluation focus
A26: Citations | B26: =HYPERLINK('citations-it1-studies'!$D29,'citations-it1-studies'!$B29) -> Online Compensation Method for Contour Error in the Parallel Module of a Hybrid Gantry Machining Center | C26: ='citations-it1-studies'!$C29 -> 2025 | D26: ='citations-it1-studies'!$H29 -> 0 | E26: O | H26: X | I26: X | M26: X | N26: =IF(COUNTIF(F26:M26,"X")>0,"Exclude",IF(UPPER(TRIM(E26))="O","Include","")) -> Exclude | O26: not clearly industrial automation context
A27: Citations | B27: =HYPERLINK('citations-it1-studies'!$D30,'citations-it1-studies'!$B30) -> RAPTOR: Advanced Persistent Threat Detection in Industrial IoT via Attack Stage Correlation | C27: ='citations-it1-studies'!$C30 -> 2023 | D27: ='citations-it1-studies'!$H30 -> 12 | E27: O | L27: X | M27: X | N27: =IF(COUNTIF(F27:M27,"X")>0,"Exclude",IF(UPPER(TRIM(E27))="O","Include","")) -> Exclude | O27: no clear protocol focus
A28: Citations | B28: =HYPERLINK('citations-it1-studies'!$D31,'citations-it1-studies'!$B31) -> Improving Security and Preventing Cyber Attacks in Smart Device Networks | C28: ='citations-it1-studies'!$C31 -> 2025 | D28: ='citations-it1-studies'!$H31 -> 6 | E28: O | H28: X | M28: X | N28: =IF(COUNTIF(F28:M28,"X")>0,"Exclude",IF(UPPER(TRIM(E28))="O","Include","")) -> Exclude | O28: not clearly industrial automation context
A29: Citations | B29: =HYPERLINK('citations-it1-studies'!$D32,'citations-it1-studies'!$B32) -> KOTO: A Kubernetes-Based Platform for Secure and Scalable OT Orchestration in Industry 5.0 | C29: ='citations-it1-studies'!$C32 -> 2025 | D29: ='citations-it1-studies'!$H32 -> 6 | E29: O | L29: X | M29: X | N29: =IF(COUNTIF(F29:M29,"X")>0,"Exclude",IF(UPPER(TRIM(E29))="O","Include","")) -> Exclude | O29: no clear protocol focus
A30: Citations | B30: =HYPERLINK('citations-it1-studies'!$D33,'citations-it1-studies'!$B33) -> A Survey of Public IoT Datasets for Network Security Research | C30: ='citations-it1-studies'!$C33 -> 2023 | D30: ='citations-it1-studies'!$H33 -> 33 | E30: O | J30: X | M30: X | N30: =IF(COUNTIF(F30:M30,"X")>0,"Exclude",IF(UPPER(TRIM(E30))="O","Include","")) -> Exclude | O30: secondary study (survey/review)
A31: Citations | B31: =HYPERLINK('citations-it1-studies'!$D37,'citations-it1-studies'!$B37) -> ExaMon-X: A Predictive Maintenance Framework for Automatic Monitoring in Industrial IoT Systems | C31: ='citations-it1-studies'!$C37 -> 2023 | D31: ='citations-it1-studies'!$H37 -> 11 | E31: O | L31: X | M31: X | N31: =IF(COUNTIF(F31:M31,"X")>0,"Exclude",IF(UPPER(TRIM(E31))="O","Include","")) -> Exclude | O31: no clear protocol focus
A32: Citations | B32: =HYPERLINK('citations-it1-studies'!$D39,'citations-it1-studies'!$B39) -> Interaction of Artificial Intelligence and Machining Processes Regarding Industry 4.0 Production Systems | C32: ='citations-it1-studies'!$C39 -> 2023 | D32: ='citations-it1-studies'!$H39 -> 10 | E32: O | L32: X | M32: X | N32: =IF(COUNTIF(F32:M32,"X")>0,"Exclude",IF(UPPER(TRIM(E32))="O","Include","")) -> Exclude | O32: no clear protocol focus
A33: Citations | B33: =HYPERLINK('citations-it1-studies'!$D40,'citations-it1-studies'!$B40) -> The Influence of Choosing Sensor Locations Inside Closed Facilities on the Reliability, Adaptability, and Energy Efficiency of IoT Systems | C33: ='citations-it1-studies'!$C40 -> 2024 | D33: ='citations-it1-studies'!$H40 -> 6 | E33: O | H33: X | M33: X | N33: =IF(COUNTIF(F33:M33,"X")>0,"Exclude",IF(UPPER(TRIM(E33))="O","Include","")) -> Exclude | O33: not clearly industrial automation context
A34: Citations | B34: =HYPERLINK('citations-it1-studies'!$D41,'citations-it1-studies'!$B41) -> Messaging Protocols for IoT Systems-A Pragmatic Comparison. | C34: ='citations-it1-studies'!$C41 -> 2021 | D34: ='citations-it1-studies'!$H41 -> 0 | E34: O | H34: X | I34: X | M34: X | N34: =IF(COUNTIF(F34:M34,"X")>0,"Exclude",IF(UPPER(TRIM(E34))="O","Include","")) -> Exclude | O34: not clearly industrial automation context
A35: Citations | B35: =HYPERLINK('citations-it1-studies'!$D42,'citations-it1-studies'!$B42) -> Deep Learning-Based Intrusion Detection for Distributed Denial of Service Attack in Agriculture 4.0 | C35: ='citations-it1-studies'!$C42 -> 2021 | D35: ='citations-it1-studies'!$H42 -> 0 | E35: O | I35: X | L35: X | M35: X | N35: =IF(COUNTIF(F35:M35,"X")>0,"Exclude",IF(UPPER(TRIM(E35))="O","Include","")) -> Exclude | O35: IDS/ML/dataset focus, not protocol evaluation
A36: Citations | B36: =HYPERLINK('citations-it1-studies'!$D44,'citations-it1-studies'!$B44) -> Enhancing Cybersecurity in Industrial Internet of Things: Machine Learning-Based Approaches for Cyber-Attack Detection in a Realworld Testbed Environment | C36: ='citations-it1-studies'!$C44 -> 2025 | D36: ='citations-it1-studies'!$H44 -> 14 | E36: O | L36: X | N36: =IF(COUNTIF(F36:M36,"X")>0,"Exclude",IF(UPPER(TRIM(E36))="O","Include","")) -> Exclude | O36: the testbed exists to validate ML-based attack detection and generate a dataset, not to evaluate communication protocols or provide a reusable protocol evaluation framework.
A37: Citations | B37: =HYPERLINK('citations-it1-studies'!$D45,'citations-it1-studies'!$B45) -> Wireless Cyber-Physical Systems Performance Evaluation through a Graph Database Approach. | C37: ='citations-it1-studies'!$C45 -> 2020 | D37: ='citations-it1-studies'!$H45 -> 19 | E37: O | H37: X | M37: X | N37: =IF(COUNTIF(F37:M37,"X")>0,"Exclude",IF(UPPER(TRIM(E37))="O","Include","")) -> Exclude | O37: not clearly industrial automation context
A38: Citations | B38: =HYPERLINK('citations-it1-studies'!$D46,'citations-it1-studies'!$B46) -> Orchestrating Embodied Systems through the Embodied Context Protocol: Motivation, Progress, and Directions. | C38: ='citations-it1-studies'!$C46 -> 2025 | D38: ='citations-it1-studies'!$H46 -> 0 | E38: O | H38: X | I38: X | M38: X | N38: =IF(COUNTIF(F38:M38,"X")>0,"Exclude",IF(UPPER(TRIM(E38))="O","Include","")) -> Exclude | O38: not clearly industrial automation context
A39: Citations | B39: =HYPERLINK('citations-it1-studies'!$D47,'citations-it1-studies'!$B47) -> Functioning and Development of a Real-Time Information System for the Oil Treatment Technological Process Control | C39: ='citations-it1-studies'!$C47 -> 2020 | D39: ='citations-it1-studies'!$H47 -> 6 | E39: O | H39: X | M39: X | N39: =IF(COUNTIF(F39:M39,"X")>0,"Exclude",IF(UPPER(TRIM(E39))="O","Include","")) -> Exclude | O39: not clearly industrial automation context
A40: Citations | B40: =HYPERLINK('citations-it1-studies'!$D48,'citations-it1-studies'!$B48) -> OPC UA PubSub and Industrial Controller Redundancy | C40: ='citations-it1-studies'!$C48 -> 2024 | D40: ='citations-it1-studies'!$H48 -> 8 | E40: O | L40: X | M40: X | N40: =IF(COUNTIF(F40:M40,"X")>0,"Exclude",IF(UPPER(TRIM(E40))="O","Include","")) -> Exclude | O40: likely not protocol evaluation focus
A41: Citations | B41: =HYPERLINK('citations-it1-studies'!$D49,'citations-it1-studies'!$B49) -> Evaluation of quality of service parameters for MQTT communication in IoT application by using deep neural network | C41: ='citations-it1-studies'!$C49 -> 2023 | D41: ='citations-it1-studies'!$H49 -> 14 | E41: O | H41: X | M41: X | N41: =IF(COUNTIF(F41:M41,"X")>0,"Exclude",IF(UPPER(TRIM(E41))="O","Include","")) -> Exclude | O41: not clearly industrial automation context
A42: Citations | B42: =HYPERLINK('citations-it1-studies'!$D50,'citations-it1-studies'!$B50) -> Game Theoretic Feedback Control for Reliability Enhancement of EtherCAT-Based Networked Systems | C42: ='citations-it1-studies'!$C50 -> 2019 | D42: ='citations-it1-studies'!$H50 -> 12 | E42: O | L42: X | M42: X | N42: =IF(COUNTIF(F42:M42,"X")>0,"Exclude",IF(UPPER(TRIM(E42))="O","Include","")) -> Exclude | O42: likely not protocol evaluation focus
A43: Citations | B43: =HYPERLINK('citations-it1-studies'!$D51,'citations-it1-studies'!$B51) -> Centralized controlling of distributed PV systems using cloud and IoT technologies | C43: ='citations-it1-studies'!$C51 -> 2023 | D43: ='citations-it1-studies'!$H51 -> 6 | E43: O | H43: X | M43: X | N43: =IF(COUNTIF(F43:M43,"X")>0,"Exclude",IF(UPPER(TRIM(E43))="O","Include","")) -> Exclude | O43: not clearly industrial automation context
A44: Citations | B44: =HYPERLINK('citations-it1-studies'!$D52,'citations-it1-studies'!$B52) -> A Thorough Analysis and Comparison of Data Communication Protocols Used in Industry 4.0: the Case of Smart-CNC | C44: ='citations-it1-studies'!$C52 -> 2022 | D44: ='citations-it1-studies'!$H52 -> 8 | E44: O | L44: X | N44: =IF(COUNTIF(F44:M44,"X")>0,"Exclude",IF(UPPER(TRIM(E44))="O","Include","")) -> Exclude | O44: Primary objective isn’t the experimental/theoretical evaluation of protocols or improving evaluation methods. It’s mainly a structured comparison to pick a protocol for Smart-CNC.
A45: Citations | B45: =HYPERLINK('citations-it1-studies'!$D53,'citations-it1-studies'!$B53) -> Redundancy for an all-in-one ISA100.11a Gateway: Protocol Design and Hardware Integration | C45: ='citations-it1-studies'!$C53 -> 2019 | D45: ='citations-it1-studies'!$H53 -> 6 | E45: O | L45: X | M45: X | N45: =IF(COUNTIF(F45:M45,"X")>0,"Exclude",IF(UPPER(TRIM(E45))="O","Include","")) -> Exclude | O45: likely not protocol evaluation focus
A46: Citations | B46: =HYPERLINK('citations-it1-studies'!$D54,'citations-it1-studies'!$B54) -> Driving Factors Behind Adopting Virtual Testbeds for ICS Cybersecurity Education. | C46: ='citations-it1-studies'!$C54 -> 2025 | D46: ='citations-it1-studies'!$H54 -> 7 | E46: O | L46: X | M46: X | N46: =IF(COUNTIF(F46:M46,"X")>0,"Exclude",IF(UPPER(TRIM(E46))="O","Include","")) -> Exclude | O46: no clear protocol focus
A47: Citations | B47: =HYPERLINK('citations-it1-studies'!$D55,'citations-it1-studies'!$B55) -> A platform-enabled CNC within edge-cloud environments: perspectives, challenges, and potential solutions | C47: ='citations-it1-studies'!$C55 -> 2025 | D47: ='citations-it1-studies'!$H55 -> 17 | E47: O | H47: X | M47: X | N47: =IF(COUNTIF(F47:M47,"X")>0,"Exclude",IF(UPPER(TRIM(E47))="O","Include","")) -> Exclude | O47: not clearly industrial automation context
A48: Citations | B48: =HYPERLINK('citations-it1-studies'!$D56,'citations-it1-studies'!$B56) -> Voltage Regulation in Microgrids via Modulation Communication: A Distributed Output Consensus Approach | C48: ='citations-it1-studies'!$C56 -> 2025 | D48: ='citations-it1-studies'!$H56 -> 10 | E48: O | H48: X | M48: X | N48: =IF(COUNTIF(F48:M48,"X")>0,"Exclude",IF(UPPER(TRIM(E48))="O","Include","")) -> Exclude | O48: not clearly industrial automation context
A49: Citations | B49: =HYPERLINK('citations-it1-studies'!$D57,'citations-it1-studies'!$B57) -> Trustworthy and Reliable Deep Learning-based Cyberattack Detection in Industrial IoT. | C49: ='citations-it1-studies'!$C57 -> 2022 | D49: ='citations-it1-studies'!$H57 -> 9 | E49: O | L49: X | M49: X | N49: =IF(COUNTIF(F49:M49,"X")>0,"Exclude",IF(UPPER(TRIM(E49))="O","Include","")) -> Exclude | O49: IDS/ML/dataset focus, not protocol evaluation
A50: Citations | B50: =HYPERLINK('citations-it1-studies'!$D58,'citations-it1-studies'!$B58) -> Characterizing the Real-Time Communication Performance of Virtual PLC in Industrial Edge Platform | C50: ='citations-it1-studies'!$C58 -> 2025 | D50: ='citations-it1-studies'!$H58 -> 11 | E50: O | N50: =IF(COUNTIF(F50:M50,"X")>0,"Exclude",IF(UPPER(TRIM(E50))="O","Include","")) -> Include | O50: It proposes a methodology for comparison, with: defined performance metrics a standardised experimental setup an analytical model to support simulation/digital twin use
A51: Citations | B51: =HYPERLINK('citations-it1-studies'!$D60,'citations-it1-studies'!$B60) -> A Hybrid VLC/RF Parking Automation System | C51: ='citations-it1-studies'!$C60 -> 2023 | D51: ='citations-it1-studies'!$H60 -> 19 | E51: O | L51: X | M51: X | N51: =IF(COUNTIF(F51:M51,"X")>0,"Exclude",IF(UPPER(TRIM(E51))="O","Include","")) -> Exclude | O51: no clear protocol focus
A52: Citations | B52: =HYPERLINK('citations-it1-studies'!$D62,'citations-it1-studies'!$B62) -> A Novel Industrial Software Model for Social Manufacturing | C52: ='citations-it1-studies'!$C62 -> 2024 | D52: ='citations-it1-studies'!$H62 -> 0 | E52: O | I52: X | L52: X | M52: X | N52: =IF(COUNTIF(F52:M52,"X")>0,"Exclude",IF(UPPER(TRIM(E52))="O","Include","")) -> Exclude | O52: no clear protocol focus
A53: Citations | B53: =HYPERLINK('citations-it1-studies'!$D63,'citations-it1-studies'!$B63) -> A Systematic Review of Recent Advances in IoT-Based Sensor Networks for Warehouse Management | C53: ='citations-it1-studies'!$C63 -> 2025 | D53: ='citations-it1-studies'!$H63 -> 0 | E53: O | I53: X | J53: X | M53: X | N53: =IF(COUNTIF(F53:M53,"X")>0,"Exclude",IF(UPPER(TRIM(E53))="O","Include","")) -> Exclude | O53: secondary study (survey/review)
A54: Citations | B54: =HYPERLINK('citations-it1-studies'!$D65,'citations-it1-studies'!$B65) -> Blake-2s based Improved Authentication Scheme for IEC 61850 GOOSE Messages | C54: ='citations-it1-studies'!$C65 -> 2025 | D54: ='citations-it1-studies'!$H65 -> 6 | E54: O | L54: X | N54: =IF(COUNTIF(F54:M54,"X")>0,"Exclude",IF(UPPER(TRIM(E54))="O","Include","")) -> Exclude | O54: it proposes a new authentication scheme and uses a lab testbed only to validate that scheme, not to present an evaluation framework/model you can reuse across protocols.
A55: Citations | B55: =HYPERLINK('citations-it1-studies'!$D67,'citations-it1-studies'!$B67) -> Communication in collaborating construction equipment | C55: ='citations-it1-studies'!$C67 -> 2023 | D55: ='citations-it1-studies'!$H67 -> 10 | E55: O | H55: X | M55: X | N55: =IF(COUNTIF(F55:M55,"X")>0,"Exclude",IF(UPPER(TRIM(E55))="O","Include","")) -> Exclude | O55: not clearly industrial automation context
A56: Citations | B56: =HYPERLINK('citations-it1-studies'!$D68,'citations-it1-studies'!$B68) -> A Blockchain-Reinforced Federated Intrusion Detection Architecture for IIoT | C56: ='citations-it1-studies'!$C68 -> 2024 | D56: ='citations-it1-studies'!$H68 -> 13 | E56: O | L56: X | M56: X | N56: =IF(COUNTIF(F56:M56,"X")>0,"Exclude",IF(UPPER(TRIM(E56))="O","Include","")) -> Exclude | O56: IDS/ML/dataset focus, not protocol evaluation
A57: Citations | B57: =HYPERLINK('citations-it1-studies'!$D69,'citations-it1-studies'!$B69) -> OPC UA client-server connection over an ISO 11783 vehicle network | C57: ='citations-it1-studies'!$C69 -> 2023 | D57: ='citations-it1-studies'!$H69 -> 12 | E57: O | L57: X | M57: X | N57: =IF(COUNTIF(F57:M57,"X")>0,"Exclude",IF(UPPER(TRIM(E57))="O","Include","")) -> Exclude | O57: likely not protocol evaluation focus
A58: Citations | B58: =HYPERLINK('citations-it1-studies'!$D71,'citations-it1-studies'!$B71) -> WiSEE - Wireless Transmission of Sensor Data over UWB in Spacecraft Payload Networks | C58: ='citations-it1-studies'!$C71 -> 2018 | D58: ='citations-it1-studies'!$H71 -> 6 | E58: O | H58: X | M58: X | N58: =IF(COUNTIF(F58:M58,"X")>0,"Exclude",IF(UPPER(TRIM(E58))="O","Include","")) -> Exclude | O58: not clearly industrial automation context
A59: Citations | B59: =HYPERLINK('citations-it1-studies'!$D72,'citations-it1-studies'!$B72) -> The Digital Backbone of Manufacturing: A Framework for Network Protocol Selection | C59: ='citations-it1-studies'!$C72 -> 2025 | D59: ='citations-it1-studies'!$H72 -> 0 | E59: O | F59: X | N59: =IF(COUNTIF(F59:M59,"X")>0,"Exclude",IF(UPPER(TRIM(E59))="O","Include","")) -> Exclude | O59: IC1, full-text not available
A60: Citations | B60: =HYPERLINK('citations-it1-studies'!$D73,'citations-it1-studies'!$B73) -> ETFA - Clock Synchronization in Integrated TSN-EtherCAT Networks | C60: ='citations-it1-studies'!$C73 -> 2020 | D60: ='citations-it1-studies'!$H73 -> 8 | E60: O | L60: X | M60: X | N60: =IF(COUNTIF(F60:M60,"X")>0,"Exclude",IF(UPPER(TRIM(E60))="O","Include","")) -> Exclude | O60: likely not protocol evaluation focus
A61: Citations | B61: =HYPERLINK('citations-it1-studies'!$D74,'citations-it1-studies'!$B74) -> End-to-End Visual Control Framework in Wireless TSN Networks for Industrial IoT | C61: ='citations-it1-studies'!$C74 -> 2025 | D61: ='citations-it1-studies'!$H74 -> 14 | E61: O | L61: X | N61: =IF(COUNTIF(F61:M61,"X")>0,"Exclude",IF(UPPER(TRIM(E61))="O","Include","")) -> Exclude | O61: framework is for visual control application, not protocol evaluation
A62: Citations | B62: =HYPERLINK('citations-it1-studies'!$D75,'citations-it1-studies'!$B75) -> Beyond the Virtual PLC Networking Constraints: MACvLAN Approach in Industrial Environments | C62: ='citations-it1-studies'!$C75 -> 2025 | D62: ='citations-it1-studies'!$H75 -> 6 | E62: O | L62: X | M62: X | N62: =IF(COUNTIF(F62:M62,"X")>0,"Exclude",IF(UPPER(TRIM(E62))="O","Include","")) -> Exclude | O62: no clear protocol focus
A63: Citations | B63: =HYPERLINK('citations-it1-studies'!$D76,'citations-it1-studies'!$B76) -> A Study on 28 GHz Power Amplifiers for Industrial Revolution 4.0 Compatible 5G NR FR2 IoT Transceivers | C63: ='citations-it1-studies'!$C76 -> 2023 | D63: ='citations-it1-studies'!$H76 -> 6 | E63: O | L63: X | M63: X | N63: =IF(COUNTIF(F63:M63,"X")>0,"Exclude",IF(UPPER(TRIM(E63))="O","Include","")) -> Exclude | O63: no clear protocol focus
A64: Citations | B64: =HYPERLINK('citations-it1-studies'!$D78,'citations-it1-studies'!$B78) -> Asset Management Method of Industrial IoT Systems for Cyber-Security Countermeasures | C64: ='citations-it1-studies'!$C78 -> 2021 | D64: ='citations-it1-studies'!$H78 -> 0 | E64: O | I64: X | L64: X | M64: X | N64: =IF(COUNTIF(F64:M64,"X")>0,"Exclude",IF(UPPER(TRIM(E64))="O","Include","")) -> Exclude | O64: no clear protocol focus
A65: Citations | B65: =HYPERLINK('citations-it1-studies'!$D79,'citations-it1-studies'!$B79) -> A threat intelligence framework for protecting smart satellite-based healthcare networks | C65: ='citations-it1-studies'!$C79 -> 2021 | D65: ='citations-it1-studies'!$H79 -> 21 | E65: O | H65: X | M65: X | N65: =IF(COUNTIF(F65:M65,"X")>0,"Exclude",IF(UPPER(TRIM(E65))="O","Include","")) -> Exclude | O65: not clearly industrial automation context
A66: Citations | B66: =HYPERLINK('citations-it1-studies'!$D80,'citations-it1-studies'!$B80) -> Performance Analysis of OPC UA for Industrial Interoperability towards Industry 4.0 | C66: ='citations-it1-studies'!$C80 -> 2022 | D66: ='citations-it1-studies'!$H80 -> 19 | E66: O | N66: =IF(COUNTIF(F66:M66,"X")>0,"Exclude",IF(UPPER(TRIM(E66))="O","Include","")) -> Include | O66: Meets IC1–IC4 based on title!proposes an "architectural system framework" and a "cost-effective testbed setup" for OPC UA performance evaluation.
A67: Citations | B67: =HYPERLINK('citations-it1-studies'!$D81,'citations-it1-studies'!$B81) -> Benchmark and Design Support for Demand-Oriented Cloud-Communication Architectures of Cyber-Physical Production Systems | C67: ='citations-it1-studies'!$C81 -> 2023 | D67: ='citations-it1-studies'!$H81 -> 8 | E67: O | H67: X | M67: X | N67: =IF(COUNTIF(F67:M67,"X")>0,"Exclude",IF(UPPER(TRIM(E67))="O","Include","")) -> Exclude | O67: not clearly industrial automation context
A68: Citations | B68: =HYPERLINK('citations-it1-studies'!$D82,'citations-it1-studies'!$B82) -> A Real Network Performance Analysis Testbed for Encrypted MQTT in DMS | C68: ='citations-it1-studies'!$C82 -> 2024 | D68: ='citations-it1-studies'!$H82 -> 6 | E68: O | H68: X | M68: X | N68: =IF(COUNTIF(F68:M68,"X")>0,"Exclude",IF(UPPER(TRIM(E68))="O","Include","")) -> Exclude | O68: not clearly industrial automation context
A69: Citations | B69: =HYPERLINK('citations-it1-studies'!$D83,'citations-it1-studies'!$B83) -> ДОСЛІДЖЕННЯ ЕФЕКТИВНОСТІ ВИКОРИСТАННЯ РОЗПОДІЛЕНИХ БАЗ ДАНИХ В СИСТЕМАХ IIOT | C69: ='citations-it1-studies'!$C83 -> 2022 | D69: ='citations-it1-studies'!$H83 -> 7 | E69: O | G69: X | M69: X | N69: =IF(COUNTIF(F69:M69,"X")>0,"Exclude",IF(UPPER(TRIM(E69))="O","Include","")) -> Exclude | O69: non-English title
A70: Citations | B70: =HYPERLINK('citations-it1-studies'!$D84,'citations-it1-studies'!$B84) -> Performance Evaluation of an IEEE 802.11g Network in an Industrial Environment | C70: ='citations-it1-studies'!$C84 -> 2020 | D70: ='citations-it1-studies'!$H84 -> 7 | E70: O | L70: X | N70: =IF(COUNTIF(F70:M70,"X")>0,"Exclude",IF(UPPER(TRIM(E70))="O","Include","")) -> Exclude | O70: Describes an experiment and metrics, but no reusable evaluation model/framework/testbed
A71: Citations | B71: =HYPERLINK('citations-it1-studies'!$D85,'citations-it1-studies'!$B85) -> Improving Fault Tolerance and Tackling Broker Failure in MQTT through Blockchain | C71: ='citations-it1-studies'!$C85 -> 2023 | D71: ='citations-it1-studies'!$H85 -> 6 | E71: O | H71: X | M71: X | N71: =IF(COUNTIF(F71:M71,"X")>0,"Exclude",IF(UPPER(TRIM(E71))="O","Include","")) -> Exclude | O71: not clearly industrial automation context
A72: Citations | B72: =HYPERLINK('citations-it1-studies'!$D87,'citations-it1-studies'!$B87) -> Time Sensitive Networking for Future Enabling Technologies: Overview and Measurement Issues for Metrological Characterization | C72: ='citations-it1-studies'!$C87 -> 2024 | D72: ='citations-it1-studies'!$H87 -> 6 | E72: O | J72: X | M72: X | N72: =IF(COUNTIF(F72:M72,"X")>0,"Exclude",IF(UPPER(TRIM(E72))="O","Include","")) -> Exclude | O72: secondary study (survey/review)
A73: Citations | B73: =HYPERLINK('citations-it1-studies'!$D88,'citations-it1-studies'!$B88) -> On the integration of OPC UA over Wired – Wireless Time Sensitive Networking | C73: ='citations-it1-studies'!$C88 -> 2023 | D73: ='citations-it1-studies'!$H88 -> 6 | E73: O | L73: X | M73: X | N73: =IF(COUNTIF(F73:M73,"X")>0,"Exclude",IF(UPPER(TRIM(E73))="O","Include","")) -> Exclude | O73: likely not protocol evaluation focus
A74: Citations | B74: =HYPERLINK('citations-it1-studies'!$D90,'citations-it1-studies'!$B90) -> An Innovative Digital Twin of Integrated Transportation and Power Networks for Efficient Scheduling of Autonomous Electric Vehicles | C74: ='citations-it1-studies'!$C90 -> 2024 | D74: ='citations-it1-studies'!$H90 -> 5 | E74: O | H74: X | M74: X | N74: =IF(COUNTIF(F74:M74,"X")>0,"Exclude",IF(UPPER(TRIM(E74))="O","Include","")) -> Exclude | O74: not clearly industrial automation context
A75: Citations | B75: =HYPERLINK('citations-it1-studies'!$D91,'citations-it1-studies'!$B91) -> A Comprehensive Review on 5G IIoT Test-Beds | C75: ='citations-it1-studies'!$C91 -> 2025 | D75: ='citations-it1-studies'!$H91 -> 25 | E75: O | J75: X | M75: X | N75: =IF(COUNTIF(F75:M75,"X")>0,"Exclude",IF(UPPER(TRIM(E75))="O","Include","")) -> Exclude | O75: secondary study (survey/review)
A76: Citations | B76: =HYPERLINK('citations-it1-studies'!$D93,'citations-it1-studies'!$B93) -> Implementing and using smart maintenance technologies: Introducing challenges and enablers related to human, organizational and technological perspectives | C76: ='citations-it1-studies'!$C93 -> 2025 | D76: ='citations-it1-studies'!$H93 -> 10 | E76: O | H76: X | M76: X | N76: =IF(COUNTIF(F76:M76,"X")>0,"Exclude",IF(UPPER(TRIM(E76))="O","Include","")) -> Exclude | O76: not clearly industrial automation context
A77: Citations | B77: =HYPERLINK('citations-it1-studies'!$D94,'citations-it1-studies'!$B94) -> Performance evaluation of industrial Ethernet protocols for networked control application | C77: ='citations-it1-studies'!$C94 -> 2019 | D77: ='citations-it1-studies'!$H94 -> 10 | E77: O | N77: =IF(COUNTIF(F77:M77,"X")>0,"Exclude",IF(UPPER(TRIM(E77))="O","Include","")) -> Include | O77: Meets IC1–IC4 based on title! Keep, It does sound like they build an evaluation model of delays + a simulation setup and use it as a “guideline”, but the abstract doesn’t say “framework/testbed” explicitly.
A78: Citations | B78: =HYPERLINK('citations-it1-studies'!$D95,'citations-it1-studies'!$B95) -> Comprehensive Exploration of IoT Communication Protocol: CoAP, MQTT, HTTP, LoRaWAN and AMQP | C78: ='citations-it1-studies'!$C95 -> 2024 | D78: ='citations-it1-studies'!$H95 -> 14 | E78: O | H78: X | M78: X | N78: =IF(COUNTIF(F78:M78,"X")>0,"Exclude",IF(UPPER(TRIM(E78))="O","Include","")) -> Exclude | O78: not clearly industrial automation context
A79: Citations | B79: =HYPERLINK('citations-it1-studies'!$D96,'citations-it1-studies'!$B96) -> System architecture for small‐scale personalized production lines based on industrial Internet | C79: ='citations-it1-studies'!$C96 -> 2024 | D79: ='citations-it1-studies'!$H96 -> 0 | E79: O | I79: X | L79: X | M79: X | N79: =IF(COUNTIF(F79:M79,"X")>0,"Exclude",IF(UPPER(TRIM(E79))="O","Include","")) -> Exclude | O79: no clear protocol focus
A80: Citations | B80: =HYPERLINK('citations-it1-studies'!$D98,'citations-it1-studies'!$B98) -> Encryption for Industrial Control Systems: A Survey of Application-Level and Network-Level Approaches in Smart Grids | C80: ='citations-it1-studies'!$C98 -> 2026 | D80: ='citations-it1-studies'!$H98 -> 0 | E80: O | I80: X | J80: X | M80: X | N80: =IF(COUNTIF(F80:M80,"X")>0,"Exclude",IF(UPPER(TRIM(E80))="O","Include","")) -> Exclude | O80: secondary study (survey/review)
A81: Citations | B81: =HYPERLINK('citations-it1-studies'!$D101,'citations-it1-studies'!$B101) -> Design of Cloud-Edge-Gateway Collaborative Zero-Trust Architecture and Workflow for Smart Factories | C81: ='citations-it1-studies'!$C101 -> 2024 | D81: ='citations-it1-studies'!$H101 -> 5 | E81: O | H81: X | M81: X | N81: =IF(COUNTIF(F81:M81,"X")>0,"Exclude",IF(UPPER(TRIM(E81))="O","Include","")) -> Exclude | O81: not clearly industrial automation context
A82: Citations | B82: =HYPERLINK('citations-it1-studies'!$D102,'citations-it1-studies'!$B102) -> Performance Evaluation of Application Layer IoT Protocols: MQTT and CoAP | C82: ='citations-it1-studies'!$C102 -> 2024 | D82: ='citations-it1-studies'!$H102 -> 6 | E82: O | H82: X | M82: X | N82: =IF(COUNTIF(F82:M82,"X")>0,"Exclude",IF(UPPER(TRIM(E82))="O","Include","")) -> Exclude | O82: not clearly industrial automation context
A83: Citations | B83: =HYPERLINK('citations-it1-studies'!$D103,'citations-it1-studies'!$B103) -> Mitigating 3D printing defects via cyber-physical systems: a process for fabricating defect-free components | C83: ='citations-it1-studies'!$C103 -> 2025 | D83: ='citations-it1-studies'!$H103 -> 22 | E83: O | H83: X | M83: X | N83: =IF(COUNTIF(F83:M83,"X")>0,"Exclude",IF(UPPER(TRIM(E83))="O","Include","")) -> Exclude | O83: not clearly industrial automation context
A84: Citations | B84: =HYPERLINK('citations-it1-studies'!$D104,'citations-it1-studies'!$B104) -> Environment Monitoring Subsystem Based on Recursive InterNetwork Architecture | C84: ='citations-it1-studies'!$C104 -> 2024 | D84: ='citations-it1-studies'!$H104 -> 19 | E84: O | H84: X | M84: X | N84: =IF(COUNTIF(F84:M84,"X")>0,"Exclude",IF(UPPER(TRIM(E84))="O","Include","")) -> Exclude | O84: not clearly industrial automation context
A85: Citations | B85: =HYPERLINK('citations-it1-studies'!$D105,'citations-it1-studies'!$B105) -> When the digital twin meets the preventive conservation of movable wooden artifacts | C85: ='citations-it1-studies'!$C105 -> 2023 | D85: ='citations-it1-studies'!$H105 -> 0 | E85: O | H85: X | I85: X | M85: X | N85: =IF(COUNTIF(F85:M85,"X")>0,"Exclude",IF(UPPER(TRIM(E85))="O","Include","")) -> Exclude | O85: not clearly industrial automation context
A86: Citations | B86: =HYPERLINK('citations-it1-studies'!$D106,'citations-it1-studies'!$B106) -> Deep Learning Applications for Blockchain in Industrial IoT | C86: ='citations-it1-studies'!$C106 -> 2022 | D86: ='citations-it1-studies'!$H106 -> 6 | E86: O | L86: X | M86: X | N86: =IF(COUNTIF(F86:M86,"X")>0,"Exclude",IF(UPPER(TRIM(E86))="O","Include","")) -> Exclude | O86: IDS/ML/dataset focus, not protocol evaluation
A87: Citations | B87: =HYPERLINK('citations-it1-studies'!$D107,'citations-it1-studies'!$B107) -> Edge Computing: Use Cases and Research Challenges | C87: ='citations-it1-studies'!$C107 -> 2023 | D87: ='citations-it1-studies'!$H107 -> 18 | E87: O | H87: X | M87: X | N87: =IF(COUNTIF(F87:M87,"X")>0,"Exclude",IF(UPPER(TRIM(E87))="O","Include","")) -> Exclude | O87: not clearly industrial automation context
A88: Citations | B88: =HYPERLINK('citations-it1-studies'!$D108,'citations-it1-studies'!$B108) -> Data Security and Privacy in Industrial IoT | C88: ='citations-it1-studies'!$C108 -> 2021 | D88: ='citations-it1-studies'!$H108 -> 19 | E88: O | L88: X | M88: X | N88: =IF(COUNTIF(F88:M88,"X")>0,"Exclude",IF(UPPER(TRIM(E88))="O","Include","")) -> Exclude | O88: no clear protocol focus
A89: Citations | B89: =HYPERLINK('citations-it1-studies'!$D109,'citations-it1-studies'!$B109) -> Cloud Computing for High Voltage Substation Based Relay Protection | C89: ='citations-it1-studies'!$C109 -> 2024 | D89: ='citations-it1-studies'!$H109 -> 7 | E89: O | L89: X | M89: X | N89: =IF(COUNTIF(F89:M89,"X")>0,"Exclude",IF(UPPER(TRIM(E89))="O","Include","")) -> Exclude | O89: no clear protocol focus
A90: Citations | B90: =HYPERLINK('citations-it1-studies'!$D110,'citations-it1-studies'!$B110) -> An Online Model to Minimize Energy Consumption of IoT Sensors in Smart Cities | C90: ='citations-it1-studies'!$C110 -> 2022 | D90: ='citations-it1-studies'!$H110 -> 9 | E90: O | H90: X | M90: X | N90: =IF(COUNTIF(F90:M90,"X")>0,"Exclude",IF(UPPER(TRIM(E90))="O","Include","")) -> Exclude | O90: not clearly industrial automation context
A91: Citations | B91: =HYPERLINK('citations-it1-studies'!$D111,'citations-it1-studies'!$B111) -> Model of a Device-Level Combined Wireless Network Based on NB-IoT and IEEE 802.15.4 Standards for Low-Power Applications in a Diverse IoT Framework. | C91: ='citations-it1-studies'!$C111 -> 2021 | D91: ='citations-it1-studies'!$H111 -> 0 | E91: O | H91: X | I91: X | M91: X | N91: =IF(COUNTIF(F91:M91,"X")>0,"Exclude",IF(UPPER(TRIM(E91))="O","Include","")) -> Exclude | O91: not clearly industrial automation context
A92: Citations | B92: =HYPERLINK('citations-it1-studies'!$D113,'citations-it1-studies'!$B113) -> Joint Security-Reliability Performance Optimization in Low-Latency Industrial IoT Networks | C92: ='citations-it1-studies'!$C113 -> 2025 | D92: ='citations-it1-studies'!$H113 -> 5 | E92: O | L92: X | N92: =IF(COUNTIF(F92:M92,"X")>0,"Exclude",IF(UPPER(TRIM(E92))="O","Include","")) -> Exclude | O92: It does not propose a protocol evaluation model/framework/testbed. It proposes an optimisation method for security–reliability trade-offs.
A93: Citations | B93: =HYPERLINK('citations-it1-studies'!$D114,'citations-it1-studies'!$B114) -> Identifying key attacks on an IEEE 9-Bus System by leveraging the MITRE ATT&CK ICS Matrix | C93: ='citations-it1-studies'!$C114 -> 2025 | D93: ='citations-it1-studies'!$H114 -> 8 | E93: O | L93: X | M93: X | N93: =IF(COUNTIF(F93:M93,"X")>0,"Exclude",IF(UPPER(TRIM(E93))="O","Include","")) -> Exclude | O93: no clear protocol focus
A94: Citations | B94: =HYPERLINK('citations-it1-studies'!$D116,'citations-it1-studies'!$B116) -> Engineering Interoperable, Plug-and-Play, Distributed, Robotic Control Systems for Futureproof Fusion Power Plants | C94: ='citations-it1-studies'!$C116 -> 2021 | D94: ='citations-it1-studies'!$H116 -> 0 | E94: O | H94: X | I94: X | M94: X | N94: =IF(COUNTIF(F94:M94,"X")>0,"Exclude",IF(UPPER(TRIM(E94))="O","Include","")) -> Exclude | O94: not clearly industrial automation context
A95: Citations | B95: =HYPERLINK('citations-it1-studies'!$D117,'citations-it1-studies'!$B117) -> Cybersecurity Testbeds for IoT: A Systematic Literature Review and Taxonomy | C95: ='citations-it1-studies'!$C117 -> 2024 | D95: ='citations-it1-studies'!$H117 -> 24 | E95: O | J95: X | M95: X | N95: =IF(COUNTIF(F95:M95,"X")>0,"Exclude",IF(UPPER(TRIM(E95))="O","Include","")) -> Exclude | O95: secondary study (survey/review)
A96: Citations | B96: =HYPERLINK('citations-it1-studies'!$D118,'citations-it1-studies'!$B118) -> A systematic literature review: Messaging protocols and electronic platforms used in the internet of things for the purpose of building smart homes | C96: ='citations-it1-studies'!$C118 -> 2023 | D96: ='citations-it1-studies'!$H118 -> 10 | E96: O | J96: X | M96: X | N96: =IF(COUNTIF(F96:M96,"X")>0,"Exclude",IF(UPPER(TRIM(E96))="O","Include","")) -> Exclude | O96: secondary study (survey/review)
A97: Citations | B97: =HYPERLINK('citations-it1-studies'!$D119,'citations-it1-studies'!$B119) -> Data-Based Process Monitoring for Structural Bonding of Fiber-Reinforced Thermoplastics in Aviation | C97: ='citations-it1-studies'!$C119 -> 2025 | D97: ='citations-it1-studies'!$H119 -> 6 | E97: O | H97: X | M97: X | N97: =IF(COUNTIF(F97:M97,"X")>0,"Exclude",IF(UPPER(TRIM(E97))="O","Include","")) -> Exclude | O97: not clearly industrial automation context
A98: Citations | B98: =HYPERLINK('citations-it1-studies'!$D120,'citations-it1-studies'!$B120) -> Smart Tree: An Architectural, Greening and ICT Multidisciplinary Approach to Smart Campus Environments. | C98: ='citations-it1-studies'!$C120 -> 2021 | D98: ='citations-it1-studies'!$H120 -> 0 | E98: O | H98: X | I98: X | M98: X | N98: =IF(COUNTIF(F98:M98,"X")>0,"Exclude",IF(UPPER(TRIM(E98))="O","Include","")) -> Exclude | O98: not clearly industrial automation context
A99: Citations | B99: =HYPERLINK('citations-it1-studies'!$D121,'citations-it1-studies'!$B121) -> The Nexus Between Digital Transformation and Economic Efficiency: Evidence from Selected Countries | C99: ='citations-it1-studies'!$C121 -> 2023 | D99: ='citations-it1-studies'!$H121 -> 10 | E99: O | H99: X | M99: X | N99: =IF(COUNTIF(F99:M99,"X")>0,"Exclude",IF(UPPER(TRIM(E99))="O","Include","")) -> Exclude | O99: not clearly industrial automation context
A100: Citations | B100: =HYPERLINK('citations-it1-studies'!$D123,'citations-it1-studies'!$B123) -> Methods and means of conflict-free data exchange in the group of mobile robotic platforms | C100: ='citations-it1-studies'!$C123 -> 2024 | D100: ='citations-it1-studies'!$H123 -> 11 | E100: O | H100: X | M100: X | N100: =IF(COUNTIF(F100:M100,"X")>0,"Exclude",IF(UPPER(TRIM(E100))="O","Include","")) -> Exclude | O100: not clearly industrial automation context
...

Sheet Snowballing-it1-fultxtscreening
A1: Source | B1: Title | C1: Year | D1: Number of pages | E1: Done (mark with 'O') | F1: IC1 | G1: IC2 | H1: IC3 | I1: IC4 | J1: IC5 | K1: EC1 | L1: EC2 | M1: EC3 | N1: EC4 | O1: EC5 | P1: EC6 | Q1: EC7 | R1: Decision | S1: Motivation
A2: Citations | B2: =HYPERLINK('citations-it1-studies'!$D25,'citations-it1-studies'!$B25) -> Evaluating Real-Time Ethernet performance indicators for SERCOS III networks | C2: ='citations-it1-studies'!$C25 -> 2021 | D2: ='citations-it1-studies'!$H25 -> 7 | E2: O | F2: X | G2: X | H2: X | I2: X | J2: X | N2: =IF(AND(D2>=1, D2<=4), "X", "") | R2: =IF(AND(OR(COUNTIF(K2:Q2,"X")>0,COUNTIF(F2:J2,"X")<>5),UPPER(TRIM(E2))="O"),"Exclude",IF(UPPER(TRIM(E2))="O","Include","")) -> Include | S2: defines/evaluates real-time Ethernet performance indicators (method + evaluation).
A3: Citations | B3: =HYPERLINK('citations-it1-studies'!$D58,'citations-it1-studies'!$B58) -> Characterizing the Real-Time Communication Performance of Virtual PLC in Industrial Edge Platform | C3: ='citations-it1-studies'!$C58 -> 2025 | D3: ='citations-it1-studies'!$H58 -> 11 | E3: O | F3: X | G3: X | H3: X | I3: X | J3: X | N3: =IF(AND(D3>=1, D3<=4), "X", "") | R3: =IF(AND(OR(COUNTIF(K3:Q3,"X")>0,COUNTIF(F3:J3,"X")<>5),UPPER(TRIM(E3))="O"),"Exclude",IF(UPPER(TRIM(E3))="O","Include","")) -> Include | S3: characterizes real-time comm performance for virtual PLC setups.
A4: Citations | B4: =HYPERLINK('citations-it1-studies'!$D80,'citations-it1-studies'!$B80) -> Performance Analysis of OPC UA for Industrial Interoperability towards Industry 4.0 | C4: ='citations-it1-studies'!$C80 -> 2022 | D4: ='citations-it1-studies'!$H80 -> 19 | E4: O | F4: X | G4: X | I4: X | J4: X | N4: =IF(AND(D4>=1, D4<=4), "X", "") | R4: =IF(AND(OR(COUNTIF(K4:Q4,"X")>0,COUNTIF(F4:J4,"X")<>5),UPPER(TRIM(E4))="O"),"Exclude",IF(UPPER(TRIM(E4))="O","Include","")) -> Exclude | S4: performance analysis/evaluation of OPC UA, but does not contribute a reusable evaluation model, framework, testbed, or method aligned with IC3.
A5: Citations | B5: =HYPERLINK('citations-it1-studies'!$D94,'citations-it1-studies'!$B94) -> Performance evaluation of industrial Ethernet protocols for networked control application | C5: ='citations-it1-studies'!$C94 -> 2019 | D5: ='citations-it1-studies'!$H94 -> 10 | E5: O | F5: X | G5: X | I5: X | J5: X | N5: =IF(AND(D5>=1, D5<=4), "X", "") | R5: =IF(AND(OR(COUNTIF(K5:Q5,"X")>0,COUNTIF(F5:J5,"X")<>5),UPPER(TRIM(E5))="O"),"Exclude",IF(UPPER(TRIM(E5))="O","Include","")) -> Exclude | S5: compares EtherNet/IP vs EtherCAT vs PROFINET IRT for networked control.
A6: Citations | B6: =HYPERLINK('citations-it1-studies'!$D178,'citations-it1-studies'!$B178) -> Comparative Evaluation of open62541 OPC UA Servers on Embedded Devices | C6: ='citations-it1-studies'!$C178 -> 2025 | D6: ='citations-it1-studies'!$H178 -> 6 | E6: O | F6: X | G6: X | H6: X | I6: X | J6: X | M6: X | N6: =IF(AND(D6>=1, D6<=4), "X", "") | R6: =IF(AND(OR(COUNTIF(K6:Q6,"X")>0,COUNTIF(F6:J6,"X")<>5),UPPER(TRIM(E6))="O"),"Exclude",IF(UPPER(TRIM(E6))="O","Include","")) -> Exclude | S6: comparative evaluation of open62541 servers on embedded devices. Narrow benchmark of one stack on embedded targets.
A7: Citations | B7: =HYPERLINK('citations-it1-studies'!$D183,'citations-it1-studies'!$B183) -> Assessment of OPC UA PubSub at Scale Using TSN Infrastructure and Network Calculus | C7: ='citations-it1-studies'!$C183 -> 2024 | D7: ='citations-it1-studies'!$H183 -> 9 | E7: O | F7: X | G7: X | H7: X | I7: X | J7: X | N7: =IF(AND(D7>=1, D7<=4), "X", "") | Q7: X | R7: =IF(AND(OR(COUNTIF(K7:Q7,"X")>0,COUNTIF(F7:J7,"X")<>5),UPPER(TRIM(E7))="O"),"Exclude",IF(UPPER(TRIM(E7))="O","Include","")) -> Exclude | S7: evaluates OPC UA PubSub at scale + TSN/network-calculus-based analysis. benchmarking OPC UA implementations on small embedded devices for distributed measurement, not closed-loop control
A8: References | B8: =HYPERLINK('references-it1-studies'!$D14,'references-it1-studies'!$B14) -> GNS3 Communication Network Emulation for Substation GOOSE Based Protection Schemes | C8: ='references-it1-studies'!$C14 -> 2022 | D8: ='references-it1-studies'!$H14 -> 0 | E8: O | F8: X | G8: X | H8: X | I8: X | J8: X | N8: =IF(AND(D8>=1, D8<=4), "X", "") | Q8: X | R8: =IF(AND(OR(COUNTIF(K8:Q8,"X")>0,COUNTIF(F8:J8,"X")<>5),UPPER(TRIM(E8))="O"),"Exclude",IF(UPPER(TRIM(E8))="O","Include","")) -> Exclude | S8: builds a comm network model/emulation to study how the comm layer (GOOSE network) affects protection schemes
A9: References | B9: =HYPERLINK('references-it1-studies'!$D24,'references-it1-studies'!$B24) -> Simulation and Analysis of Cyber-Attack on Modbus Protocol for Smart Grids in Virtual Environment | C9: ='references-it1-studies'!$C24 -> 2023 | D9: ='references-it1-studies'!$H24 -> 0 | E9: O | F9: X | G9: X | H9: X | I9: X | N9: =IF(AND(D9>=1, D9<=4), "X", "") | R9: =IF(AND(OR(COUNTIF(K9:Q9,"X")>0,COUNTIF(F9:J9,"X")<>5),UPPER(TRIM(E9))="O"),"Exclude",IF(UPPER(TRIM(E9))="O","Include","")) -> Exclude | S9: Fails IC5, not peer-reviewed
A10: References | B10: =HYPERLINK('references-it1-studies'!$D27,'references-it1-studies'!$B27) -> MetroInd4.0&amp;IoT - Performance Comparison Between OPC UA and MQTT for Data Exchange | C10: ='references-it1-studies'!$C27 -> 2018 | D10: ='references-it1-studies'!$H27 -> 5 | E10: O | F10: X | G10: X | H10: X | I10: X | J10: X | N10: =IF(AND(D10>=1, D10<=4), "X", "") | R10: =IF(AND(OR(COUNTIF(K10:Q10,"X")>0,COUNTIF(F10:J10,"X")<>5),UPPER(TRIM(E10))="O"),"Exclude",IF(UPPER(TRIM(E10))="O","Include","")) -> Include | S10: OPC UA vs MQTT performance comparison
A11: References | B11: =HYPERLINK('references-it1-studies'!$D29,'references-it1-studies'!$B29) -> Practical Implementation of an OPC UA TSN Communication Architecture for a Manufacturing System | C11: ='references-it1-studies'!$C29 -> 2020 | D11: ='references-it1-studies'!$H29 -> 12 | E11: O | F11: X | G11: X | H11: X | I11: X | J11: X | N11: =IF(AND(D11>=1, D11<=4), "X", "") | Q11: X | R11: =IF(AND(OR(COUNTIF(K11:Q11,"X")>0,COUNTIF(F11:J11,"X")<>5),UPPER(TRIM(E11))="O"),"Exclude",IF(UPPER(TRIM(E11))="O","Include","")) -> Exclude | S11: OPC UA TSN architecture, not a reusable model for evaluating secure industrial protocols.
A12: References | B12: =HYPERLINK('references-it1-studies'!$D33,'references-it1-studies'!$B33) -> Performance of the XMPP and the MQTT Protocols on IEC 61850-Based Micro Grid Communication Architecture | C12: ='references-it1-studies'!$C33 -> 2021 | D12: ='references-it1-studies'!$H33 -> 0 | E12: O | F12: X | G12: X | H12: X | I12: X | J12: X | N12: =IF(AND(D12>=1, D12<=4), "X", "") | Q12: X | R12: =IF(AND(OR(COUNTIF(K12:Q12,"X")>0,COUNTIF(F12:J12,"X")<>5),UPPER(TRIM(E12))="O"),"Exclude",IF(UPPER(TRIM(E12))="O","Include","")) -> Exclude | S12: microgrid testbed, not focus on prtocool evaluation
A13: References | B13: =HYPERLINK('references-it1-studies'!$D55,'references-it1-studies'!$B55) -> ICPE - Bottleneck Identification and Performance Modeling of OPC UA Communication Models | C13: ='references-it1-studies'!$C55 -> 2019 | D13: ='references-it1-studies'!$H55 -> 12 | E13: O | F13: X | G13: X | H13: X | I13: X | J13: X | N13: =IF(AND(D13>=1, D13<=4), "X", "") | R13: =IF(AND(OR(COUNTIF(K13:Q13,"X")>0,COUNTIF(F13:J13,"X")<>5),UPPER(TRIM(E13))="O"),"Exclude",IF(UPPER(TRIM(E13))="O","Include","")) -> Include | S13: bottleneck identification + performance model for OPC UA (protocol eval + modeling)
